Workbook

Sheet 01_QUESTIONS_72
A1: ordre | B1: item_id | C1: dimension | D1: facette | E1: bloc | F1: question_finale | G1: item_version | H1: bank_version | I1: statut | J1: risque_hybridite | K1: risque_desirabilite | L1: risque_familiarite_sectorielle | M1: note_methodologique
A2: 1 | B2: PIP-ACT-R-R1-001 | C2: R | D2: R1 | E2: ACT | F2: Assembler plusieurs pièces pour obtenir un objet solide et utilisable. | G2: 0.6 | H2: PIP-BANK-0.5 | I2: ACTIF | J2: FAIBLE | K2: FAIBLE | L2: MOYEN | M2: Activité professionnelle formulée à l’infinitif ; réponse = degré d’envie de réaliser cette activité, indépendamment du métier actuel et de la compétence perçue.
A3: 2 | B3: PIP-ACT-R-R1-002 | C3: R | D3: R1 | E3: ACT | F3: Façonner du bois, du métal ou un autre matériau pour lui donner une forme précise et utile. | G3: 0.6 | H3: PIP-BANK-0.5 | I3: ACTIF | J3: FAIBLE | K3: FAIBLE | L3: MOYEN | M3: Activité professionnelle formulée à l’infinitif ; réponse = degré d’envie de réaliser cette activité, indépendamment du métier actuel et de la compétence perçue.
A4: 3 | B4: PIP-SIT-R-R1-003 | C4: R | D4: R1 | E4: SIT | F4: Construire concrètement une petite structure à partir d’éléments séparés. | G4: 0.6 | H4: PIP-BANK-0.5 | I4: ACTIF | J4: FAIBLE | K4: FAIBLE | L4: MOYEN | M4: Activité professionnelle formulée à l’infinitif ; réponse = degré d’envie de réaliser cette activité, indépendamment du métier actuel et de la compétence perçue.
A5: 4 | B5: PIP-ACT-R-R2-005 | C5: R | D5: R2 | E5: ACT | F5: Installer un appareil ou un équipement puis vérifier qu’il fonctionne correctement. | G5: 0.6 | H5: PIP-BANK-0.5 | I5: ACTIF | J5: FAIBLE | K5: FAIBLE | L5: MOYEN | M5: Activité professionnelle formulée à l’infinitif ; réponse = degré d’envie de réaliser cette activité, indépendamment du métier actuel et de la compétence perçue.
A6: 5 | B6: PIP-ACT-R-R2-006 | C6: R | D6: R2 | E6: ACT | F6: Rechercher la cause d’une panne puis intervenir concrètement pour remettre l’équipement en service. | G6: 0.6 | H6: PIP-BANK-0.5 | I6: ACTIF | J6: MOYEN | K6: FAIBLE | L6: MOYEN | M6: Activité professionnelle formulée à l’infinitif ; réponse = degré d’envie de réaliser cette activité, indépendamment du métier actuel et de la compétence perçue.
A7: 6 | B7: PIP-ACT-R-R3-009 | C7: R | D7: R3 | E7: ACT | F7: Utiliser directement des outils de mesure et des outils manuels pour réaliser un montage précis. | G7: 0.6 | H7: PIP-BANK-0.5 | I7: ACTIF | J7: FAIBLE | K7: FAIBLE | L7: MOYEN | M7: Activité professionnelle formulée à l’infinitif ; réponse = degré d’envie de réaliser cette activité, indépendamment du métier actuel et de la compétence perçue.
A8: 7 | B8: PIP-ACT-R-R3-010 | C8: R | D8: R3 | E8: ACT | F8: Régler une machine ou un équipement pour obtenir le résultat demandé. | G8: 0.6 | H8: PIP-BANK-0.5 | I8: ACTIF | J8: FAIBLE | K8: FAIBLE | L8: MOYEN | M8: Activité professionnelle formulée à l’infinitif ; réponse = degré d’envie de réaliser cette activité, indépendamment du métier actuel et de la compétence perçue.
A9: 8 | B9: PIP-SIT-R-R3-011 | C9: R | D9: R3 | E9: SIT | F9: Manipuler directement une machine, un appareil ou un instrument pour réaliser une opération. | G9: 0.6 | H9: PIP-BANK-0.5 | I9: ACTIF | J9: FAIBLE | K9: FAIBLE | L9: MOYEN | M9: Activité professionnelle formulée à l’infinitif ; réponse = degré d’envie de réaliser cette activité, indépendamment du métier actuel et de la compétence perçue.
A10: 9 | B10: PIP-ACT-R-R4-013 | C10: R | D10: R4 | E10: ACT | F10: Se déplacer sur le terrain pour constater une situation et intervenir sur place. | G10: 0.6 | H10: PIP-BANK-0.5 | I10: ACTIF | J10: FAIBLE | K10: FAIBLE | L10: MOYEN | M10: Activité professionnelle formulée à l’infinitif ; réponse = degré d’envie de réaliser cette activité, indépendamment du métier actuel et de la compétence perçue.
A11: 10 | B11: PIP-ACT-R-R4-014 | C11: R | D11: R4 | E11: ACT | F11: Réaliser une grande partie de son travail à l’extérieur, sur un chantier, un site ou dans un espace naturel. | G11: 0.6 | H11: PIP-BANK-0.5 | I11: ACTIF | J11: FAIBLE | K11: FAIBLE | L11: MOYEN | M11: Activité professionnelle formulée à l’infinitif ; réponse = degré d’envie de réaliser cette activité, indépendamment du métier actuel et de la compétence perçue.
A12: 11 | B12: PIP-ACT-R-R5-017 | C12: R | D12: R5 | E12: ACT | F12: Prendre soin concrètement de plantes, de cultures ou d’animaux en assurant leur entretien et leur suivi. | G12: 0.6 | H12: PIP-BANK-0.5 | I12: ACTIF | J12: MOYEN | K12: FAIBLE | L12: MOYEN | M12: Activité professionnelle formulée à l’infinitif ; réponse = degré d’envie de réaliser cette activité, indépendamment du métier actuel et de la compétence perçue.
A13: 12 | B13: PIP-ACT-R-R5-018 | C13: R | D13: R5 | E13: ACT | F13: Manipuler des matériaux, déplacer ou préparer physiquement des éléments pour réaliser une tâche utile. | G13: 0.6 | H13: PIP-BANK-0.5 | I13: ACTIF | J13: FAIBLE | K13: FAIBLE | L13: MOYEN | M13: Activité professionnelle formulée à l’infinitif ; réponse = degré d’envie de réaliser cette activité, indépendamment du métier actuel et de la compétence perçue.
... A73: 72 | B73: PIP-ACT-C-C5-018 | C73: C | D73: C5 | E73: ACT | F73: Planifier plusieurs échéances et vérifier régulièrement que les opérations prévues sont réalisées au bon moment. | G73: 0.6 | H73: PIP-BANK-0.5 | I73: ACTIF | J73: MOYEN | K73: MOYEN | L73: FAIBLE | M73: Activité professionnelle formulée à l’infinitif ; réponse = degré d’envie de réaliser cette activité, indépendamment du métier actuel et de la compétence perçue.

Sheet 02_REPONSES_CONSIGNE
A1: CLARTÉ360 — PIP RIASEC — CONSIGNE ET ÉCHELLE DE RÉPONSE
A3: Principe | B3: Le PIP mesure des intérêts professionnels. Il ne mesure ni les compétences, ni les aptitudes, ni l’intelligence, ni la personnalité.
A4: Consigne affichée | B4: Pour chacune des activités suivantes, indiquez dans quelle mesure vous aimeriez la réaliser dans votre travail. Répondez selon votre envie, et non selon ce que vous savez déjà faire, votre métier actuel ou ce que vous pensez devoir aimer.
A5: Règle de lecture | B5: Chaque item décrit une activité. La réponse exprime uniquement le degré d’attirance pour cette activité. Une réponse élevée sur une dimension secondaire enrichit le profil ; elle ne constitue jamais une injonction à changer de métier.
A7: score | B7: libellé affiché
A8: 1 | B8: Je n’aimerais pas du tout faire cela
A9: 2 | B9: J’aimerais peu faire cela
A10: 3 | B10: Je suis partagé(e) / sans préférence marquée
A11: 4 | B11: J’aimerais assez faire cela
A12: 5 | B12: J’aimerais beaucoup faire cela

Sheet 03_REVUE_HISTORIQUE
A1: ordre | B1: item_id | C1: dimension | D1: facette | E1: formulation_v0_4 | F1: formulation_v0_5_concrete | G1: formulation_finale_v0_6 | H1: decision_A1 | I1: motif_A1
A2: 1 | B2: PIP-ACT-R-R1-001 | C2: R | D2: R1 | E2: Assembler des éléments pour fabriquer un objet fonctionnel. | F2: Assembler les pièces d’un petit meuble ou d’un support pour qu’il soit solide et utilisable. | G2: Assembler plusieurs pièces pour obtenir un objet solide et utilisable. | H2: VALIDÉ_A1 | I2: Centrage explicite sur l’intérêt pour une activité professionnelle ; compatible avec la consigne « aimeriez-vous réaliser cette activité », sans présumer métier ni compétence.
A3: 2 | B3: PIP-ACT-R-R1-002 | C3: R | D3: R1 | E3: Transformer une matière ou un matériau pour lui donner une forme utile. | F3: Travailler du bois, du métal ou un autre matériau pour obtenir une pièce ayant une fonction précise. | G3: Façonner du bois, du métal ou un autre matériau pour lui donner une forme précise et utile. | H3: VALIDÉ_A1 | I3: Centrage explicite sur l’intérêt pour une activité professionnelle ; compatible avec la consigne « aimeriez-vous réaliser cette activité », sans présumer métier ni compétence.
A4: 3 | B4: PIP-SIT-R-R1-003 | C4: R | D4: R1 | E4: Prendre en charge la réalisation concrète d’un objet ou d’une structure à partir d’éléments séparés. | F4: À partir de pièces séparées, réaliser concrètement une étagère, un présentoir ou une petite structure. | G4: Construire concrètement une petite structure à partir d’éléments séparés. | H4: VALIDÉ_A1 | I4: Centrage explicite sur l’intérêt pour une activité professionnelle ; compatible avec la consigne « aimeriez-vous réaliser cette activité », sans présumer métier ni compétence.
A5: 4 | B5: PIP-ACT-R-R2-005 | C5: R | D5: R2 | E5: Installer un équipement pour qu’il soit prêt à fonctionner. | F5: Installer un poste de travail, un appareil ou un équipement puis vérifier qu’il fonctionne. | G5: Installer un appareil ou un équipement puis vérifier qu’il fonctionne correctement. | H5: VALIDÉ_A1 | I5: Centrage explicite sur l’intérêt pour une activité professionnelle ; compatible avec la consigne « aimeriez-vous réaliser cette activité », sans présumer métier ni compétence.
A6: 5 | B6: PIP-ACT-R-R2-006 | C6: R | D6: R2 | E6: Réparer un matériel qui ne fonctionne plus correctement. | F6: Rechercher la panne d’un appareil simple puis intervenir concrètement pour le remettre en service. | G6: Rechercher la cause d’une panne puis intervenir concrètement pour remettre l’équipement en service. | H6: VALIDÉ_A1 | I6: Centrage explicite sur l’intérêt pour une activité professionnelle ; compatible avec la consigne « aimeriez-vous réaliser cette activité », sans présumer métier ni compétence.
A7: 6 | B7: PIP-ACT-R-R3-009 | C7: R | D7: R3 | E7: Utiliser des outils pour réaliser une tâche concrète avec précision. | F7: Utiliser des outils de mesure et des outils manuels pour réaliser un montage avec précision. | G7: Utiliser directement des outils de mesure et des outils manuels pour réaliser un montage précis. | H7: VALIDÉ_A1 | I7: Centrage explicite sur l’intérêt pour une activité professionnelle ; compatible avec la consigne « aimeriez-vous réaliser cette activité », sans présumer métier ni compétence.
A8: 7 | B8: PIP-ACT-R-R3-010 | C8: R | D8: R3 | E8: Piloter ou régler une machine pour obtenir le résultat attendu. | F8: Régler une machine ou un équipement pour obtenir une dimension, une forme ou un résultat précis. | G8: Régler une machine ou un équipement pour obtenir le résultat demandé. | H8: VALIDÉ_A1 | I8: Centrage explicite sur l’intérêt pour une activité professionnelle ; compatible avec la consigne « aimeriez-vous réaliser cette activité », sans présumer métier ni compétence.
A9: 8 | B9: PIP-SIT-R-R3-011 | C9: R | D9: R3 | E9: Prendre en charge une tâche qui nécessite de manipuler directement un appareil ou un équipement. | F9: Réaliser une opération qui demande de manipuler directement un appareil, une machine ou un instrument. | G9: Manipuler directement une machine, un appareil ou un instrument pour réaliser une opération. | H9: VALIDÉ_A1 | I9: Centrage explicite sur l’intérêt pour une activité professionnelle ; compatible avec la consigne « aimeriez-vous réaliser cette activité », sans présumer métier ni compétence.
A10: 9 | B10: PIP-ACT-R-R4-013 | C10: R | D10: R4 | E10: Se rendre sur différents sites pour intervenir directement sur le terrain. | F10: Se déplacer sur plusieurs sites pour constater une situation et intervenir directement sur place. | G10: Se déplacer sur le terrain pour constater une situation et intervenir sur place. | H10: VALIDÉ_A1 | I10: Centrage explicite sur l’intérêt pour une activité professionnelle ; compatible avec la consigne « aimeriez-vous réaliser cette activité », sans présumer métier ni compétence.
A11: 10 | B11: PIP-ACT-R-R4-014 | C11: R | D11: R4 | E11: Réaliser une activité professionnelle principalement en extérieur. | F11: Passer l’essentiel de sa journée de travail dehors, sur un chantier, un site naturel ou un espace extérieur. | G11: Réaliser une grande partie de son travail à l’extérieur, sur un chantier, un site ou dans un espace naturel. | H11: VALIDÉ_A1 | I11: Centrage explicite sur l’intérêt pour une activité professionnelle ; compatible avec la consigne « aimeriez-vous réaliser cette activité », sans présumer métier ni compétence.
A12: 11 | B12: PIP-ACT-R-R5-017 | C12: R | D12: R5 | E12: S’occuper concrètement de plantes ou d’animaux dans le cadre du travail. | F12: S’occuper concrètement de cultures, de plantes ou d’animaux : nourrir, entretenir, surveiller leur état. | G12: Prendre soin concrètement de plantes, de cultures ou d’animaux en assurant leur entretien et leur suivi. | H12: VALIDÉ_A1 | I12: Centrage explicite sur l’intérêt pour une activité professionnelle ; compatible avec la consigne « aimeriez-vous réaliser cette activité », sans présumer métier ni compétence.
A13: 12 | B13: PIP-ACT-R-R5-018 | C13: R | D13: R5 | E13: Manipuler des matériaux ou des produits pour réaliser une tâche physique utile. | F13: Manipuler des matériaux, déplacer des éléments ou préparer physiquement des produits pour réaliser une opération utile. | G13: Manipuler des matériaux, déplacer ou préparer physiquement des éléments pour réaliser une tâche utile. | H13: VALIDÉ_A1 | I13: Centrage explicite sur l’intérêt pour une activité professionnelle ; compatible avec la consigne « aimeriez-vous réaliser cette activité », sans présumer métier ni compétence.
... A73: 72 | B73: PIP-ACT-C-C5-018 | C73: C | D73: C5 | E73: Planifier et suivre des échéances pour que plusieurs opérations soient réalisées au bon moment. | F73: Planifier plusieurs échéances et vérifier régulièrement que les opérations prévues sont réalisées au bon moment. | G73: Planifier plusieurs échéances et vérifier régulièrement que les opérations prévues sont réalisées au bon moment. | H73: VALIDÉ_A1 | I73: Centrage explicite sur l’intérêt pour une activité professionnelle ; compatible avec la consigne « aimeriez-vous réaliser cette activité », sans présumer métier ni compétence.

Sheet README
A1: CLARTÉ360 — TABLEUR MAÎTRE PIP RIASEC
A2: V0.4 — Revue de contextualisation des 120 items + journal de recette L1 | formulations source conservées | exemples distincts du scoring
A4: Champ | B4: Valeur | D4: Mode d’emploi
A5: Nom | B5: 0.5.1 | D5: 1. Rédiger les items dans QUESTIONS sans modifier les IDs.
A6: Version tableur | B6: 0.6 | D6: 2. Passer les risques/biais de A_EVALUER à FAIBLE/MOYEN/ELEVE après revue.
A7: Statut | B7: BANQUE ACTIVE A1 — 72 items ; source métier = 01_QUESTIONS_72 ; protocole = 02_REPONSES_CONSIGNE | D7: 3. Changer le statut BROUILLON → REVU → PILOTE → ACTIF selon validation.
A8: Date | B8: 10/09/2026 | D8: 4. Contrôler PARAMETRES : tous les contrôles critiques doivent être OK avant export.
A9: Référentiel méthodologique | B9: REFERENTIEL_METHODOLOGIQUE_PIP_RIASEC_CLARTE360_V1_0.docx | D9: 5. L’application utilisera un export JSON/versionné ; le classeur reste la source métier.
A10: CDC | B10: CDC_PIP_RIASEC_CLARTE360_ONET_V1_4.docx | D10: 6. O*NET est appelé via API officielle ; seule la configuration non secrète figure dans ONET_CONFIG.
A11: Banque cible expérimentale | B11: 72 items actifs : 12 par dimension ; 30 facettes couvertes | D11: 7. La formulation source reste inchangée tant qu’une décision méthodologique explicite n’est pas prise.
A12: Version finale visée | B12: 72 items — Jalon A1 | D12: 8. Les exemples de contextualisation sont gérés dans CONTEXTUALISATION et ne participent jamais au scoring.
A13: Scoring PIP | B13: Réponse 1–5, moyenne par dimension, indice = 25 × (moyenne − 1) | D13: 9. Toute modification d’exemple doit être revue pour hybridité, désirabilité et familiarité sectorielle.
A14: O*NET | B14: Instrument externe distinct ; cible d’intégration via O*NET Web Services API. Aucun item O*NET ni clé API dans ce classeur. | D14: 10. Les anomalies issues de la recette réelle sont suivies dans RECETTE_L1.
A15: Sécurité | B15: Classeur et exports côté serveur / dépôt privé. Jamais exposer mapping, scoring ou banque complète au navigateur.
A16: Règle de source de vérité | B16: Le tableur maître est éditable ; l’application consomme un export contrôlé/versionné et ne devient pas une seconde source de vérité.
A19: Sources externes de référence
A20: https://www.onetcenter.org/IP.html
A21: https://services.onetcenter.org/
A22: https://www.onetcenter.org/license_tools.html
A23: https://www.onetcenter.org/reports/IP_Manual.html
A24: https://www.onetcenter.org/reports/Voc_Interests.html
A26: Évolution V0.5.1 | B26: Les 72 items sont reformulés pour répondre à la question implicite « Dans votre travail, dans quelle mesure aimeriez-vous réaliser cette activité ? ». L’échelle « Cela m’attire » est remplacée par une échelle « J’aimerais… ». Le tableur reste la source métier ; l’application consomme un export JSON versionné.
A27: Architecture de publication | B27: Une modification du tableur ne modifie pas automatiquement l’application : elle doit générer un nouvel export JSON contrôlé, puis passer les tests avant livraison.

Sheet BANQUE_72_V0.5
A1: ordre | B1: item_id_source | C1: item_version | D1: bank_version | E1: dimension | F1: facette | G1: bloc | H1: formulation_v0_4 | I1: formulation_v0_5_concrete | J1: decision | K1: justification_selection | L1: risque_hybridite | M1: risque_desirabilite | N1: risque_familiarite_sectorielle
A2: 1 | B2: PIP-ACT-R-R1-001 | C2: 0.5 | D2: PIP-BANK-0.4 | E2: R | F2: R1 | G2: ACT | H2: Assembler des éléments pour fabriquer un objet fonctionnel. | I2: Assembler les pièces d’un petit meuble ou d’un support pour qu’il soit solide et utilisable. | J2: RETENU | K2: Couverture de facette + activité observable ; priorité ACT, complétée par SIT à faible risque. | L2: FAIBLE | M2: FAIBLE | N2: MOYEN
A3: 2 | B3: PIP-ACT-R-R1-002 | C3: 0.5 | D3: PIP-BANK-0.4 | E3: R | F3: R1 | G3: ACT | H3: Transformer une matière ou un matériau pour lui donner une forme utile. | I3: Travailler du bois, du métal ou un autre matériau pour obtenir une pièce ayant une fonction précise. | J3: RETENU | K3: Couverture de facette + activité observable ; priorité ACT, complétée par SIT à faible risque. | L3: FAIBLE | M3: FAIBLE | N3: MOYEN
A4: 3 | B4: PIP-SIT-R-R1-003 | C4: 0.5 | D4: PIP-BANK-0.4 | E4: R | F4: R1 | G4: SIT | H4: Prendre en charge la réalisation concrète d’un objet ou d’une structure à partir d’éléments séparés. | I4: À partir de pièces séparées, réaliser concrètement une étagère, un présentoir ou une petite structure. | J4: RETENU | K4: Couverture de facette + activité observable ; priorité ACT, complétée par SIT à faible risque. | L4: FAIBLE | M4: FAIBLE | N4: MOYEN
A5: 4 | B5: PIP-ACT-R-R2-005 | C5: 0.5 | D5: PIP-BANK-0.4 | E5: R | F5: R2 | G5: ACT | H5: Installer un équipement pour qu’il soit prêt à fonctionner. | I5: Installer un poste de travail, un appareil ou un équipement puis vérifier qu’il fonctionne. | J5: RETENU | K5: Couverture de facette + activité observable ; priorité ACT, complétée par SIT à faible risque. | L5: FAIBLE | M5: FAIBLE | N5: MOYEN
A6: 5 | B6: PIP-ACT-R-R2-006 | C6: 0.5 | D6: PIP-BANK-0.4 | E6: R | F6: R2 | G6: ACT | H6: Réparer un matériel qui ne fonctionne plus correctement. | I6: Rechercher la panne d’un appareil simple puis intervenir concrètement pour le remettre en service. | J6: RETENU | K6: Couverture de facette + activité observable ; priorité ACT, complétée par SIT à faible risque. | L6: MOYEN | M6: FAIBLE | N6: MOYEN
A7: 6 | B7: PIP-ACT-R-R3-009 | C7: 0.5 | D7: PIP-BANK-0.4 | E7: R | F7: R3 | G7: ACT | H7: Utiliser des outils pour réaliser une tâche concrète avec précision. | I7: Utiliser des outils de mesure et des outils manuels pour réaliser un montage avec précision. | J7: RETENU | K7: Couverture de facette + activité observable ; priorité ACT, complétée par SIT à faible risque. | L7: FAIBLE | M7: FAIBLE | N7: MOYEN
A8: 7 | B8: PIP-ACT-R-R3-010 | C8: 0.5 | D8: PIP-BANK-0.4 | E8: R | F8: R3 | G8: ACT | H8: Piloter ou régler une machine pour obtenir le résultat attendu. | I8: Régler une machine ou un équipement pour obtenir une dimension, une forme ou un résultat précis. | J8: RETENU | K8: Couverture de facette + activité observable ; priorité ACT, complétée par SIT à faible risque. | L8: FAIBLE | M8: FAIBLE | N8: MOYEN
A9: 8 | B9: PIP-SIT-R-R3-011 | C9: 0.5 | D9: PIP-BANK-0.4 | E9: R | F9: R3 | G9: SIT | H9: Prendre en charge une tâche qui nécessite de manipuler directement un appareil ou un équipement. | I9: Réaliser une opération qui demande de manipuler directement un appareil, une machine ou un instrument. | J9: RETENU | K9: Couverture de facette + activité observable ; priorité ACT, complétée par SIT à faible risque. | L9: FAIBLE | M9: FAIBLE | N9: MOYEN
A10: 9 | B10: PIP-ACT-R-R4-013 | C10: 0.5 | D10: PIP-BANK-0.4 | E10: R | F10: R4 | G10: ACT | H10: Se rendre sur différents sites pour intervenir directement sur le terrain. | I10: Se déplacer sur plusieurs sites pour constater une situation et intervenir directement sur place. | J10: RETENU | K10: Couverture de facette + activité observable ; priorité ACT, complétée par SIT à faible risque. | L10: FAIBLE | M10: FAIBLE | N10: MOYEN
A11: 10 | B11: PIP-ACT-R-R4-014 | C11: 0.5 | D11: PIP-BANK-0.4 | E11: R | F11: R4 | G11: ACT | H11: Réaliser une activité professionnelle principalement en extérieur. | I11: Passer l’essentiel de sa journée de travail dehors, sur un chantier, un site naturel ou un espace extérieur. | J11: RETENU | K11: Couverture de facette + activité observable ; priorité ACT, complétée par SIT à faible risque. | L11: FAIBLE | M11: FAIBLE | N11: MOYEN
A12: 11 | B12: PIP-ACT-R-R5-017 | C12: 0.5 | D12: PIP-BANK-0.4 | E12: R | F12: R5 | G12: ACT | H12: S’occuper concrètement de plantes ou d’animaux dans le cadre du travail. | I12: S’occuper concrètement de cultures, de plantes ou d’animaux : nourrir, entretenir, surveiller leur état. | J12: RETENU | K12: Couverture de facette + activité observable ; priorité ACT, complétée par SIT à faible risque. | L12: MOYEN | M12: FAIBLE | N12: MOYEN
A13: 12 | B13: PIP-ACT-R-R5-018 | C13: 0.5 | D13: PIP-BANK-0.4 | E13: R | F13: R5 | G13: ACT | H13: Manipuler des matériaux ou des produits pour réaliser une tâche physique utile. | I13: Manipuler des matériaux, déplacer des éléments ou préparer physiquement des produits pour réaliser une opération utile. | J13: RETENU | K13: Couverture de facette + activité observable ; priorité ACT, complétée par SIT à faible risque. | L13: FAIBLE | M13: FAIBLE | N13: MOYEN
... A73: 72 | B73: PIP-ACT-C-C5-018 | C73: 0.5 | D73: PIP-BANK-0.4 | E73: C | F73: C5 | G73: ACT | H73: Planifier et suivre des échéances pour que plusieurs opérations soient réalisées au bon moment. | I73: Planifier plusieurs échéances et vérifier régulièrement que les opérations prévues sont réalisées au bon moment. | J73: RETENU | K73: Couverture de facette + activité observable ; priorité ACT, complétée par SIT à faible risque. | L73: MOYEN | M73: MOYEN | N73: FAIBLE

Sheet PROTOCOLE_REPONSE_V0.5.1
A1: CLARTÉ360 — PIP RIASEC — PROTOCOLE DE RÉPONSE V0.5.1
A2: Objectif | B2: Mesurer l’intérêt professionnel : ce que la personne aimerait faire dans son travail, indépendamment de son métier actuel, de son expérience ou de son niveau de compétence.
A3: Consigne utilisateur | B3: Pour chacune des activités suivantes, indiquez dans quelle mesure vous aimeriez la réaliser dans votre travail. Répondez selon votre envie, et non selon ce que vous savez déjà faire, votre métier actuel ou ce que vous pensez devoir aimer.
A4: Stem UI recommandé | B4: Dans votre travail, dans quelle mesure aimeriez-vous réaliser cette activité ?
A5: Réponse 1 | B5: Je n’aimerais pas du tout faire cela.
A6: Réponse 2 | B6: J’aimerais peu faire cela.
A7: Réponse 3 | B7: Je suis partagé(e) / sans préférence marquée.
A8: Réponse 4 | B8: J’aimerais assez faire cela.
A9: Réponse 5 | B9: J’aimerais beaucoup faire cela.
A10: Règle méthodologique | B10: Les réponses portent sur l’attrait pour l’activité et non sur la compétence, l’aptitude, l’intelligence, la personnalité ou la probabilité de réussir dans un métier.
A11: Règle de rédaction | B11: Chaque item décrit une seule activité professionnelle observable, concrète, courte et visualisable, tout en restant suffisamment transversale pour ne pas enfermer la réponse dans un métier particulier.
A12: Règle Holland | B12: Chaque item conserve une dimension principale R/I/A/S/E/C et une facette documentée ; les formulations doivent privilégier le noyau d’intérêt de la dimension sans transformer le questionnaire en test de compétences.

Sheet REVUE_120_V0.5
A1: item_id | B1: dimension | C1: facette | D1: bloc | E1: formulation_v0_4 | F1: exemple_v0_4 | G1: niveau_concretude | H1: ambiguite_chevauchement | I1: pertinence_professionnelle | J1: decision_v0_5 | K1: formulation_v0_5_si_retenu | L1: motif | M1: bank_version_sortie
A2: PIP-ACT-R-R1-001 | B2: R | C2: R1 | D2: ACT | E2: Assembler des éléments pour fabriquer un objet fonctionnel. | F2: Assembler les pièces d’un petit meuble ou d’un support pour qu’il soit solide et utilisable. | G2: MOYENNE | H2: FAIBLE | I2: FORTE | J2: MAINTIEN_REECRIT | K2: Assembler les pièces d’un petit meuble ou d’un support pour qu’il soit solide et utilisable. | L2: Retenu pour couverture de facette et formulation rendue directement concrète. | M2: PIP-BANK-0.4
A3: PIP-ACT-R-R1-002 | B3: R | C3: R1 | D3: ACT | E3: Transformer une matière ou un matériau pour lui donner une forme utile. | F3: Travailler du bois, du métal ou un autre matériau pour obtenir une pièce ayant une fonction précise. | G3: MOYENNE | H3: FAIBLE | I3: FORTE | J3: MAINTIEN_REECRIT | K3: Travailler du bois, du métal ou un autre matériau pour obtenir une pièce ayant une fonction précise. | L3: Retenu pour couverture de facette et formulation rendue directement concrète. | M3: PIP-BANK-0.4
A4: PIP-SIT-R-R1-003 | B4: R | C4: R1 | D4: SIT | E4: Prendre en charge la réalisation concrète d’un objet ou d’une structure à partir d’éléments séparés. | F4: À partir de pièces séparées, réaliser concrètement une étagère, un présentoir ou une petite structure. | G4: FAIBLE_A_MOYENNE | H4: FAIBLE | I4: FORTE | J4: MAINTIEN_REECRIT | K4: À partir de pièces séparées, réaliser concrètement une étagère, un présentoir ou une petite structure. | L4: Retenu pour couverture de facette et formulation rendue directement concrète. | M4: PIP-BANK-0.4
A5: PIP-ENV-R-R1-004 | B5: R | C5: R1 | D5: ENV | E5: Travailler dans un contexte où l’on voit directement le résultat matériel de ce que l’on fabrique ou transforme. | F5: Évoluer dans un atelier ou un espace de fabrication où l’on voit physiquement ce qui a été produit. | G5: FAIBLE_A_MOYENNE | H5: FAIBLE | I5: MOYENNE | J5: RETRAIT_BANQUE72 | L5: Historique conservé ; item non nécessaire pour atteindre 12/dimension et ≥2/facette. | M5: PIP-BANK-0.3
A6: PIP-ACT-R-R2-005 | B6: R | C6: R2 | D6: ACT | E6: Installer un équipement pour qu’il soit prêt à fonctionner. | F6: Installer un poste de travail, un appareil ou un équipement puis vérifier qu’il fonctionne. | G6: MOYENNE | H6: FAIBLE | I6: FORTE | J6: MAINTIEN_REECRIT | K6: Installer un poste de travail, un appareil ou un équipement puis vérifier qu’il fonctionne. | L6: Retenu pour couverture de facette et formulation rendue directement concrète. | M6: PIP-BANK-0.4
A7: PIP-ACT-R-R2-006 | B7: R | C7: R2 | D7: ACT | E7: Réparer un matériel qui ne fonctionne plus correctement. | F7: Rechercher la panne d’un appareil simple puis intervenir concrètement pour le remettre en service. | G7: MOYENNE | H7: A_SURVEILLER | I7: FORTE | J7: MAINTIEN_REECRIT | K7: Rechercher la panne d’un appareil simple puis intervenir concrètement pour le remettre en service. | L7: Retenu pour couverture de facette et formulation rendue directement concrète. | M7: PIP-BANK-0.4
A8: PIP-SIT-R-R2-007 | B8: R | C8: R2 | D8: SIT | E8: Intervenir lorsqu’un équipement doit être réglé ou remis en service. | F8: Un équipement fonctionne mal : le régler, remplacer l’élément défectueux et tester le résultat. | G8: FAIBLE_A_MOYENNE | H8: A_SURVEILLER | I8: FORTE | J8: RETRAIT_BANQUE72 | L8: Historique conservé ; item non nécessaire pour atteindre 12/dimension et ≥2/facette. | M8: PIP-BANK-0.3
A9: PIP-ENV-R-R2-008 | B9: R | C9: R2 | D9: ENV | E9: Évoluer dans un contexte où une part importante du travail consiste à entretenir et remettre en fonctionnement des équipements. | F9: Travailler dans un service où l’on entretient régulièrement des équipements et où l’on intervient en cas de panne. | G9: FAIBLE_A_MOYENNE | H9: FAIBLE | I9: MOYENNE | J9: RETRAIT_BANQUE72 | L9: Historique conservé ; item non nécessaire pour atteindre 12/dimension et ≥2/facette. | M9: PIP-BANK-0.3
A10: PIP-ACT-R-R3-009 | B10: R | C10: R3 | D10: ACT | E10: Utiliser des outils pour réaliser une tâche concrète avec précision. | F10: Utiliser des outils de mesure et des outils manuels pour réaliser un montage avec précision. | G10: MOYENNE | H10: FAIBLE | I10: FORTE | J10: MAINTIEN_REECRIT | K10: Utiliser des outils de mesure et des outils manuels pour réaliser un montage avec précision. | L10: Retenu pour couverture de facette et formulation rendue directement concrète. | M10: PIP-BANK-0.4
A11: PIP-ACT-R-R3-010 | B11: R | C11: R3 | D11: ACT | E11: Piloter ou régler une machine pour obtenir le résultat attendu. | F11: Régler une machine ou un équipement pour obtenir une dimension, une forme ou un résultat précis. | G11: MOYENNE | H11: FAIBLE | I11: FORTE | J11: MAINTIEN_REECRIT | K11: Régler une machine ou un équipement pour obtenir une dimension, une forme ou un résultat précis. | L11: Retenu pour couverture de facette et formulation rendue directement concrète. | M11: PIP-BANK-0.4
A12: PIP-SIT-R-R3-011 | B12: R | C12: R3 | D12: SIT | E12: Prendre en charge une tâche qui nécessite de manipuler directement un appareil ou un équipement. | F12: Réaliser une opération qui demande de manipuler directement un appareil, une machine ou un instrument. | G12: FAIBLE_A_MOYENNE | H12: FAIBLE | I12: FORTE | J12: MAINTIEN_REECRIT | K12: Réaliser une opération qui demande de manipuler directement un appareil, une machine ou un instrument. | L12: Retenu pour couverture de facette et formulation rendue directement concrète. | M12: PIP-BANK-0.4
A13: PIP-ENV-R-R3-012 | B13: R | C13: R3 | D13: ENV | E13: Travailler dans un environnement où l’on utilise régulièrement des outils, des instruments ou des machines pour agir sur le réel. | F13: Travailler dans un environnement où l’usage d’outils, d’instruments ou de machines fait partie du quotidien. | G13: FAIBLE_A_MOYENNE | H13: FAIBLE | I13: MOYENNE | J13: RETRAIT_BANQUE72 | L13: Historique conservé ; item non nécessaire pour atteindre 12/dimension et ≥2/facette. | M13: PIP-BANK-0.3
A14: PIP-ACT-R-R4-013 | B14: R | C14: R4 | D14: ACT | E14: Se rendre sur différents sites pour intervenir directement sur le terrain. | F14: Se déplacer sur plusieurs sites pour constater une situation et intervenir directement sur place. | G14: MOYENNE | H14: FAIBLE | I14: FORTE | J14: MAINTIEN_REECRIT | K14: Se déplacer sur plusieurs sites pour constater une situation et intervenir directement sur place. | L14: Retenu pour couverture de facette et formulation rendue directement concrète. | M14: PIP-BANK-0.4
A15: PIP-ACT-R-R4-014 | B15: R | C15: R4 | D15: ACT | E15: Réaliser une activité professionnelle principalement en extérieur. | F15: Passer l’essentiel de sa journée de travail dehors, sur un chantier, un site naturel ou un espace extérieur. | G15: MOYENNE | H15: FAIBLE | I15: FORTE | J15: MAINTIEN_REECRIT | K15: Passer l’essentiel de sa journée de travail dehors, sur un chantier, un site naturel ou un espace extérieur. | L15: Retenu pour couverture de facette et formulation rendue directement concrète. | M15: PIP-BANK-0.4
A16: PIP-SIT-R-R4-015 | B16: R | C16: R4 | D16: SIT | E16: Intervenir sur place lorsqu’une situation concrète doit être traitée directement plutôt qu’à distance. | F16: Un problème apparaît sur un site : aller sur place pour observer la situation et agir immédiatement. | G16: FAIBLE_A_MOYENNE | H16: FAIBLE | I16: FORTE | J16: RETRAIT_BANQUE72 | L16: Historique conservé ; item non nécessaire pour atteindre 12/dimension et ≥2/facette. | M16: PIP-BANK-0.3
A17: PIP-ENV-R-R4-016 | B17: R | C17: R4 | D17: ENV | E17: Travailler dans un contexte où l’activité se déroule souvent sur le terrain, au contact direct de l’environnement réel. | F17: Exercer un métier où l’on est souvent sur le terrain plutôt que derrière un bureau. | G17: FAIBLE_A_MOYENNE | H17: FAIBLE | I17: MOYENNE | J17: RETRAIT_BANQUE72 | L17: Historique conservé ; item non nécessaire pour atteindre 12/dimension et ≥2/facette. | M17: PIP-BANK-0.3
A18: PIP-ACT-R-R5-017 | B18: R | C18: R5 | D18: ACT | E18: S’occuper concrètement de plantes ou d’animaux dans le cadre du travail. | F18: S’occuper concrètement de cultures, de plantes ou d’animaux : nourrir, entretenir, surveiller leur état. | G18: MOYENNE | H18: A_SURVEILLER | I18: FORTE | J18: MAINTIEN_REECRIT | K18: S’occuper concrètement de cultures, de plantes ou d’animaux : nourrir, entretenir, surveiller leur état. | L18: Retenu pour couverture de facette et formulation rendue directement concrète. | M18: PIP-BANK-0.4
A19: PIP-ACT-R-R5-018 | B19: R | C19: R5 | D19: ACT | E19: Manipuler des matériaux ou des produits pour réaliser une tâche physique utile. | F19: Manipuler des matériaux, déplacer des éléments ou préparer physiquement des produits pour réaliser une opération utile. | G19: MOYENNE | H19: FAIBLE | I19: FORTE | J19: MAINTIEN_REECRIT | K19: Manipuler des matériaux, déplacer des éléments ou préparer physiquement des produits pour réaliser une opération utile. | L19: Retenu pour couverture de facette et formulation rendue directement concrète. | M19: PIP-BANK-0.4
A20: PIP-SIT-R-R5-019 | B20: R | C20: R5 | D20: SIT | E20: Prendre en charge une activité où il faut agir directement sur du vivant, de la matière ou un environnement physique. | F20: Prendre en charge une tâche nécessitant d’agir directement sur des matières, des plantes, des animaux ou un espace physique. | G20: FAIBLE_A_MOYENNE | H20: FAIBLE | I20: FORTE | J20: RETRAIT_BANQUE72 | L20: Historique conservé ; item non nécessaire pour atteindre 12/dimension et ≥2/facette. | M20: PIP-BANK-0.3
A21: PIP-ENV-R-R5-020 | B21: R | C21: R5 | D21: ENV | E21: Évoluer dans un environnement où le travail implique régulièrement une action physique concrète sur des matières, des plantes, des animaux ou des objets. | F21: Travailler dans un environnement où l’activité implique régulièrement de manipuler des matières, des objets ou du vivant. | G21: FAIBLE_A_MOYENNE | H21: FAIBLE | I21: MOYENNE | J21: RETRAIT_BANQUE72 | L21: Historique conservé ; item non nécessaire pour atteindre 12/dimension et ≥2/facette. | M21: PIP-BANK-0.3
A22: PIP-ACT-I-I1-001 | B22: I | C22: I1 | D22: ACT | E22: Observer attentivement une situation pour en repérer les caractéristiques importantes. | F22: Observer un fonctionnement, un phénomène ou une situation et relever les détails importants avant de conclure. | G22: MOYENNE | H22: FAIBLE | I22: FORTE | J22: MAINTIEN_REECRIT | K22: Observer un fonctionnement, un phénomène ou une situation et relever les détails importants avant de conclure. | L22: Retenu pour couverture de facette et formulation rendue directement concrète. | M22: PIP-BANK-0.4
A23: PIP-ACT-I-I1-002 | B23: I | C23: I1 | D23: ACT | E23: Comparer plusieurs informations ou observations pour identifier ce qui les distingue. | F23: Comparer deux séries d’informations ou d’observations pour identifier précisément ce qui diffère. | G23: MOYENNE | H23: FAIBLE | I23: FORTE | J23: MAINTIEN_REECRIT | K23: Comparer deux séries d’informations ou d’observations pour identifier précisément ce qui diffère. | L23: Retenu pour couverture de facette et formulation rendue directement concrète. | M23: PIP-BANK-0.4
A24: PIP-SIT-I-I1-003 | B24: I | C24: I1 | D24: SIT | E24: Examiner une situation nouvelle afin de comprendre précisément ce qui s’y passe. | F24: Face à une situation inhabituelle, prendre le temps d’examiner les faits avant d’avancer une explication. | G24: FAIBLE_A_MOYENNE | H24: FAIBLE | I24: FORTE | J24: MAINTIEN_REECRIT | K24: Face à une situation inhabituelle, prendre le temps d’examiner les faits avant d’avancer une explication. | L24: Retenu pour couverture de facette et formulation rendue directement concrète. | M24: PIP-BANK-0.4
A25: PIP-ENV-I-I1-004 | B25: I | C25: I1 | D25: ENV | E25: Travailler dans un contexte où l’on dispose de temps pour observer et examiner les faits avant de tirer des conclusions. | F25: Travailler dans un contexte où l’on peut observer, vérifier et examiner les faits avant de prendre position. | G25: FAIBLE_A_MOYENNE | H25: FAIBLE | I25: MOYENNE | J25: RETRAIT_BANQUE72 | L25: Historique conservé ; item non nécessaire pour atteindre 12/dimension et ≥2/facette. | M25: PIP-BANK-0.3
A26: PIP-ACT-I-I2-005 | B26: I | C26: I2 | D26: ACT | E26: Analyser plusieurs informations pour comprendre les liens entre elles. | F26: Analyser plusieurs données pour comprendre comment elles sont liées et ce qu’elles expliquent. | G26: MOYENNE | H26: FAIBLE | I26: FORTE | J26: MAINTIEN_REECRIT | K26: Analyser plusieurs données pour comprendre comment elles sont liées et ce qu’elles expliquent. | L26: Retenu pour couverture de facette et formulation rendue directement concrète. | M26: PIP-BANK-0.4
A27: PIP-ACT-I-I2-006 | B27: I | C27: I2 | D27: ACT | E27: Décomposer un problème complexe en plusieurs éléments pour mieux le comprendre. | F27: Découper un problème complexe en plusieurs questions plus simples afin d’en comprendre la logique. | G27: MOYENNE | H27: FAIBLE | I27: FORTE | J27: MAINTIEN_REECRIT | K27: Découper un problème complexe en plusieurs questions plus simples afin d’en comprendre la logique. | L27: Retenu pour couverture de facette et formulation rendue directement concrète. | M27: PIP-BANK-0.4
A28: PIP-SIT-I-I2-007 | B28: I | C28: I2 | D28: SIT | E28: Faire face à un problème où il faut raisonner étape par étape avant de trouver une explication. | F28: Un problème n’a pas de réponse évidente : raisonner étape par étape pour comprendre ce qui se passe. | G28: FAIBLE_A_MOYENNE | H28: FAIBLE | I28: FORTE | J28: MAINTIEN_REECRIT | K28: Un problème n’a pas de réponse évidente : raisonner étape par étape pour comprendre ce qui se passe. | L28: Retenu pour couverture de facette et formulation rendue directement concrète. | M28: PIP-BANK-0.4
A29: PIP-ENV-I-I2-008 | B29: I | C29: I2 | D29: ENV | E29: Évoluer dans un contexte où l’on doit régulièrement interpréter des informations et construire un raisonnement. | F29: Exercer dans un environnement où l’on doit souvent interpréter des informations et construire un raisonnement argumenté. | G29: FAIBLE_A_MOYENNE | H29: FAIBLE | I29: MOYENNE | J29: RETRAIT_BANQUE72 | L29: Historique conservé ; item non nécessaire pour atteindre 12/dimension et ≥2/facette. | M29: PIP-BANK-0.3
A30: PIP-ACT-I-I3-009 | B30: I | C30: I3 | D30: ACT | E30: Rechercher des informations provenant de plusieurs sources pour répondre à une question. | F30: Chercher des informations dans plusieurs sources fiables pour répondre à une question précise. | G30: MOYENNE | H30: FAIBLE | I30: FORTE | J30: MAINTIEN_REECRIT | K30: Chercher des informations dans plusieurs sources fiables pour répondre à une question précise. | L30: Retenu pour couverture de facette et formulation rendue directement concrète. | M30: PIP-BANK-0.4
A31: PIP-ACT-I-I3-010 | B31: I | C31: I3 | D31: ACT | E31: Enquêter pour vérifier ce qui est exact lorsqu’une situation reste incertaine. | F31: Vérifier une information incertaine en recoupant des sources et en recherchant des éléments de preuve. | G31: MOYENNE | H31: FAIBLE | I31: FORTE | J31: MAINTIEN_REECRIT | K31: Vérifier une information incertaine en recoupant des sources et en recherchant des éléments de preuve. | L31: Retenu pour couverture de facette et formulation rendue directement concrète. | M31: PIP-BANK-0.4
A32: PIP-SIT-I-I3-011 | B32: I | C32: I3 | D32: SIT | E32: Être confronté à une question sans réponse immédiate et devoir approfondir les recherches pour la comprendre. | F32: Une question reste sans réponse : approfondir la recherche jusqu’à comprendre les éléments essentiels. | G32: FAIBLE_A_MOYENNE | H32: FAIBLE | I32: FORTE | J32: RETRAIT_BANQUE72 | L32: Historique conservé ; item non nécessaire pour atteindre 12/dimension et ≥2/facette. | M32: PIP-BANK-0.3
A33: PIP-ENV-I-I3-012 | B33: I | C33: I3 | D33: ENV | E33: Travailler dans un contexte où l’on peut explorer des sujets, consulter des sources et approfondir des questions. | F33: Travailler dans un contexte où l’on dispose régulièrement de temps pour chercher, documenter et approfondir des sujets. | G33: FAIBLE_A_MOYENNE | H33: FAIBLE | I33: MOYENNE | J33: RETRAIT_BANQUE72 | L33: Historique conservé ; item non nécessaire pour atteindre 12/dimension et ≥2/facette. | M33: PIP-BANK-0.3
A34: PIP-ACT-I-I4-013 | B34: I | C34: I4 | D34: ACT | E34: Tester une hypothèse pour voir si elle se vérifie. | F34: Tester une hypothèse en définissant une manière simple de vérifier si elle se confirme. | G34: MOYENNE | H34: FAIBLE | I34: FORTE | J34: MAINTIEN_REECRIT | K34: Tester une hypothèse en définissant une manière simple de vérifier si elle se confirme. | L34: Retenu pour couverture de facette et formulation rendue directement concrète. | M34: PIP-BANK-0.4
A35: PIP-ACT-I-I4-014 | B35: I | C35: I4 | D35: ACT | E35: Comparer plusieurs essais pour comprendre ce qui produit un résultat différent. | F35: Réaliser plusieurs essais en modifiant un paramètre pour comprendre ce qui change le résultat. | G35: MOYENNE | H35: FAIBLE | I35: FORTE | J35: MAINTIEN_REECRIT | K35: Réaliser plusieurs essais en modifiant un paramètre pour comprendre ce qui change le résultat. | L35: Retenu pour couverture de facette et formulation rendue directement concrète. | M35: PIP-BANK-0.4
A36: PIP-SIT-I-I4-015 | B36: I | C36: I4 | D36: SIT | E36: Chercher la meilleure explication d’un phénomène en réalisant des essais ou des mesures. | F36: Pour expliquer un phénomène, effectuer des mesures ou des essais et comparer les résultats obtenus. | G36: FAIBLE_A_MOYENNE | H36: FAIBLE | I36: FORTE | J36: RETRAIT_BANQUE72 | L36: Historique conservé ; item non nécessaire pour atteindre 12/dimension et ≥2/facette. | M36: PIP-BANK-0.3
A37: PIP-ENV-I-I4-016 | B37: I | C37: I4 | D37: ENV | E37: Évoluer dans un contexte où l’on peut expérimenter, mesurer et tirer des enseignements des résultats. | F37: Évoluer dans un environnement où l’on peut tester, mesurer, expérimenter et apprendre des résultats. | G37: FAIBLE_A_MOYENNE | H37: FAIBLE | I37: MOYENNE | J37: RETRAIT_BANQUE72 | L37: Historique conservé ; item non nécessaire pour atteindre 12/dimension et ≥2/facette. | M37: PIP-BANK-0.3
A38: PIP-ACT-I-I5-017 | B38: I | C38: I5 | D38: ACT | E38: Chercher la cause d’un problème pour pouvoir l’expliquer. | F38: Rechercher la cause d’un dysfonctionnement ou d’un phénomène avant de proposer une explication. | G38: MOYENNE | H38: FAIBLE | I38: FORTE | J38: MAINTIEN_REECRIT | K38: Rechercher la cause d’un dysfonctionnement ou d’un phénomène avant de proposer une explication. | L38: Retenu pour couverture de facette et formulation rendue directement concrète. | M38: PIP-BANK-0.4
A39: PIP-ACT-I-I5-018 | B39: I | C39: I5 | D39: ACT | E39: Résoudre un problème nouveau en construisant une solution fondée sur les informations disponibles. | F39: Résoudre un problème nouveau en utilisant les informations disponibles pour construire une solution raisonnée. | G39: MOYENNE | H39: FAIBLE | I39: FORTE | J39: MAINTIEN_REECRIT | K39: Résoudre un problème nouveau en utilisant les informations disponibles pour construire une solution raisonnée. | L39: Retenu pour couverture de facette et formulation rendue directement concrète. | M39: PIP-BANK-0.4
A40: PIP-SIT-I-I5-019 | B40: I | C40: I5 | D40: SIT | E40: Prendre en charge une situation complexe dont la solution n’est pas connue à l’avance et qui demande d’abord de comprendre le problème. | F40: Face à une situation complexe et inédite, comprendre d’abord le problème avant d’élaborer une solution. | G40: FAIBLE_A_MOYENNE | H40: A_SURVEILLER | I40: FORTE | J40: RETRAIT_BANQUE72 | L40: Historique conservé ; item non nécessaire pour atteindre 12/dimension et ≥2/facette. | M40: PIP-BANK-0.3
A41: PIP-ENV-I-I5-020 | B41: I | C41: I5 | D41: ENV | E41: Travailler dans un contexte où l’on est régulièrement amené à expliquer des phénomènes ou à résoudre des problèmes qui demandent réflexion et compréhension. | F41: Travailler dans un contexte où l’on doit fréquemment expliquer des phénomènes ou résoudre des problèmes qui demandent réflexion. | G41: FAIBLE_A_MOYENNE | H41: FAIBLE | I41: MOYENNE | J41: RETRAIT_BANQUE72 | L41: Historique conservé ; item non nécessaire pour atteindre 12/dimension et ≥2/facette. | M41: PIP-BANK-0.3
A42: PIP-ACT-A-A1-001 | B42: A | C42: A1 | D42: ACT | E42: Imaginer plusieurs idées nouvelles à partir d’un même sujet. | F42: Imaginer plusieurs concepts différents pour répondre à un même thème ou à une même demande. | G42: MOYENNE | H42: FAIBLE | I42: FORTE | J42: MAINTIEN_REECRIT | K42: Imaginer plusieurs concepts différents pour répondre à un même thème ou à une même demande. | L42: Retenu pour couverture de facette et formulation rendue directement concrète. | M42: PIP-BANK-0.4
A43: PIP-ACT-A-A1-002 | B43: A | C43: A1 | D43: ACT | E43: Inventer une manière originale de présenter ou de réaliser quelque chose. | F43: Inventer une manière originale de présenter un message, un objet ou une expérience. | G43: MOYENNE | H43: FAIBLE | I43: FORTE | J43: MAINTIEN_REECRIT | K43: Inventer une manière originale de présenter un message, un objet ou une expérience. | L43: Retenu pour couverture de facette et formulation rendue directement concrète. | M43: PIP-BANK-0.4
A44: PIP-SIT-A-A1-003 | B44: A | C44: A1 | D44: SIT | E44: Faire face à une demande pour laquelle aucune solution n’est imposée et imaginer une proposition nouvelle. | F44: Une demande est ouverte et aucune solution n’est imposée : imaginer une proposition nouvelle et personnelle. | G44: FAIBLE_A_MOYENNE | H44: FAIBLE | I44: FORTE | J44: MAINTIEN_REECRIT | K44: Une demande est ouverte et aucune solution n’est imposée : imaginer une proposition nouvelle et personnelle. | L44: Retenu pour couverture de facette et formulation rendue directement concrète. | M44: PIP-BANK-0.4
A45: PIP-ENV-A-A1-004 | B45: A | C45: A1 | D45: ENV | E45: Travailler dans un contexte où l’on attend régulièrement des idées nouvelles et où plusieurs pistes sont possibles. | F45: Travailler dans un contexte où l’on attend des idées nouvelles et où plusieurs réponses créatives sont possibles. | G45: FAIBLE_A_MOYENNE | H45: FAIBLE | I45: MOYENNE | J45: RETRAIT_BANQUE72 | L45: Historique conservé ; item non nécessaire pour atteindre 12/dimension et ≥2/facette. | M45: PIP-BANK-0.3
A46: PIP-ACT-A-A2-005 | B46: A | C46: A2 | D46: ACT | E46: Concevoir l’organisation visuelle ou la forme d’un support pour qu’il exprime une intention. | F46: Concevoir librement la mise en page d’une affiche, d’une brochure ou d’un support visuel pour transmettre une intention. | G46: MOYENNE | H46: A_SURVEILLER | I46: FORTE | J46: MAINTIEN_REECRIT | K46: Concevoir librement la mise en page d’une affiche, d’une brochure ou d’un support visuel pour transmettre une intention. | L46: Retenu pour couverture de facette et formulation rendue directement concrète. | M46: PIP-BANK-0.4
A47: PIP-ACT-A-A2-006 | B47: A | C47: A2 | D47: ACT | E47: Composer différents éléments pour créer un ensemble cohérent et personnel. | F47: Composer un ensemble en choisissant personnellement la disposition des formes, textes, images, sons ou autres éléments. | G47: MOYENNE | H47: FAIBLE | I47: FORTE | J47: MAINTIEN_REECRIT | K47: Composer un ensemble en choisissant personnellement la disposition des formes, textes, images, sons ou autres éléments. | L47: Retenu pour couverture de facette et formulation rendue directement concrète. | M47: PIP-BANK-0.4
A48: PIP-SIT-A-A2-007 | B48: A | C48: A2 | D48: SIT | E48: Créer une proposition en choisissant librement la manière d’agencer plusieurs éléments. | F48: Créer une proposition en décidant librement comment agencer les éléments d’un support visuel, d’un espace ou d’une présentation créative. | G48: FAIBLE_A_MOYENNE | H48: FAIBLE | I48: FORTE | J48: MAINTIEN_REECRIT | K48: Créer une proposition en décidant librement comment agencer les éléments d’un support visuel, d’un espace ou d’une présentation créative. | L48: Retenu pour couverture de facette et formulation rendue directement concrète. | M48: PIP-BANK-0.4
A49: PIP-ENV-A-A2-008 | B49: A | C49: A2 | D49: ENV | E49: Évoluer dans un contexte où l’on peut concevoir des formes, des contenus ou des expériences avec une réelle liberté de choix. | F49: Évoluer dans un contexte où l’on conçoit des formes, contenus ou expériences avec une vraie marge de choix personnel. | G49: FAIBLE_A_MOYENNE | H49: FAIBLE | I49: MOYENNE | J49: RETRAIT_BANQUE72 | L49: Historique conservé ; item non nécessaire pour atteindre 12/dimension et ≥2/facette. | M49: PIP-BANK-0.3
A50: PIP-ACT-A-A3-009 | B50: A | C50: A3 | D50: ACT | E50: Écrire un texte pour transmettre une idée, une émotion ou un point de vue. | F50: Écrire un texte, un récit ou un message destiné à faire ressentir une idée, une émotion ou un point de vue. | G50: MOYENNE | H50: FAIBLE | I50: FORTE | J50: MAINTIEN_REECRIT | K50: Écrire un texte, un récit ou un message destiné à faire ressentir une idée, une émotion ou un point de vue. | L50: Retenu pour couverture de facette et formulation rendue directement concrète. | M50: PIP-BANK-0.4
A51: PIP-ACT-A-A3-010 | B51: A | C51: A3 | D51: ACT | E51: Mettre en récit un sujet pour le rendre vivant et expressif. | F51: Transformer un sujet factuel en récit vivant pour capter l’attention d’un public. | G51: MOYENNE | H51: FAIBLE | I51: FORTE | J51: MAINTIEN_REECRIT | K51: Transformer un sujet factuel en récit vivant pour capter l’attention d’un public. | L51: Retenu pour couverture de facette et formulation rendue directement concrète. | M51: PIP-BANK-0.4
A52: PIP-SIT-A-A3-011 | B52: A | C52: A3 | D52: SIT | E52: Trouver une manière personnelle de raconter ou de représenter une histoire, une idée ou une expérience. | F52: Choisir une manière personnelle de raconter ou représenter une expérience afin qu’elle ait une tonalité propre. | G52: FAIBLE_A_MOYENNE | H52: FAIBLE | I52: FORTE | J52: RETRAIT_BANQUE72 | L52: Historique conservé ; item non nécessaire pour atteindre 12/dimension et ≥2/facette. | M52: PIP-BANK-0.3
A53: PIP-ENV-A-A3-012 | B53: A | C53: A3 | D53: ENV | E53: Travailler dans un contexte où l’expression par les mots, les images, le son ou la mise en scène occupe une place importante. | F53: Travailler dans un environnement où les mots, les images, le son ou la mise en scène servent régulièrement à s’exprimer. | G53: FAIBLE_A_MOYENNE | H53: FAIBLE | I53: MOYENNE | J53: RETRAIT_BANQUE72 | L53: Historique conservé ; item non nécessaire pour atteindre 12/dimension et ≥2/facette. | M53: PIP-BANK-0.3
A54: PIP-ACT-A-A4-013 | B54: A | C54: A4 | D54: ACT | E54: Créer une composition visuelle en jouant sur les formes, les images ou les couleurs. | F54: Créer une affiche, une illustration ou une composition visuelle en jouant librement sur les formes et les couleurs. | G54: MOYENNE | H54: FAIBLE | I54: FORTE | J54: MAINTIEN_REECRIT | K54: Créer une affiche, une illustration ou une composition visuelle en jouant librement sur les formes et les couleurs. | L54: Retenu pour couverture de facette et formulation rendue directement concrète. | M54: PIP-BANK-0.4
A55: PIP-ACT-A-A4-014 | B55: A | C55: A4 | D55: ACT | E55: Imaginer une ambiance à partir de sons, d’images, de matières ou d’un espace. | F55: Imaginer l’ambiance d’un espace, d’un événement ou d’un contenu à partir de sons, d’images, de matières ou de lumière. | G55: MOYENNE | H55: FAIBLE | I55: FORTE | J55: MAINTIEN_REECRIT | K55: Imaginer l’ambiance d’un espace, d’un événement ou d’un contenu à partir de sons, d’images, de matières ou de lumière. | L55: Retenu pour couverture de facette et formulation rendue directement concrète. | M55: PIP-BANK-0.4
A56: PIP-SIT-A-A4-015 | B56: A | C56: A4 | D56: SIT | E56: Concevoir une expérience où l’effet visuel, sonore ou sensoriel compte autant que la fonction. | F56: Concevoir une expérience dans laquelle l’effet visuel, sonore ou sensoriel compte autant que sa fonction pratique. | G56: FAIBLE_A_MOYENNE | H56: FAIBLE | I56: FORTE | J56: RETRAIT_BANQUE72 | L56: Historique conservé ; item non nécessaire pour atteindre 12/dimension et ≥2/facette. | M56: PIP-BANK-0.3
A57: PIP-ENV-A-A4-016 | B57: A | C57: A4 | D57: ENV | E57: Évoluer dans un contexte où l’on crée régulièrement des contenus, des espaces ou des objets destinés à produire une impression visuelle ou sensorielle. | F57: Évoluer dans un contexte où l’on crée régulièrement des contenus ou des espaces destinés à produire une impression visuelle ou sensorielle. | G57: FAIBLE_A_MOYENNE | H57: FAIBLE | I57: MOYENNE | J57: RETRAIT_BANQUE72 | L57: Historique conservé ; item non nécessaire pour atteindre 12/dimension et ≥2/facette. | M57: PIP-BANK-0.3
A58: PIP-ACT-A-A5-017 | B58: A | C58: A5 | D58: ACT | E58: Explorer plusieurs pistes créatives avant de choisir celle qui convient le mieux. | F58: Explorer plusieurs pistes créatives pour un même projet avant de retenir celle qui exprime le mieux l’intention recherchée. | G58: MOYENNE | H58: FAIBLE | I58: FORTE | J58: MAINTIEN_REECRIT | K58: Explorer plusieurs pistes créatives pour un même projet avant de retenir celle qui exprime le mieux l’intention recherchée. | L58: Retenu pour couverture de facette et formulation rendue directement concrète. | M58: PIP-BANK-0.4
A59: PIP-ACT-A-A5-018 | B59: A | C59: A5 | D59: ACT | E59: Réinventer une manière habituelle de faire pour proposer une approche originale. | F59: Repenser une manière habituelle de présenter ou de réaliser quelque chose afin de proposer une approche originale. | G59: MOYENNE | H59: FAIBLE | I59: FORTE | J59: MAINTIEN_REECRIT | K59: Repenser une manière habituelle de présenter ou de réaliser quelque chose afin de proposer une approche originale. | L59: Retenu pour couverture de facette et formulation rendue directement concrète. | M59: PIP-BANK-0.4
A60: PIP-SIT-A-A5-019 | B60: A | C60: A5 | D60: SIT | E60: Travailler sur un problème pour lequel plusieurs réponses différentes peuvent être pertinentes. | F60: Travailler sur une demande ouverte pour laquelle plusieurs réponses créatives différentes peuvent être pertinentes. | G60: FAIBLE_A_MOYENNE | H60: A_SURVEILLER | I60: FORTE | J60: RETRAIT_BANQUE72 | L60: Historique conservé ; item non nécessaire pour atteindre 12/dimension et ≥2/facette. | M60: PIP-BANK-0.3
A61: PIP-ENV-A-A5-020 | B61: A | C61: A5 | D61: ENV | E61: Évoluer dans un contexte où les consignes laissent une place importante à l’interprétation personnelle et à l’expérimentation créative. | F61: Évoluer dans un environnement où les consignes laissent volontairement une large place à l’interprétation et à l’expérimentation créative. | G61: FAIBLE_A_MOYENNE | H61: FAIBLE | I61: MOYENNE | J61: RETRAIT_BANQUE72 | L61: Historique conservé ; item non nécessaire pour atteindre 12/dimension et ≥2/facette. | M61: PIP-BANK-0.3
A62: PIP-ACT-S-S1-001 | B62: S | C62: S1 | D62: ACT | E62: Expliquer un sujet à une personne pour l’aider à le comprendre. | F62: Expliquer une notion à une personne jusqu’à ce qu’elle puisse la comprendre par elle-même. | G62: MOYENNE | H62: FAIBLE | I62: FORTE | J62: MAINTIEN_REECRIT | K62: Expliquer une notion à une personne jusqu’à ce qu’elle puisse la comprendre par elle-même. | L62: Retenu pour couverture de facette et formulation rendue directement concrète. | M62: PIP-BANK-0.4
A63: PIP-ACT-S-S1-002 | B63: S | C63: S1 | D63: ACT | E63: Montrer à quelqu’un comment réaliser une tâche afin qu’il puisse ensuite la faire seul. | F63: Montrer étape par étape à quelqu’un comment réaliser une tâche pour qu’il puisse ensuite la refaire seul. | G63: MOYENNE | H63: FAIBLE | I63: FORTE | J63: MAINTIEN_REECRIT | K63: Montrer étape par étape à quelqu’un comment réaliser une tâche pour qu’il puisse ensuite la refaire seul. | L63: Retenu pour couverture de facette et formulation rendue directement concrète. | M63: PIP-BANK-0.4
A64: PIP-SIT-S-S1-003 | B64: S | C64: S1 | D64: SIT | E64: Adapter sa manière d’expliquer lorsqu’une personne ne comprend pas du premier coup. | F64: Une personne ne comprend pas une première explication : chercher une autre manière de lui présenter les choses. | G64: FAIBLE_A_MOYENNE | H64: FAIBLE | I64: FORTE | J64: MAINTIEN_REECRIT | K64: Une personne ne comprend pas une première explication : chercher une autre manière de lui présenter les choses. | L64: Retenu pour couverture de facette et formulation rendue directement concrète. | M64: PIP-BANK-0.4
A65: PIP-ENV-S-S1-004 | B65: S | C65: S1 | D65: ENV | E65: Travailler dans un contexte où l’on aide régulièrement d’autres personnes à apprendre ou à progresser. | F65: Travailler dans un contexte où l’on consacre régulièrement du temps à aider d’autres personnes à apprendre ou progresser. | G65: FAIBLE_A_MOYENNE | H65: FAIBLE | I65: MOYENNE | J65: RETRAIT_BANQUE72 | L65: Historique conservé ; item non nécessaire pour atteindre 12/dimension et ≥2/facette. | M65: PIP-BANK-0.3
A66: PIP-ACT-S-S2-005 | B66: S | C66: S2 | D66: ACT | E66: Accompagner une personne dans la réalisation d’un objectif qui compte pour elle. | F66: Accompagner une personne dans les étapes nécessaires pour atteindre un objectif qui compte pour elle. | G66: MOYENNE | H66: FAIBLE | I66: FORTE | J66: MAINTIEN_REECRIT | K66: Accompagner une personne dans les étapes nécessaires pour atteindre un objectif qui compte pour elle. | L66: Retenu pour couverture de facette et formulation rendue directement concrète. | M66: PIP-BANK-0.4
A67: PIP-ACT-S-S2-006 | B67: S | C67: S2 | D67: ACT | E67: Soutenir quelqu’un qui rencontre une difficulté dans son parcours. | F67: Soutenir quelqu’un qui traverse une difficulté professionnelle ou personnelle liée à son parcours. | G67: MOYENNE | H67: FAIBLE | I67: FORTE | J67: MAINTIEN_REECRIT | K67: Soutenir quelqu’un qui traverse une difficulté professionnelle ou personnelle liée à son parcours. | L67: Retenu pour couverture de facette et formulation rendue directement concrète. | M67: PIP-BANK-0.4
A68: PIP-SIT-S-S2-007 | B68: S | C68: S2 | D68: SIT | E68: Être aux côtés d’une personne pendant une période de changement et l’aider à avancer. | F68: Être présent auprès d’une personne pendant un changement important et l’aider à avancer progressivement. | G68: FAIBLE_A_MOYENNE | H68: FAIBLE | I68: FORTE | J68: MAINTIEN_REECRIT | K68: Être présent auprès d’une personne pendant un changement important et l’aider à avancer progressivement. | L68: Retenu pour couverture de facette et formulation rendue directement concrète. | M68: PIP-BANK-0.4
A69: PIP-ENV-S-S2-008 | B69: S | C69: S2 | D69: ENV | E69: Évoluer dans un contexte où une part importante du travail consiste à soutenir directement des personnes dans leur progression. | F69: Évoluer dans un contexte où une part importante du travail consiste à soutenir directement des personnes dans leur progression. | G69: FAIBLE_A_MOYENNE | H69: FAIBLE | I69: MOYENNE | J69: RETRAIT_BANQUE72 | L69: Historique conservé ; item non nécessaire pour atteindre 12/dimension et ≥2/facette. | M69: PIP-BANK-0.3
A70: PIP-ACT-S-S3-009 | B70: S | C70: S3 | D70: ACT | E70: Écouter la situation d’une personne puis l’aider à identifier les options qui s’offrent à elle. | F70: Écouter la situation d’une personne puis l’aider à repérer les différentes options possibles. | G70: MOYENNE | H70: A_SURVEILLER | I70: FORTE | J70: MAINTIEN_REECRIT | K70: Écouter la situation d’une personne puis l’aider à repérer les différentes options possibles. | L70: Retenu pour couverture de facette et formulation rendue directement concrète. | M70: PIP-BANK-0.4
A71: PIP-ACT-S-S3-010 | B71: S | C71: S3 | D71: ACT | E71: Donner des informations utiles pour aider quelqu’un à faire un choix. | F71: Donner à quelqu’un les informations utiles pour qu’il puisse prendre lui-même une décision éclairée. | G71: MOYENNE | H71: FAIBLE | I71: FORTE | J71: MAINTIEN_REECRIT | K71: Donner à quelqu’un les informations utiles pour qu’il puisse prendre lui-même une décision éclairée. | L71: Retenu pour couverture de facette et formulation rendue directement concrète. | M71: PIP-BANK-0.4
A72: PIP-SIT-S-S3-011 | B72: S | C72: S3 | D72: SIT | E72: Aider une personne indécise à clarifier ce qui lui conviendrait le mieux sans décider à sa place. | F72: Une personne hésite entre plusieurs choix : l’aider à clarifier ce qui lui convient sans choisir à sa place. | G72: FAIBLE_A_MOYENNE | H72: A_SURVEILLER | I72: FORTE | J72: RETRAIT_BANQUE72 | L72: Historique conservé ; item non nécessaire pour atteindre 12/dimension et ≥2/facette. | M72: PIP-BANK-0.3
A73: PIP-ENV-S-S3-012 | B73: S | C73: S3 | D73: ENV | E73: Travailler dans un contexte où l’on conseille et oriente régulièrement des personnes en fonction de leur situation. | F73: Travailler dans un contexte où l’on conseille et oriente régulièrement des personnes selon leur situation. | G73: FAIBLE_A_MOYENNE | H73: FAIBLE | I73: MOYENNE | J73: RETRAIT_BANQUE72 | L73: Historique conservé ; item non nécessaire pour atteindre 12/dimension et ≥2/facette. | M73: PIP-BANK-0.3
A74: PIP-ACT-S-S4-013 | B74: S | C74: S4 | D74: ACT | E74: Prendre soin d’une personne qui a besoin d’aide pour préserver ou retrouver son bien-être. | F74: Aider concrètement une personne fragilisée à préserver ou retrouver son confort, sa santé ou son autonomie. | G74: MOYENNE | H74: FAIBLE | I74: FORTE | J74: MAINTIEN_REECRIT | K74: Aider concrètement une personne fragilisée à préserver ou retrouver son confort, sa santé ou son autonomie. | L74: Retenu pour couverture de facette et formulation rendue directement concrète. | M74: PIP-BANK-0.4
A75: PIP-ACT-S-S4-014 | B75: S | C75: S4 | D75: ACT | E75: Réaliser des gestes d’assistance destinés à protéger la santé ou la sécurité d’une personne. | F75: Réaliser des gestes d’assistance ou de prévention destinés à protéger la santé ou la sécurité d’une personne. | G75: MOYENNE | H75: FAIBLE | I75: FORTE | J75: MAINTIEN_REECRIT | K75: Réaliser des gestes d’assistance ou de prévention destinés à protéger la santé ou la sécurité d’une personne. | L75: Retenu pour couverture de facette et formulation rendue directement concrète. | M75: PIP-BANK-0.4
A76: PIP-SIT-S-S4-015 | B76: S | C76: S4 | D76: SIT | E76: Intervenir auprès d’une personne fragilisée afin de l’aider à retrouver davantage d’autonomie. | F76: Intervenir auprès d’une personne temporairement en difficulté afin de l’aider à retrouver davantage d’autonomie. | G76: FAIBLE_A_MOYENNE | H76: FAIBLE | I76: FORTE | J76: RETRAIT_BANQUE72 | L76: Historique conservé ; item non nécessaire pour atteindre 12/dimension et ≥2/facette. | M76: PIP-BANK-0.3
A77: PIP-ENV-S-S4-016 | B77: S | C77: S4 | D77: ENV | E77: Évoluer dans un contexte où l’on contribue directement à la santé, au bien-être ou à la sécurité des personnes. | F77: Évoluer dans un contexte où l’on contribue directement au bien-être, à la santé ou à la sécurité des personnes. | G77: FAIBLE_A_MOYENNE | H77: FAIBLE | I77: MOYENNE | J77: RETRAIT_BANQUE72 | L77: Historique conservé ; item non nécessaire pour atteindre 12/dimension et ≥2/facette. | M77: PIP-BANK-0.3
A78: PIP-ACT-S-S5-017 | B78: S | C78: S5 | D78: ACT | E78: Accueillir une personne et l’aider à obtenir le service dont elle a besoin. | F78: Accueillir une personne, comprendre ce dont elle a besoin et l’aider à obtenir le service recherché. | G78: MOYENNE | H78: FAIBLE | I78: FORTE | J78: MAINTIEN_REECRIT | K78: Accueillir une personne, comprendre ce dont elle a besoin et l’aider à obtenir le service recherché. | L78: Retenu pour couverture de facette et formulation rendue directement concrète. | M78: PIP-BANK-0.4
A79: PIP-ACT-S-S5-018 | B79: S | C79: S5 | D79: ACT | E79: Répondre concrètement à une demande afin de faciliter la démarche d’une personne. | F79: Répondre concrètement à la demande d’un usager ou d’un client afin de lui faciliter une démarche. | G79: MOYENNE | H79: FAIBLE | I79: FORTE | J79: MAINTIEN_REECRIT | K79: Répondre concrètement à la demande d’un usager ou d’un client afin de lui faciliter une démarche. | L79: Retenu pour couverture de facette et formulation rendue directement concrète. | M79: PIP-BANK-0.4
A80: PIP-SIT-S-S5-019 | B80: S | C80: S5 | D80: SIT | E80: Aider un usager ou un client qui ne sait pas comment accomplir une démarche. | F80: Une personne ne sait pas comment accomplir une démarche : l’accompagner jusqu’à ce qu’elle sache quoi faire. | G80: FAIBLE_A_MOYENNE | H80: FAIBLE | I80: FORTE | J80: RETRAIT_BANQUE72 | L80: Historique conservé ; item non nécessaire pour atteindre 12/dimension et ≥2/facette. | M80: PIP-BANK-0.3
A81: PIP-ENV-S-S5-020 | B81: S | C81: S5 | D81: ENV | E81: Travailler dans un contexte où l’on rend directement des services utiles à des personnes aux besoins variés. | F81: Travailler dans un environnement où l’on rend directement des services utiles à des personnes aux besoins variés. | G81: FAIBLE_A_MOYENNE | H81: FAIBLE | I81: MOYENNE | J81: RETRAIT_BANQUE72 | L81: Historique conservé ; item non nécessaire pour atteindre 12/dimension et ≥2/facette. | M81: PIP-BANK-0.3
A82: PIP-ACT-E-E1-001 | B82: E | C82: E1 | D82: ACT | E82: Lancer un nouveau projet à partir d’une idée ou d’une opportunité. | F82: Lancer un nouveau service, une activité ou un projet à partir d’une idée ou d’une opportunité identifiée. | G82: MOYENNE | H82: FAIBLE | I82: FORTE | J82: MAINTIEN_REECRIT | K82: Lancer un nouveau service, une activité ou un projet à partir d’une idée ou d’une opportunité identifiée. | L82: Retenu pour couverture de facette et formulation rendue directement concrète. | M82: PIP-BANK-0.4
A83: PIP-ACT-E-E1-002 | B83: E | C83: E1 | D83: ACT | E83: Faire progresser un projet en identifiant de nouvelles possibilités de développement. | F83: Chercher de nouvelles possibilités pour développer un projet, une activité ou une offre existante. | G83: MOYENNE | H83: FAIBLE | I83: FORTE | J83: MAINTIEN_REECRIT | K83: Chercher de nouvelles possibilités pour développer un projet, une activité ou une offre existante. | L83: Retenu pour couverture de facette et formulation rendue directement concrète. | M83: PIP-BANK-0.4
A84: PIP-SIT-E-E1-003 | B84: E | C84: E1 | D84: SIT | E84: Voir une opportunité et prendre l’initiative de la transformer en projet concret. | F84: Repérer une opportunité et prendre l’initiative de réunir les moyens nécessaires pour en faire un projet concret. | G84: FAIBLE_A_MOYENNE | H84: FAIBLE | I84: FORTE | J84: MAINTIEN_REECRIT | K84: Repérer une opportunité et prendre l’initiative de réunir les moyens nécessaires pour en faire un projet concret. | L84: Retenu pour couverture de facette et formulation rendue directement concrète. | M84: PIP-BANK-0.4
A85: PIP-ENV-E-E1-004 | B85: E | C85: E1 | D85: ENV | E85: Évoluer dans un contexte où l’on peut proposer des initiatives et faire avancer de nouveaux projets. | F85: Évoluer dans un environnement où l’on peut proposer des initiatives et faire démarrer de nouveaux projets. | G85: FAIBLE_A_MOYENNE | H85: FAIBLE | I85: MOYENNE | J85: RETRAIT_BANQUE72 | L85: Historique conservé ; item non nécessaire pour atteindre 12/dimension et ≥2/facette. | M85: PIP-BANK-0.3
A86: PIP-ACT-E-E2-005 | B86: E | C86: E2 | D86: ACT | E86: Présenter une proposition de façon à donner envie d’y adhérer. | F86: Présenter une proposition à un client, une équipe ou un partenaire de façon à susciter son adhésion. | G86: MOYENNE | H86: FAIBLE | I86: FORTE | J86: MAINTIEN_REECRIT | K86: Présenter une proposition à un client, une équipe ou un partenaire de façon à susciter son adhésion. | L86: Retenu pour couverture de facette et formulation rendue directement concrète. | M86: PIP-BANK-0.4
A87: PIP-ACT-E-E2-006 | B87: E | C87: E2 | D87: ACT | E87: Promouvoir un produit, un service ou une idée auprès d’un public. | F87: Promouvoir un produit, un service, un projet ou une idée auprès d’un public susceptible d’être intéressé. | G87: MOYENNE | H87: FAIBLE | I87: FORTE | J87: MAINTIEN_REECRIT | K87: Promouvoir un produit, un service, un projet ou une idée auprès d’un public susceptible d’être intéressé. | L87: Retenu pour couverture de facette et formulation rendue directement concrète. | M87: PIP-BANK-0.4
A88: PIP-SIT-E-E2-007 | B88: E | C88: E2 | D88: SIT | E88: Défendre une proposition devant des personnes qui hésitent afin d’obtenir leur adhésion. | F88: Défendre une proposition devant des personnes hésitantes afin de les convaincre de la retenir. | G88: FAIBLE_A_MOYENNE | H88: FAIBLE | I88: FORTE | J88: MAINTIEN_REECRIT | K88: Défendre une proposition devant des personnes hésitantes afin de les convaincre de la retenir. | L88: Retenu pour couverture de facette et formulation rendue directement concrète. | M88: PIP-BANK-0.4
A89: PIP-ENV-E-E2-008 | B89: E | C89: E2 | D89: ENV | E89: Travailler dans un contexte où il faut régulièrement présenter, promouvoir ou faire accepter des propositions. | F89: Travailler dans un contexte où il faut régulièrement présenter, promouvoir ou faire accepter des propositions. | G89: FAIBLE_A_MOYENNE | H89: FAIBLE | I89: MOYENNE | J89: RETRAIT_BANQUE72 | L89: Historique conservé ; item non nécessaire pour atteindre 12/dimension et ≥2/facette. | M89: PIP-BANK-0.3
A90: PIP-ACT-E-E3-009 | B90: E | C90: E3 | D90: ACT | E90: Négocier les conditions d’un accord entre plusieurs parties. | F90: Négocier avec plusieurs parties les conditions d’un accord afin de parvenir à une solution acceptable. | G90: MOYENNE | H90: FAIBLE | I90: FORTE | J90: MAINTIEN_REECRIT | K90: Négocier avec plusieurs parties les conditions d’un accord afin de parvenir à une solution acceptable. | L90: Retenu pour couverture de facette et formulation rendue directement concrète. | M90: PIP-BANK-0.4
A91: PIP-ACT-E-E3-010 | B91: E | C91: E3 | D91: ACT | E91: Chercher un compromis lorsque des personnes défendent des intérêts différents. | F91: Rechercher un compromis lorsque deux personnes ou organisations défendent des intérêts différents. | G91: MOYENNE | H91: A_SURVEILLER | I91: FORTE | J91: MAINTIEN_REECRIT | K91: Rechercher un compromis lorsque deux personnes ou organisations défendent des intérêts différents. | L91: Retenu pour couverture de facette et formulation rendue directement concrète. | M91: PIP-BANK-0.4
A92: PIP-SIT-E-E3-011 | B92: E | C92: E3 | D92: SIT | E92: Conduire une discussion où chacun a des attentes différentes afin d’aboutir à un accord. | F92: Conduire une discussion où chacun a ses contraintes afin d’aboutir à un accord concret. | G92: FAIBLE_A_MOYENNE | H92: FAIBLE | I92: FORTE | J92: RETRAIT_BANQUE72 | L92: Historique conservé ; item non nécessaire pour atteindre 12/dimension et ≥2/facette. | M92: PIP-BANK-0.3
A93: PIP-ENV-E-E3-012 | B93: E | C93: E3 | D93: ENV | E93: Évoluer dans un contexte où la négociation et la recherche d’accords occupent une place importante. | F93: Évoluer dans un environnement où la négociation et la recherche d’accords font partie du travail courant. | G93: FAIBLE_A_MOYENNE | H93: FAIBLE | I93: MOYENNE | J93: RETRAIT_BANQUE72 | L93: Historique conservé ; item non nécessaire pour atteindre 12/dimension et ≥2/facette. | M93: PIP-BANK-0.3
A94: PIP-ACT-E-E4-013 | B94: E | C94: E4 | D94: ACT | E94: Coordonner le travail de plusieurs personnes pour faire avancer un projet. | F94: Coordonner plusieurs personnes, répartir les responsabilités et suivre l’avancement d’un projet. | G94: MOYENNE | H94: A_SURVEILLER | I94: FORTE | J94: MAINTIEN_REECRIT | K94: Coordonner plusieurs personnes, répartir les responsabilités et suivre l’avancement d’un projet. | L94: Retenu pour couverture de facette et formulation rendue directement concrète. | M94: PIP-BANK-0.4
A95: PIP-ACT-E-E4-014 | B95: E | C95: E4 | D95: ACT | E95: Prendre des décisions qui orientent l’action d’une équipe ou d’un projet. | F95: Prendre une décision qui donne une direction claire à une équipe ou à un projet. | G95: MOYENNE | H95: FAIBLE | I95: FORTE | J95: MAINTIEN_REECRIT | K95: Prendre une décision qui donne une direction claire à une équipe ou à un projet. | L95: Retenu pour couverture de facette et formulation rendue directement concrète. | M95: PIP-BANK-0.4
A96: PIP-SIT-E-E4-015 | B96: E | C96: E4 | D96: SIT | E96: Arbitrer entre plusieurs priorités lorsque le groupe attend une décision pour continuer. | F96: Plusieurs priorités s’opposent : arbitrer et décider pour permettre au groupe de continuer. | G96: FAIBLE_A_MOYENNE | H96: FAIBLE | I96: FORTE | J96: RETRAIT_BANQUE72 | L96: Historique conservé ; item non nécessaire pour atteindre 12/dimension et ≥2/facette. | M96: PIP-BANK-0.3
A97: PIP-ENV-E-E4-016 | B97: E | C97: E4 | D97: ENV | E97: Travailler dans un contexte où l’on assume régulièrement la responsabilité de décisions et de coordination. | F97: Travailler dans un contexte où l’on assume régulièrement des décisions, des arbitrages et la coordination d’autres personnes. | G97: FAIBLE_A_MOYENNE | H97: FAIBLE | I97: MOYENNE | J97: RETRAIT_BANQUE72 | L97: Historique conservé ; item non nécessaire pour atteindre 12/dimension et ≥2/facette. | M97: PIP-BANK-0.3
A98: PIP-ACT-E-E5-017 | B98: E | C98: E5 | D98: ACT | E98: Prendre la parole pour représenter une organisation, un projet ou une cause. | F98: Prendre la parole au nom d’une organisation, d’un projet ou d’une cause devant des interlocuteurs externes. | G98: MOYENNE | H98: FAIBLE | I98: FORTE | J98: MAINTIEN_REECRIT | K98: Prendre la parole au nom d’une organisation, d’un projet ou d’une cause devant des interlocuteurs externes. | L98: Retenu pour couverture de facette et formulation rendue directement concrète. | M98: PIP-BANK-0.4
A99: PIP-ACT-E-E5-018 | B99: E | C99: E5 | D99: ACT | E99: Mobiliser plusieurs personnes autour d’un objectif commun. | F99: Mobiliser plusieurs personnes autour d’un objectif et leur donner envie de contribuer. | G99: MOYENNE | H99: FAIBLE | I99: FORTE | J99: MAINTIEN_REECRIT | K99: Mobiliser plusieurs personnes autour d’un objectif et leur donner envie de contribuer. | L99: Retenu pour couverture de facette et formulation rendue directement concrète. | M99: PIP-BANK-0.4
A100: PIP-SIT-E-E5-019 | B100: E | C100: E5 | D100: SIT | E100: Faire adhérer un groupe à une orientation et l’encourager à se mettre en action. | F100: Présenter une orientation à un groupe, obtenir son adhésion et l’inciter à passer à l’action. | G100: FAIBLE_A_MOYENNE | H100: FAIBLE | I100: FORTE | J100: RETRAIT_BANQUE72 | L100: Historique conservé ; item non nécessaire pour atteindre 12/dimension et ≥2/facette. | M100: PIP-BANK-0.3
...

Sheet DIMENSIONS
A1: DIMENSIONS & FACETTES RIASEC
A2: 6 dimensions / 30 facettes — référentiel V1.0
A4: facette_id | B4: dimension | C4: dimension_nom | D4: facette_nom | E4: definition_dimension | F4: noyau_dimension | G4: ce_que_le_score_ne_mesure_pas | H4: description_facette | I4: verbes_indicatifs | J4: statut
A5: R1 | B5: R | C5: Réaliste | D5: Construire / fabriquer / transformer | E5: Attirance pour des activités où l’on agit concrètement sur le monde physique : construire, fabriquer, installer, réparer, utiliser des outils ou équipements, intervenir sur des matières, objets, systèmes, organismes ou environnements réels, et résoudre des problèmes pratiques par l’action. | F5: Action concrète sur le réel et résultat tangible. | G5: Ni dextérité, ni niveau technique, ni goût exclusif pour le travail manuel. | H5: Création ou transformation concrète d’objets, structures ou matières. | I5: Assembler, fabriquer, construire, façonner, transformer | J5: ACTIF
A6: R2 | B6: R | C6: Réaliste | D6: Installer / réparer / maintenir | E6: Attirance pour des activités où l’on agit concrètement sur le monde physique : construire, fabriquer, installer, réparer, utiliser des outils ou équipements, intervenir sur des matières, objets, systèmes, organismes ou environnements réels, et résoudre des problèmes pratiques par l’action. | F6: Action concrète sur le réel et résultat tangible. | G6: Ni dextérité, ni niveau technique, ni goût exclusif pour le travail manuel. | H6: Diagnostic pratique suivi d’une intervention concrète visant le fonctionnement. | I6: Installer, régler, réparer, entretenir, remettre en service | J6: ACTIF
A7: R3 | B7: R | C7: Réaliste | D7: Outils / machines / équipements | E7: Attirance pour des activités où l’on agit concrètement sur le monde physique : construire, fabriquer, installer, réparer, utiliser des outils ou équipements, intervenir sur des matières, objets, systèmes, organismes ou environnements réels, et résoudre des problèmes pratiques par l’action. | F7: Action concrète sur le réel et résultat tangible. | G7: Ni dextérité, ni niveau technique, ni goût exclusif pour le travail manuel. | H7: Usage direct d’outils, machines, instruments ou équipements techniques. | I7: Manipuler, piloter, régler, utiliser un équipement | J7: ACTIF
A8: R4 | B8: R | C8: Réaliste | D8: Terrain / environnement concret | E8: Attirance pour des activités où l’on agit concrètement sur le monde physique : construire, fabriquer, installer, réparer, utiliser des outils ou équipements, intervenir sur des matières, objets, systèmes, organismes ou environnements réels, et résoudre des problèmes pratiques par l’action. | F8: Action concrète sur le réel et résultat tangible. | G8: Ni dextérité, ni niveau technique, ni goût exclusif pour le travail manuel. | H8: Action dans des contextes physiques, extérieurs ou directement liés à un environnement réel. | I8: Intervenir sur site, travailler dehors, se déplacer sur le terrain | J8: ACTIF
A9: R5 | B9: R | C9: Réaliste | D9: Vivant / matière / action physique | E9: Attirance pour des activités où l’on agit concrètement sur le monde physique : construire, fabriquer, installer, réparer, utiliser des outils ou équipements, intervenir sur des matières, objets, systèmes, organismes ou environnements réels, et résoudre des problèmes pratiques par l’action. | F9: Action concrète sur le réel et résultat tangible. | G9: Ni dextérité, ni niveau technique, ni goût exclusif pour le travail manuel. | H9: Activités pratiques impliquant plantes, animaux, matière, effort corporel ou intervention physique finalisée. | I9: S’occuper d’animaux ou cultures, manipuler des matériaux | J9: ACTIF
A10: I1 | B10: I | C10: Investigateur | D10: Observer / examiner | E10: Attirance pour des activités où l’on cherche à comprendre, examiner, expliquer ou résoudre des questions en mobilisant observation, analyse, raisonnement, recherche d’informations, expérimentation ou mise en relation d’idées et de faits. | F10: Comprendre, rechercher, expliquer et résoudre. | G10: Ni intelligence, ni niveau scolaire, ni étiquette de scientifique. | H10: Examen attentif de faits, phénomènes, informations ou situations. | I10: Observer, examiner, comparer, repérer, documenter | J10: ACTIF
A11: I2 | B11: I | C11: Investigateur | D11: Analyser / raisonner | E11: Attirance pour des activités où l’on cherche à comprendre, examiner, expliquer ou résoudre des questions en mobilisant observation, analyse, raisonnement, recherche d’informations, expérimentation ou mise en relation d’idées et de faits. | F11: Comprendre, rechercher, expliquer et résoudre. | G11: Ni intelligence, ni niveau scolaire, ni étiquette de scientifique. | H11: Décomposition d’un problème et mise en relation d’informations. | I11: Analyser, relier, déduire, interpréter, modéliser | J11: ACTIF
A12: I3 | B12: I | C12: Investigateur | D12: Rechercher / enquêter | E12: Attirance pour des activités où l’on cherche à comprendre, examiner, expliquer ou résoudre des questions en mobilisant observation, analyse, raisonnement, recherche d’informations, expérimentation ou mise en relation d’idées et de faits. | F12: Comprendre, rechercher, expliquer et résoudre. | G12: Ni intelligence, ni niveau scolaire, ni étiquette de scientifique. | H12: Recherche d’informations, preuves ou explications lorsqu’une question reste ouverte. | I12: Rechercher, enquêter, vérifier, approfondir, confronter des sources | J12: ACTIF
A13: I4 | B13: I | C13: Investigateur | D13: Expérimenter / tester | E13: Attirance pour des activités où l’on cherche à comprendre, examiner, expliquer ou résoudre des questions en mobilisant observation, analyse, raisonnement, recherche d’informations, expérimentation ou mise en relation d’idées et de faits. | F13: Comprendre, rechercher, expliquer et résoudre. | G13: Ni intelligence, ni niveau scolaire, ni étiquette de scientifique. | H13: Mise à l’épreuve d’hypothèses ou solutions afin d’apprendre du résultat. | I13: Tester, expérimenter, mesurer, essayer | J13: ACTIF
A14: I5 | B14: I | C14: Investigateur | D14: Résoudre / expliquer | E14: Attirance pour des activités où l’on cherche à comprendre, examiner, expliquer ou résoudre des questions en mobilisant observation, analyse, raisonnement, recherche d’informations, expérimentation ou mise en relation d’idées et de faits. | F14: Comprendre, rechercher, expliquer et résoudre. | G14: Ni intelligence, ni niveau scolaire, ni étiquette de scientifique. | H14: Problèmes intellectuels dont l’enjeu est de comprendre, expliquer ou trouver une solution fondée. | I14: Résoudre, expliquer, diagnostiquer intellectuellement, conceptualiser | J14: ACTIF
A15: A1 | B15: A | C15: Artistique | D15: Imaginer / inventer | E15: Attirance pour des activités où l’on imagine, crée, compose, conçoit ou exprime quelque chose avec un espace d’originalité, d’interprétation, de sensibilité ou de choix personnel. | F15: Créer, concevoir ou exprimer avec ouverture. | G15: Ni talent artistique, ni originalité personnelle mesurée, ni obligation de métier culturel. | H15: Génération d’idées, concepts, scénarios ou formes nouvelles. | I15: Imaginer, inventer, proposer, explorer, détourner | J15: ACTIF
... A34: C5 | B34: C | C34: Conventionnel | D34: Traiter / suivre dossiers, données et opérations | E34: Attirance pour des activités où l’on organise, enregistre, classe, traite, vérifie ou suit des informations, données, dossiers, transactions ou ressources dans un cadre structuré. | F34: Structurer, fiabiliser et suivre méthodiquement. | G34: Ni rigidité, ni conscienciosité, ni routine, ni compétence administrative. | H34: Faire avancer méthodiquement dossiers, données, opérations ou transactions en assurant leur suivi. | I34: Traiter, suivre, planifier des échéances, rapprocher, clôturer | J34: ACTIF

Sheet QUESTIONS
A1: BANQUE EXPÉRIMENTALE PIP — QUESTIONS
A2: 120 items historiques conservés. V0.5 : décision documentée de passage à 72 items ; les formulations V0.4 restent intactes dans cette feuille.
A4: item_id | B4: item_version | C4: statut | D4: date_creation | E4: date_modification | F4: bloc | G4: famille_formulation | H4: dimension | I4: facette | J4: dimensions_concurrentes | K4: texte_fr | L4: reponse_1 | M4: reponse_2 | N4: reponse_3 | O4: reponse_4 | P4: reponse_5 | Q4: score_1 | R4: score_2 | S4: score_3 | T4: score_4 | U4: score_5 | V4: justification_dimension | W4: justification_facette | X4: commentaire_concepteur | Y4: risque_genre | Z4: risque_age_generation | AA4: risque_origine_culturelle_sociale | AB4: risque_niveau_etudes | AC4: risque_langue_litteratie | AD4: risque_accessibilite | AE4: risque_familiarite_numerique | AF4: risque_prestige | AG4: risque_familiarite_sectorielle | AH4: risque_desirabilite | AI4: risque_hybridite | AJ4: n_passations | AK4: indicateurs_item | AL4: decision_validation | AM4: motif_retrait | AN4: version_questionnaire_entree | AO4: version_questionnaire_sortie | AP4: controle_ligne
A5: PIP-ACT-R-R1-001 | B5: 0.2 | C5: PILOTE | D5: 08/09/2026 | E5: 08/09/2026 | F5: ACT | G5: Verbe d’action + objet/contexte | H5: R | I5: R1 | J5: A | K5: Assembler des éléments pour fabriquer un objet fonctionnel. | L5: Cela ne m’attire pas du tout | M5: Cela m’attire peu | N5: Je suis partagé(e) / sans préférence marquée | O5: Cela m’attire | P5: Cela m’attire beaucoup | Q5: 1 | R5: 2 | S5: 3 | T5: 4 | U5: 5 | V5: La formulation cible l’intérêt pour action concrète sur le réel et résultat tangible. Elle mobilise un comportement caractéristique de la dimension R (Réaliste) sans demander un niveau de compétence préalable. | W5: L’item relève de R1 — Construire / fabriquer / transformer : Création ou transformation concrète d’objets, structures ou matières. | X5: Revue méthodologique V0.3 : surveiller projection en cas de limitation physique ou sensorielle, familiarité avec le contexte professionnel au pilote. | Y5: FAIBLE | Z5: FAIBLE | AA5: FAIBLE | AB5: FAIBLE | AC5: FAIBLE | AD5: MOYEN | AE5: FAIBLE | AF5: FAIBLE | AG5: MOYEN | AH5: FAIBLE | AI5: FAIBLE | AJ5: 0 | AL5: RETENU_V0.5_REECRIT_CONCRET | AN5: PIP-BANK-0.3 | AO5: PIP-BANK-0.4 | AP5: =IF(OR(C5="PILOTE",C5="ACTIF"),IF(AND(A5<>"",H5<>"",I5<>"",K5<>"",V5<>"",W5<>""),"OK","A_COMPLETER"),"OK_STRUCTURE")
A6: PIP-ACT-R-R1-002 | B6: 0.2 | C6: PILOTE | D6: 08/09/2026 | E6: 08/09/2026 | F6: ACT | G6: Verbe d’action + objet/contexte | H6: R | I6: R1 | J6: A | K6: Transformer une matière ou un matériau pour lui donner une forme utile. | L6: Cela ne m’attire pas du tout | M6: Cela m’attire peu | N6: Je suis partagé(e) / sans préférence marquée | O6: Cela m’attire | P6: Cela m’attire beaucoup | Q6: 1 | R6: 2 | S6: 3 | T6: 4 | U6: 5 | V6: La formulation cible l’intérêt pour action concrète sur le réel et résultat tangible. Elle mobilise un comportement caractéristique de la dimension R (Réaliste) sans demander un niveau de compétence préalable. | W6: L’item relève de R1 — Construire / fabriquer / transformer : Création ou transformation concrète d’objets, structures ou matières. | X6: Revue méthodologique V0.3 : surveiller projection en cas de limitation physique ou sensorielle, familiarité avec le contexte professionnel au pilote. | Y6: FAIBLE | Z6: FAIBLE | AA6: FAIBLE | AB6: FAIBLE | AC6: FAIBLE | AD6: MOYEN | AE6: FAIBLE | AF6: FAIBLE | AG6: MOYEN | AH6: FAIBLE | AI6: FAIBLE | AJ6: 0 | AL6: RETENU_V0.5_REECRIT_CONCRET | AN6: PIP-BANK-0.3 | AO6: PIP-BANK-0.4 | AP6: =IF(OR(C6="PILOTE",C6="ACTIF"),IF(AND(A6<>"",H6<>"",I6<>"",K6<>"",V6<>"",W6<>""),"OK","A_COMPLETER"),"OK_STRUCTURE")
A7: PIP-SIT-R-R1-003 | B7: 0.2 | C7: PILOTE | D7: 08/09/2026 | E7: 08/09/2026 | F7: SIT | G7: Situation courte avec enjeu central | H7: R | I7: R1 | J7: A | K7: Prendre en charge la réalisation concrète d’un objet ou d’une structure à partir d’éléments séparés. | L7: Cela ne m’attire pas du tout | M7: Cela m’attire peu | N7: Je suis partagé(e) / sans préférence marquée | O7: Cela m’attire | P7: Cela m’attire beaucoup | Q7: 1 | R7: 2 | S7: 3 | T7: 4 | U7: 5 | V7: La formulation cible l’intérêt pour action concrète sur le réel et résultat tangible. Elle mobilise un comportement caractéristique de la dimension R (Réaliste) sans demander un niveau de compétence préalable. | W7: L’item relève de R1 — Construire / fabriquer / transformer : Création ou transformation concrète d’objets, structures ou matières. | X7: Revue méthodologique V0.3 : surveiller projection en cas de limitation physique ou sensorielle, familiarité avec le contexte professionnel au pilote. | Y7: FAIBLE | Z7: FAIBLE | AA7: FAIBLE | AB7: FAIBLE | AC7: FAIBLE | AD7: MOYEN | AE7: FAIBLE | AF7: FAIBLE | AG7: MOYEN | AH7: FAIBLE | AI7: FAIBLE | AJ7: 0 | AL7: RETENU_V0.5_REECRIT_CONCRET | AN7: PIP-BANK-0.3 | AO7: PIP-BANK-0.4 | AP7: =IF(OR(C7="PILOTE",C7="ACTIF"),IF(AND(A7<>"",H7<>"",I7<>"",K7<>"",V7<>"",W7<>""),"OK","A_COMPLETER"),"OK_STRUCTURE")
A8: PIP-ENV-R-R1-004 | B8: 0.2 | C8: PILOTE | D8: 08/09/2026 | E8: 08/09/2026 | F8: ENV | G8: Contexte décrit par ce qu’il permet de faire | H8: R | I8: R1 | J8: A | K8: Travailler dans un contexte où l’on voit directement le résultat matériel de ce que l’on fabrique ou transforme. | L8: Cela ne m’attire pas du tout | M8: Cela m’attire peu | N8: Je suis partagé(e) / sans préférence marquée | O8: Cela m’attire | P8: Cela m’attire beaucoup | Q8: 1 | R8: 2 | S8: 3 | T8: 4 | U8: 5 | V8: La formulation cible l’intérêt pour action concrète sur le réel et résultat tangible. Elle mobilise un comportement caractéristique de la dimension R (Réaliste) sans demander un niveau de compétence préalable. | W8: L’item relève de R1 — Construire / fabriquer / transformer : Création ou transformation concrète d’objets, structures ou matières. | X8: Revue méthodologique V0.3 : surveiller projection en cas de limitation physique ou sensorielle, familiarité avec le contexte professionnel au pilote. | Y8: FAIBLE | Z8: FAIBLE | AA8: FAIBLE | AB8: FAIBLE | AC8: FAIBLE | AD8: MOYEN | AE8: FAIBLE | AF8: FAIBLE | AG8: MOYEN | AH8: FAIBLE | AI8: FAIBLE | AJ8: 0 | AL8: RETIRE_BANQUE72_HISTORIQUE_CONSERVE | AM8: Réduction méthodologique 120→72 : doublon de facette / priorité aux activités professionnelles observables et aux items à plus faible risque. | AN8: PIP-BANK-0.3 | AO8: PIP-BANK-0.3 | AP8: =IF(OR(C8="PILOTE",C8="ACTIF"),IF(AND(A8<>"",H8<>"",I8<>"",K8<>"",V8<>"",W8<>""),"OK","A_COMPLETER"),"OK_STRUCTURE")
A9: PIP-ACT-R-R2-005 | B9: 0.2 | C9: PILOTE | D9: 08/09/2026 | E9: 08/09/2026 | F9: ACT | G9: Verbe d’action + objet/contexte | H9: R | I9: R2 | J9: I | K9: Installer un équipement pour qu’il soit prêt à fonctionner. | L9: Cela ne m’attire pas du tout | M9: Cela m’attire peu | N9: Je suis partagé(e) / sans préférence marquée | O9: Cela m’attire | P9: Cela m’attire beaucoup | Q9: 1 | R9: 2 | S9: 3 | T9: 4 | U9: 5 | V9: La formulation cible l’intérêt pour action concrète sur le réel et résultat tangible. Elle mobilise un comportement caractéristique de la dimension R (Réaliste) sans demander un niveau de compétence préalable. | W9: L’item relève de R2 — Installer / réparer / maintenir : Diagnostic pratique suivi d’une intervention concrète visant le fonctionnement. | X9: Revue méthodologique V0.3 : surveiller projection en cas de limitation physique ou sensorielle, familiarité avec le contexte professionnel au pilote. | Y9: FAIBLE | Z9: FAIBLE | AA9: FAIBLE | AB9: FAIBLE | AC9: FAIBLE | AD9: MOYEN | AE9: FAIBLE | AF9: FAIBLE | AG9: MOYEN | AH9: FAIBLE | AI9: FAIBLE | AJ9: 0 | AL9: RETENU_V0.5_REECRIT_CONCRET | AN9: PIP-BANK-0.3 | AO9: PIP-BANK-0.4 | AP9: =IF(OR(C9="PILOTE",C9="ACTIF"),IF(AND(A9<>"",H9<>"",I9<>"",K9<>"",V9<>"",W9<>""),"OK","A_COMPLETER"),"OK_STRUCTURE")
A10: PIP-ACT-R-R2-006 | B10: 0.2 | C10: PILOTE | D10: 08/09/2026 | E10: 08/09/2026 | F10: ACT | G10: Verbe d’action + objet/contexte | H10: R | I10: R2 | J10: I | K10: Réparer un matériel qui ne fonctionne plus correctement. | L10: Cela ne m’attire pas du tout | M10: Cela m’attire peu | N10: Je suis partagé(e) / sans préférence marquée | O10: Cela m’attire | P10: Cela m’attire beaucoup | Q10: 1 | R10: 2 | S10: 3 | T10: 4 | U10: 5 | V10: La formulation cible l’intérêt pour action concrète sur le réel et résultat tangible. Elle mobilise un comportement caractéristique de la dimension R (Réaliste) sans demander un niveau de compétence préalable. | W10: L’item relève de R2 — Installer / réparer / maintenir : Diagnostic pratique suivi d’une intervention concrète visant le fonctionnement. | X10: Revue méthodologique V0.3 : surveiller projection en cas de limitation physique ou sensorielle, familiarité avec le contexte professionnel, frontière avec I au pilote. | Y10: FAIBLE | Z10: FAIBLE | AA10: FAIBLE | AB10: FAIBLE | AC10: FAIBLE | AD10: MOYEN | AE10: FAIBLE | AF10: FAIBLE | AG10: MOYEN | AH10: FAIBLE | AI10: MOYEN | AJ10: 0 | AL10: RETENU_V0.5_REECRIT_CONCRET | AN10: PIP-BANK-0.3 | AO10: PIP-BANK-0.4 | AP10: =IF(OR(C10="PILOTE",C10="ACTIF"),IF(AND(A10<>"",H10<>"",I10<>"",K10<>"",V10<>"",W10<>""),"OK","A_COMPLETER"),"OK_STRUCTURE")
A11: PIP-SIT-R-R2-007 | B11: 0.2 | C11: PILOTE | D11: 08/09/2026 | E11: 08/09/2026 | F11: SIT | G11: Situation courte avec enjeu central | H11: R | I11: R2 | J11: I | K11: Intervenir lorsqu’un équipement doit être réglé ou remis en service. | L11: Cela ne m’attire pas du tout | M11: Cela m’attire peu | N11: Je suis partagé(e) / sans préférence marquée | O11: Cela m’attire | P11: Cela m’attire beaucoup | Q11: 1 | R11: 2 | S11: 3 | T11: 4 | U11: 5 | V11: La formulation cible l’intérêt pour action concrète sur le réel et résultat tangible. Elle mobilise un comportement caractéristique de la dimension R (Réaliste) sans demander un niveau de compétence préalable. | W11: L’item relève de R2 — Installer / réparer / maintenir : Diagnostic pratique suivi d’une intervention concrète visant le fonctionnement. | X11: Revue méthodologique V0.3 : surveiller projection en cas de limitation physique ou sensorielle, familiarité avec le contexte professionnel, frontière avec I au pilote. | Y11: FAIBLE | Z11: FAIBLE | AA11: FAIBLE | AB11: FAIBLE | AC11: FAIBLE | AD11: MOYEN | AE11: FAIBLE | AF11: FAIBLE | AG11: MOYEN | AH11: FAIBLE | AI11: MOYEN | AJ11: 0 | AL11: RETIRE_BANQUE72_HISTORIQUE_CONSERVE | AM11: Réduction méthodologique 120→72 : doublon de facette / priorité aux activités professionnelles observables et aux items à plus faible risque. | AN11: PIP-BANK-0.3 | AO11: PIP-BANK-0.3 | AP11: =IF(OR(C11="PILOTE",C11="ACTIF"),IF(AND(A11<>"",H11<>"",I11<>"",K11<>"",V11<>"",W11<>""),"OK","A_COMPLETER"),"OK_STRUCTURE")
A12: PIP-ENV-R-R2-008 | B12: 0.2 | C12: PILOTE | D12: 08/09/2026 | E12: 08/09/2026 | F12: ENV | G12: Contexte décrit par ce qu’il permet de faire | H12: R | I12: R2 | J12: I | K12: Évoluer dans un contexte où une part importante du travail consiste à entretenir et remettre en fonctionnement des équipements. | L12: Cela ne m’attire pas du tout | M12: Cela m’attire peu | N12: Je suis partagé(e) / sans préférence marquée | O12: Cela m’attire | P12: Cela m’attire beaucoup | Q12: 1 | R12: 2 | S12: 3 | T12: 4 | U12: 5 | V12: La formulation cible l’intérêt pour action concrète sur le réel et résultat tangible. Elle mobilise un comportement caractéristique de la dimension R (Réaliste) sans demander un niveau de compétence préalable. | W12: L’item relève de R2 — Installer / réparer / maintenir : Diagnostic pratique suivi d’une intervention concrète visant le fonctionnement. | X12: Revue méthodologique V0.3 : surveiller projection en cas de limitation physique ou sensorielle, familiarité avec le contexte professionnel au pilote. | Y12: FAIBLE | Z12: FAIBLE | AA12: FAIBLE | AB12: FAIBLE | AC12: FAIBLE | AD12: MOYEN | AE12: FAIBLE | AF12: FAIBLE | AG12: MOYEN | AH12: FAIBLE | AI12: FAIBLE | AJ12: 0 | AL12: RETIRE_BANQUE72_HISTORIQUE_CONSERVE | AM12: Réduction méthodologique 120→72 : doublon de facette / priorité aux activités professionnelles observables et aux items à plus faible risque. | AN12: PIP-BANK-0.3 | AO12: PIP-BANK-0.3 | AP12: =IF(OR(C12="PILOTE",C12="ACTIF"),IF(AND(A12<>"",H12<>"",I12<>"",K12<>"",V12<>"",W12<>""),"OK","A_COMPLETER"),"OK_STRUCTURE")
A13: PIP-ACT-R-R3-009 | B13: 0.2 | C13: PILOTE | D13: 08/09/2026 | E13: 08/09/2026 | F13: ACT | G13: Verbe d’action + objet/contexte | H13: R | I13: R3 | J13: I | K13: Utiliser des outils pour réaliser une tâche concrète avec précision. | L13: Cela ne m’attire pas du tout | M13: Cela m’attire peu | N13: Je suis partagé(e) / sans préférence marquée | O13: Cela m’attire | P13: Cela m’attire beaucoup | Q13: 1 | R13: 2 | S13: 3 | T13: 4 | U13: 5 | V13: La formulation cible l’intérêt pour action concrète sur le réel et résultat tangible. Elle mobilise un comportement caractéristique de la dimension R (Réaliste) sans demander un niveau de compétence préalable. | W13: L’item relève de R3 — Outils / machines / équipements : Usage direct d’outils, machines, instruments ou équipements techniques. | X13: Revue méthodologique V0.3 : surveiller projection en cas de limitation physique ou sensorielle, familiarité avec le contexte professionnel au pilote. | Y13: FAIBLE | Z13: FAIBLE | AA13: FAIBLE | AB13: FAIBLE | AC13: FAIBLE | AD13: MOYEN | AE13: FAIBLE | AF13: FAIBLE | AG13: MOYEN | AH13: FAIBLE | AI13: FAIBLE | AJ13: 0 | AL13: RETENU_V0.5_REECRIT_CONCRET | AN13: PIP-BANK-0.3 | AO13: PIP-BANK-0.4 | AP13: =IF(OR(C13="PILOTE",C13="ACTIF"),IF(AND(A13<>"",H13<>"",I13<>"",K13<>"",V13<>"",W13<>""),"OK","A_COMPLETER"),"OK_STRUCTURE")
A14: PIP-ACT-R-R3-010 | B14: 0.2 | C14: PILOTE | D14: 08/09/2026 | E14: 08/09/2026 | F14: ACT | G14: Verbe d’action + objet/contexte | H14: R | I14: R3 | J14: I | K14: Piloter ou régler une machine pour obtenir le résultat attendu. | L14: Cela ne m’attire pas du tout | M14: Cela m’attire peu | N14: Je suis partagé(e) / sans préférence marquée | O14: Cela m’attire | P14: Cela m’attire beaucoup | Q14: 1 | R14: 2 | S14: 3 | T14: 4 | U14: 5 | V14: La formulation cible l’intérêt pour action concrète sur le réel et résultat tangible. Elle mobilise un comportement caractéristique de la dimension R (Réaliste) sans demander un niveau de compétence préalable. | W14: L’item relève de R3 — Outils / machines / équipements : Usage direct d’outils, machines, instruments ou équipements techniques. | X14: Revue méthodologique V0.3 : surveiller projection en cas de limitation physique ou sensorielle, familiarité avec le contexte professionnel au pilote. | Y14: FAIBLE | Z14: FAIBLE | AA14: FAIBLE | AB14: FAIBLE | AC14: FAIBLE | AD14: MOYEN | AE14: FAIBLE | AF14: FAIBLE | AG14: MOYEN | AH14: FAIBLE | AI14: FAIBLE | AJ14: 0 | AL14: RETENU_V0.5_REECRIT_CONCRET | AN14: PIP-BANK-0.3 | AO14: PIP-BANK-0.4 | AP14: =IF(OR(C14="PILOTE",C14="ACTIF"),IF(AND(A14<>"",H14<>"",I14<>"",K14<>"",V14<>"",W14<>""),"OK","A_COMPLETER"),"OK_STRUCTURE")
A15: PIP-SIT-R-R3-011 | B15: 0.2 | C15: PILOTE | D15: 08/09/2026 | E15: 08/09/2026 | F15: SIT | G15: Situation courte avec enjeu central | H15: R | I15: R3 | J15: I | K15: Prendre en charge une tâche qui nécessite de manipuler directement un appareil ou un équipement. | L15: Cela ne m’attire pas du tout | M15: Cela m’attire peu | N15: Je suis partagé(e) / sans préférence marquée | O15: Cela m’attire | P15: Cela m’attire beaucoup | Q15: 1 | R15: 2 | S15: 3 | T15: 4 | U15: 5 | V15: La formulation cible l’intérêt pour action concrète sur le réel et résultat tangible. Elle mobilise un comportement caractéristique de la dimension R (Réaliste) sans demander un niveau de compétence préalable. | W15: L’item relève de R3 — Outils / machines / équipements : Usage direct d’outils, machines, instruments ou équipements techniques. | X15: Revue méthodologique V0.3 : surveiller projection en cas de limitation physique ou sensorielle, familiarité avec le contexte professionnel au pilote. | Y15: FAIBLE | Z15: FAIBLE | AA15: FAIBLE | AB15: FAIBLE | AC15: FAIBLE | AD15: MOYEN | AE15: FAIBLE | AF15: FAIBLE | AG15: MOYEN | AH15: FAIBLE | AI15: FAIBLE | AJ15: 0 | AL15: RETENU_V0.5_REECRIT_CONCRET | AN15: PIP-BANK-0.3 | AO15: PIP-BANK-0.4 | AP15: =IF(OR(C15="PILOTE",C15="ACTIF"),IF(AND(A15<>"",H15<>"",I15<>"",K15<>"",V15<>"",W15<>""),"OK","A_COMPLETER"),"OK_STRUCTURE")
A16: PIP-ENV-R-R3-012 | B16: 0.2 | C16: PILOTE | D16: 08/09/2026 | E16: 08/09/2026 | F16: ENV | G16: Contexte décrit par ce qu’il permet de faire | H16: R | I16: R3 | J16: I | K16: Travailler dans un environnement où l’on utilise régulièrement des outils, des instruments ou des machines pour agir sur le réel. | L16: Cela ne m’attire pas du tout | M16: Cela m’attire peu | N16: Je suis partagé(e) / sans préférence marquée | O16: Cela m’attire | P16: Cela m’attire beaucoup | Q16: 1 | R16: 2 | S16: 3 | T16: 4 | U16: 5 | V16: La formulation cible l’intérêt pour action concrète sur le réel et résultat tangible. Elle mobilise un comportement caractéristique de la dimension R (Réaliste) sans demander un niveau de compétence préalable. | W16: L’item relève de R3 — Outils / machines / équipements : Usage direct d’outils, machines, instruments ou équipements techniques. | X16: Revue méthodologique V0.3 : surveiller projection en cas de limitation physique ou sensorielle, familiarité avec le contexte professionnel au pilote. | Y16: FAIBLE | Z16: FAIBLE | AA16: FAIBLE | AB16: FAIBLE | AC16: FAIBLE | AD16: MOYEN | AE16: FAIBLE | AF16: FAIBLE | AG16: MOYEN | AH16: FAIBLE | AI16: FAIBLE | AJ16: 0 | AL16: RETIRE_BANQUE72_HISTORIQUE_CONSERVE | AM16: Réduction méthodologique 120→72 : doublon de facette / priorité aux activités professionnelles observables et aux items à plus faible risque. | AN16: PIP-BANK-0.3 | AO16: PIP-BANK-0.3 | AP16: =IF(OR(C16="PILOTE",C16="ACTIF"),IF(AND(A16<>"",H16<>"",I16<>"",K16<>"",V16<>"",W16<>""),"OK","A_COMPLETER"),"OK_STRUCTURE")
A17: PIP-ACT-R-R4-013 | B17: 0.2 | C17: PILOTE | D17: 08/09/2026 | E17: 08/09/2026 | F17: ACT | G17: Verbe d’action + objet/contexte | H17: R | I17: R4 | J17: I | K17: Se rendre sur différents sites pour intervenir directement sur le terrain. | L17: Cela ne m’attire pas du tout | M17: Cela m’attire peu | N17: Je suis partagé(e) / sans préférence marquée | O17: Cela m’attire | P17: Cela m’attire beaucoup | Q17: 1 | R17: 2 | S17: 3 | T17: 4 | U17: 5 | V17: La formulation cible l’intérêt pour action concrète sur le réel et résultat tangible. Elle mobilise un comportement caractéristique de la dimension R (Réaliste) sans demander un niveau de compétence préalable. | W17: L’item relève de R4 — Terrain / environnement concret : Action dans des contextes physiques, extérieurs ou directement liés à un environnement réel. | X17: Revue méthodologique V0.3 : surveiller projection en cas de limitation physique ou sensorielle, familiarité avec le contexte professionnel au pilote. | Y17: FAIBLE | Z17: FAIBLE | AA17: FAIBLE | AB17: FAIBLE | AC17: FAIBLE | AD17: MOYEN | AE17: FAIBLE | AF17: FAIBLE | AG17: MOYEN | AH17: FAIBLE | AI17: FAIBLE | AJ17: 0 | AL17: RETENU_V0.5_REECRIT_CONCRET | AN17: PIP-BANK-0.3 | AO17: PIP-BANK-0.4 | AP17: =IF(OR(C17="PILOTE",C17="ACTIF"),IF(AND(A17<>"",H17<>"",I17<>"",K17<>"",V17<>"",W17<>""),"OK","A_COMPLETER"),"OK_STRUCTURE")
A18: PIP-ACT-R-R4-014 | B18: 0.2 | C18: PILOTE | D18: 08/09/2026 | E18: 08/09/2026 | F18: ACT | G18: Verbe d’action + objet/contexte | H18: R | I18: R4 | J18: I | K18: Réaliser une activité professionnelle principalement en extérieur. | L18: Cela ne m’attire pas du tout | M18: Cela m’attire peu | N18: Je suis partagé(e) / sans préférence marquée | O18: Cela m’attire | P18: Cela m’attire beaucoup | Q18: 1 | R18: 2 | S18: 3 | T18: 4 | U18: 5 | V18: La formulation cible l’intérêt pour action concrète sur le réel et résultat tangible. Elle mobilise un comportement caractéristique de la dimension R (Réaliste) sans demander un niveau de compétence préalable. | W18: L’item relève de R4 — Terrain / environnement concret : Action dans des contextes physiques, extérieurs ou directement liés à un environnement réel. | X18: Revue méthodologique V0.3 : surveiller projection en cas de limitation physique ou sensorielle, familiarité avec le contexte professionnel au pilote. | Y18: FAIBLE | Z18: FAIBLE | AA18: FAIBLE | AB18: FAIBLE | AC18: FAIBLE | AD18: MOYEN | AE18: FAIBLE | AF18: FAIBLE | AG18: MOYEN | AH18: FAIBLE | AI18: FAIBLE | AJ18: 0 | AL18: RETENU_V0.5_REECRIT_CONCRET | AN18: PIP-BANK-0.3 | AO18: PIP-BANK-0.4 | AP18: =IF(OR(C18="PILOTE",C18="ACTIF"),IF(AND(A18<>"",H18<>"",I18<>"",K18<>"",V18<>"",W18<>""),"OK","A_COMPLETER"),"OK_STRUCTURE")
A19: PIP-SIT-R-R4-015 | B19: 0.2 | C19: PILOTE | D19: 08/09/2026 | E19: 08/09/2026 | F19: SIT | G19: Situation courte avec enjeu central | H19: R | I19: R4 | J19: I | K19: Intervenir sur place lorsqu’une situation concrète doit être traitée directement plutôt qu’à distance. | L19: Cela ne m’attire pas du tout | M19: Cela m’attire peu | N19: Je suis partagé(e) / sans préférence marquée | O19: Cela m’attire | P19: Cela m’attire beaucoup | Q19: 1 | R19: 2 | S19: 3 | T19: 4 | U19: 5 | V19: La formulation cible l’intérêt pour action concrète sur le réel et résultat tangible. Elle mobilise un comportement caractéristique de la dimension R (Réaliste) sans demander un niveau de compétence préalable. | W19: L’item relève de R4 — Terrain / environnement concret : Action dans des contextes physiques, extérieurs ou directement liés à un environnement réel. | X19: Revue méthodologique V0.3 : surveiller projection en cas de limitation physique ou sensorielle, familiarité avec le contexte professionnel au pilote. | Y19: FAIBLE | Z19: FAIBLE | AA19: FAIBLE | AB19: FAIBLE | AC19: FAIBLE | AD19: MOYEN | AE19: FAIBLE | AF19: FAIBLE | AG19: MOYEN | AH19: FAIBLE | AI19: FAIBLE | AJ19: 0 | AL19: RETIRE_BANQUE72_HISTORIQUE_CONSERVE | AM19: Réduction méthodologique 120→72 : doublon de facette / priorité aux activités professionnelles observables et aux items à plus faible risque. | AN19: PIP-BANK-0.3 | AO19: PIP-BANK-0.3 | AP19: =IF(OR(C19="PILOTE",C19="ACTIF"),IF(AND(A19<>"",H19<>"",I19<>"",K19<>"",V19<>"",W19<>""),"OK","A_COMPLETER"),"OK_STRUCTURE")
A20: PIP-ENV-R-R4-016 | B20: 0.2 | C20: PILOTE | D20: 08/09/2026 | E20: 08/09/2026 | F20: ENV | G20: Contexte décrit par ce qu’il permet de faire | H20: R | I20: R4 | J20: I | K20: Travailler dans un contexte où l’activité se déroule souvent sur le terrain, au contact direct de l’environnement réel. | L20: Cela ne m’attire pas du tout | M20: Cela m’attire peu | N20: Je suis partagé(e) / sans préférence marquée | O20: Cela m’attire | P20: Cela m’attire beaucoup | Q20: 1 | R20: 2 | S20: 3 | T20: 4 | U20: 5 | V20: La formulation cible l’intérêt pour action concrète sur le réel et résultat tangible. Elle mobilise un comportement caractéristique de la dimension R (Réaliste) sans demander un niveau de compétence préalable. | W20: L’item relève de R4 — Terrain / environnement concret : Action dans des contextes physiques, extérieurs ou directement liés à un environnement réel. | X20: Revue méthodologique V0.3 : surveiller projection en cas de limitation physique ou sensorielle, familiarité avec le contexte professionnel au pilote. | Y20: FAIBLE | Z20: FAIBLE | AA20: FAIBLE | AB20: FAIBLE | AC20: FAIBLE | AD20: MOYEN | AE20: FAIBLE | AF20: FAIBLE | AG20: MOYEN | AH20: FAIBLE | AI20: FAIBLE | AJ20: 0 | AL20: RETIRE_BANQUE72_HISTORIQUE_CONSERVE | AM20: Réduction méthodologique 120→72 : doublon de facette / priorité aux activités professionnelles observables et aux items à plus faible risque. | AN20: PIP-BANK-0.3 | AO20: PIP-BANK-0.3 | AP20: =IF(OR(C20="PILOTE",C20="ACTIF"),IF(AND(A20<>"",H20<>"",I20<>"",K20<>"",V20<>"",W20<>""),"OK","A_COMPLETER"),"OK_STRUCTURE")
A21: PIP-ACT-R-R5-017 | B21: 0.2 | C21: PILOTE | D21: 08/09/2026 | E21: 08/09/2026 | F21: ACT | G21: Verbe d’action + objet/contexte | H21: R | I21: R5 | J21: S,I | K21: S’occuper concrètement de plantes ou d’animaux dans le cadre du travail. | L21: Cela ne m’attire pas du tout | M21: Cela m’attire peu | N21: Je suis partagé(e) / sans préférence marquée | O21: Cela m’attire | P21: Cela m’attire beaucoup | Q21: 1 | R21: 2 | S21: 3 | T21: 4 | U21: 5 | V21: La formulation cible l’intérêt pour action concrète sur le réel et résultat tangible. Elle mobilise un comportement caractéristique de la dimension R (Réaliste) sans demander un niveau de compétence préalable. | W21: L’item relève de R5 — Vivant / matière / action physique : Activités pratiques impliquant plantes, animaux, matière, effort corporel ou intervention physique finalisée. | X21: Revue méthodologique V0.3 : surveiller projection en cas de limitation physique ou sensorielle, familiarité avec le contexte professionnel, frontière avec S au pilote. | Y21: FAIBLE | Z21: FAIBLE | AA21: FAIBLE | AB21: FAIBLE | AC21: FAIBLE | AD21: MOYEN | AE21: FAIBLE | AF21: FAIBLE | AG21: MOYEN | AH21: FAIBLE | AI21: MOYEN | AJ21: 0 | AL21: RETENU_V0.5_REECRIT_CONCRET | AN21: PIP-BANK-0.3 | AO21: PIP-BANK-0.4 | AP21: =IF(OR(C21="PILOTE",C21="ACTIF"),IF(AND(A21<>"",H21<>"",I21<>"",K21<>"",V21<>"",W21<>""),"OK","A_COMPLETER"),"OK_STRUCTURE")
A22: PIP-ACT-R-R5-018 | B22: 0.2 | C22: PILOTE | D22: 08/09/2026 | E22: 08/09/2026 | F22: ACT | G22: Verbe d’action + objet/contexte | H22: R | I22: R5 | J22: S,I | K22: Manipuler des matériaux ou des produits pour réaliser une tâche physique utile. | L22: Cela ne m’attire pas du tout | M22: Cela m’attire peu | N22: Je suis partagé(e) / sans préférence marquée | O22: Cela m’attire | P22: Cela m’attire beaucoup | Q22: 1 | R22: 2 | S22: 3 | T22: 4 | U22: 5 | V22: La formulation cible l’intérêt pour action concrète sur le réel et résultat tangible. Elle mobilise un comportement caractéristique de la dimension R (Réaliste) sans demander un niveau de compétence préalable. | W22: L’item relève de R5 — Vivant / matière / action physique : Activités pratiques impliquant plantes, animaux, matière, effort corporel ou intervention physique finalisée. | X22: Revue méthodologique V0.3 : surveiller projection en cas de limitation physique ou sensorielle, familiarité avec le contexte professionnel au pilote. | Y22: FAIBLE | Z22: FAIBLE | AA22: FAIBLE | AB22: FAIBLE | AC22: FAIBLE | AD22: MOYEN | AE22: FAIBLE | AF22: FAIBLE | AG22: MOYEN | AH22: FAIBLE | AI22: FAIBLE | AJ22: 0 | AL22: RETENU_V0.5_REECRIT_CONCRET | AN22: PIP-BANK-0.3 | AO22: PIP-BANK-0.4 | AP22: =IF(OR(C22="PILOTE",C22="ACTIF"),IF(AND(A22<>"",H22<>"",I22<>"",K22<>"",V22<>"",W22<>""),"OK","A_COMPLETER"),"OK_STRUCTURE")
A23: PIP-SIT-R-R5-019 | B23: 0.2 | C23: PILOTE | D23: 08/09/2026 | E23: 08/09/2026 | F23: SIT | G23: Situation courte avec enjeu central | H23: R | I23: R5 | J23: S,I | K23: Prendre en charge une activité où il faut agir directement sur du vivant, de la matière ou un environnement physique. | L23: Cela ne m’attire pas du tout | M23: Cela m’attire peu | N23: Je suis partagé(e) / sans préférence marquée | O23: Cela m’attire | P23: Cela m’attire beaucoup | Q23: 1 | R23: 2 | S23: 3 | T23: 4 | U23: 5 | V23: La formulation cible l’intérêt pour action concrète sur le réel et résultat tangible. Elle mobilise un comportement caractéristique de la dimension R (Réaliste) sans demander un niveau de compétence préalable. | W23: L’item relève de R5 — Vivant / matière / action physique : Activités pratiques impliquant plantes, animaux, matière, effort corporel ou intervention physique finalisée. | X23: Revue méthodologique V0.3 : surveiller projection en cas de limitation physique ou sensorielle, familiarité avec le contexte professionnel au pilote. | Y23: FAIBLE | Z23: FAIBLE | AA23: FAIBLE | AB23: FAIBLE | AC23: FAIBLE | AD23: MOYEN | AE23: FAIBLE | AF23: FAIBLE | AG23: MOYEN | AH23: FAIBLE | AI23: FAIBLE | AJ23: 0 | AL23: RETIRE_BANQUE72_HISTORIQUE_CONSERVE | AM23: Réduction méthodologique 120→72 : doublon de facette / priorité aux activités professionnelles observables et aux items à plus faible risque. | AN23: PIP-BANK-0.3 | AO23: PIP-BANK-0.3 | AP23: =IF(OR(C23="PILOTE",C23="ACTIF"),IF(AND(A23<>"",H23<>"",I23<>"",K23<>"",V23<>"",W23<>""),"OK","A_COMPLETER"),"OK_STRUCTURE")
A24: PIP-ENV-R-R5-020 | B24: 0.2 | C24: PILOTE | D24: 08/09/2026 | E24: 08/09/2026 | F24: ENV | G24: Contexte décrit par ce qu’il permet de faire | H24: R | I24: R5 | J24: S,I | K24: Évoluer dans un environnement où le travail implique régulièrement une action physique concrète sur des matières, des plantes, des animaux ou des objets. | L24: Cela ne m’attire pas du tout | M24: Cela m’attire peu | N24: Je suis partagé(e) / sans préférence marquée | O24: Cela m’attire | P24: Cela m’attire beaucoup | Q24: 1 | R24: 2 | S24: 3 | T24: 4 | U24: 5 | V24: La formulation cible l’intérêt pour action concrète sur le réel et résultat tangible. Elle mobilise un comportement caractéristique de la dimension R (Réaliste) sans demander un niveau de compétence préalable. | W24: L’item relève de R5 — Vivant / matière / action physique : Activités pratiques impliquant plantes, animaux, matière, effort corporel ou intervention physique finalisée. | X24: Revue méthodologique V0.3 : surveiller projection en cas de limitation physique ou sensorielle, familiarité avec le contexte professionnel au pilote. | Y24: FAIBLE | Z24: FAIBLE | AA24: FAIBLE | AB24: FAIBLE | AC24: FAIBLE | AD24: MOYEN | AE24: FAIBLE | AF24: FAIBLE | AG24: MOYEN | AH24: FAIBLE | AI24: FAIBLE | AJ24: 0 | AL24: RETIRE_BANQUE72_HISTORIQUE_CONSERVE | AM24: Réduction méthodologique 120→72 : doublon de facette / priorité aux activités professionnelles observables et aux items à plus faible risque. | AN24: PIP-BANK-0.3 | AO24: PIP-BANK-0.3 | AP24: =IF(OR(C24="PILOTE",C24="ACTIF"),IF(AND(A24<>"",H24<>"",I24<>"",K24<>"",V24<>"",W24<>""),"OK","A_COMPLETER"),"OK_STRUCTURE")
A25: PIP-ACT-I-I1-001 | B25: 0.2 | C25: PILOTE | D25: 08/09/2026 | E25: 08/09/2026 | F25: ACT | G25: Verbe d’action + objet/contexte | H25: I | I25: I1 | J25: C | K25: Observer attentivement une situation pour en repérer les caractéristiques importantes. | L25: Cela ne m’attire pas du tout | M25: Cela m’attire peu | N25: Je suis partagé(e) / sans préférence marquée | O25: Cela m’attire | P25: Cela m’attire beaucoup | Q25: 1 | R25: 2 | S25: 3 | T25: 4 | U25: 5 | V25: La formulation cible l’intérêt pour comprendre, rechercher, expliquer et résoudre. Elle mobilise un comportement caractéristique de la dimension I (Investigateur) sans demander un niveau de compétence préalable. | W25: L’item relève de I1 — Observer / examiner : Examen attentif de faits, phénomènes, informations ou situations. | X25: Revue méthodologique V0.3 : surveiller compréhension du vocabulaire au pilote. | Y25: FAIBLE | Z25: FAIBLE | AA25: FAIBLE | AB25: MOYEN | AC25: MOYEN | AD25: FAIBLE | AE25: FAIBLE | AF25: FAIBLE | AG25: FAIBLE | AH25: FAIBLE | AI25: FAIBLE | AJ25: 0 | AL25: RETENU_V0.5_REECRIT_CONCRET | AN25: PIP-BANK-0.3 | AO25: PIP-BANK-0.4 | AP25: =IF(OR(C25="PILOTE",C25="ACTIF"),IF(AND(A25<>"",H25<>"",I25<>"",K25<>"",V25<>"",W25<>""),"OK","A_COMPLETER"),"OK_STRUCTURE")
A26: PIP-ACT-I-I1-002 | B26: 0.2 | C26: PILOTE | D26: 08/09/2026 | E26: 08/09/2026 | F26: ACT | G26: Verbe d’action + objet/contexte | H26: I | I26: I1 | J26: C | K26: Comparer plusieurs informations ou observations pour identifier ce qui les distingue. | L26: Cela ne m’attire pas du tout | M26: Cela m’attire peu | N26: Je suis partagé(e) / sans préférence marquée | O26: Cela m’attire | P26: Cela m’attire beaucoup | Q26: 1 | R26: 2 | S26: 3 | T26: 4 | U26: 5 | V26: La formulation cible l’intérêt pour comprendre, rechercher, expliquer et résoudre. Elle mobilise un comportement caractéristique de la dimension I (Investigateur) sans demander un niveau de compétence préalable. | W26: L’item relève de I1 — Observer / examiner : Examen attentif de faits, phénomènes, informations ou situations. | X26: Revue méthodologique V0.3 : surveiller compréhension du vocabulaire au pilote. | Y26: FAIBLE | Z26: FAIBLE | AA26: FAIBLE | AB26: MOYEN | AC26: MOYEN | AD26: FAIBLE | AE26: FAIBLE | AF26: FAIBLE | AG26: FAIBLE | AH26: FAIBLE | AI26: FAIBLE | AJ26: 0 | AL26: RETENU_V0.5_REECRIT_CONCRET | AN26: PIP-BANK-0.3 | AO26: PIP-BANK-0.4 | AP26: =IF(OR(C26="PILOTE",C26="ACTIF"),IF(AND(A26<>"",H26<>"",I26<>"",K26<>"",V26<>"",W26<>""),"OK","A_COMPLETER"),"OK_STRUCTURE")
A27: PIP-SIT-I-I1-003 | B27: 0.2 | C27: PILOTE | D27: 08/09/2026 | E27: 08/09/2026 | F27: SIT | G27: Situation courte avec enjeu central | H27: I | I27: I1 | J27: C | K27: Examiner une situation nouvelle afin de comprendre précisément ce qui s’y passe. | L27: Cela ne m’attire pas du tout | M27: Cela m’attire peu | N27: Je suis partagé(e) / sans préférence marquée | O27: Cela m’attire | P27: Cela m’attire beaucoup | Q27: 1 | R27: 2 | S27: 3 | T27: 4 | U27: 5 | V27: La formulation cible l’intérêt pour comprendre, rechercher, expliquer et résoudre. Elle mobilise un comportement caractéristique de la dimension I (Investigateur) sans demander un niveau de compétence préalable. | W27: L’item relève de I1 — Observer / examiner : Examen attentif de faits, phénomènes, informations ou situations. | X27: Revue méthodologique V0.3 : surveiller compréhension du vocabulaire au pilote. | Y27: FAIBLE | Z27: FAIBLE | AA27: FAIBLE | AB27: MOYEN | AC27: MOYEN | AD27: FAIBLE | AE27: FAIBLE | AF27: FAIBLE | AG27: FAIBLE | AH27: FAIBLE | AI27: FAIBLE | AJ27: 0 | AL27: RETENU_V0.5_REECRIT_CONCRET | AN27: PIP-BANK-0.3 | AO27: PIP-BANK-0.4 | AP27: =IF(OR(C27="PILOTE",C27="ACTIF"),IF(AND(A27<>"",H27<>"",I27<>"",K27<>"",V27<>"",W27<>""),"OK","A_COMPLETER"),"OK_STRUCTURE")
A28: PIP-ENV-I-I1-004 | B28: 0.2 | C28: PILOTE | D28: 08/09/2026 | E28: 08/09/2026 | F28: ENV | G28: Contexte décrit par ce qu’il permet de faire | H28: I | I28: I1 | J28: C | K28: Travailler dans un contexte où l’on dispose de temps pour observer et examiner les faits avant de tirer des conclusions. | L28: Cela ne m’attire pas du tout | M28: Cela m’attire peu | N28: Je suis partagé(e) / sans préférence marquée | O28: Cela m’attire | P28: Cela m’attire beaucoup | Q28: 1 | R28: 2 | S28: 3 | T28: 4 | U28: 5 | V28: La formulation cible l’intérêt pour comprendre, rechercher, expliquer et résoudre. Elle mobilise un comportement caractéristique de la dimension I (Investigateur) sans demander un niveau de compétence préalable. | W28: L’item relève de I1 — Observer / examiner : Examen attentif de faits, phénomènes, informations ou situations. | X28: Revue méthodologique V0.3 : surveiller compréhension du vocabulaire au pilote. | Y28: FAIBLE | Z28: FAIBLE | AA28: FAIBLE | AB28: MOYEN | AC28: MOYEN | AD28: FAIBLE | AE28: FAIBLE | AF28: FAIBLE | AG28: FAIBLE | AH28: FAIBLE | AI28: FAIBLE | AJ28: 0 | AL28: RETIRE_BANQUE72_HISTORIQUE_CONSERVE | AM28: Réduction méthodologique 120→72 : doublon de facette / priorité aux activités professionnelles observables et aux items à plus faible risque. | AN28: PIP-BANK-0.3 | AO28: PIP-BANK-0.3 | AP28: =IF(OR(C28="PILOTE",C28="ACTIF"),IF(AND(A28<>"",H28<>"",I28<>"",K28<>"",V28<>"",W28<>""),"OK","A_COMPLETER"),"OK_STRUCTURE")
A29: PIP-ACT-I-I2-005 | B29: 0.2 | C29: PILOTE | D29: 08/09/2026 | E29: 08/09/2026 | F29: ACT | G29: Verbe d’action + objet/contexte | H29: I | I29: I2 | J29: C | K29: Analyser plusieurs informations pour comprendre les liens entre elles. | L29: Cela ne m’attire pas du tout | M29: Cela m’attire peu | N29: Je suis partagé(e) / sans préférence marquée | O29: Cela m’attire | P29: Cela m’attire beaucoup | Q29: 1 | R29: 2 | S29: 3 | T29: 4 | U29: 5 | V29: La formulation cible l’intérêt pour comprendre, rechercher, expliquer et résoudre. Elle mobilise un comportement caractéristique de la dimension I (Investigateur) sans demander un niveau de compétence préalable. | W29: L’item relève de I2 — Analyser / raisonner : Décomposition d’un problème et mise en relation d’informations. | X29: Revue méthodologique V0.3 : surveiller compréhension du vocabulaire au pilote. | Y29: FAIBLE | Z29: FAIBLE | AA29: FAIBLE | AB29: MOYEN | AC29: MOYEN | AD29: FAIBLE | AE29: FAIBLE | AF29: FAIBLE | AG29: FAIBLE | AH29: FAIBLE | AI29: FAIBLE | AJ29: 0 | AL29: RETENU_V0.5_REECRIT_CONCRET | AN29: PIP-BANK-0.3 | AO29: PIP-BANK-0.4 | AP29: =IF(OR(C29="PILOTE",C29="ACTIF"),IF(AND(A29<>"",H29<>"",I29<>"",K29<>"",V29<>"",W29<>""),"OK","A_COMPLETER"),"OK_STRUCTURE")
A30: PIP-ACT-I-I2-006 | B30: 0.2 | C30: PILOTE | D30: 08/09/2026 | E30: 08/09/2026 | F30: ACT | G30: Verbe d’action + objet/contexte | H30: I | I30: I2 | J30: C | K30: Décomposer un problème complexe en plusieurs éléments pour mieux le comprendre. | L30: Cela ne m’attire pas du tout | M30: Cela m’attire peu | N30: Je suis partagé(e) / sans préférence marquée | O30: Cela m’attire | P30: Cela m’attire beaucoup | Q30: 1 | R30: 2 | S30: 3 | T30: 4 | U30: 5 | V30: La formulation cible l’intérêt pour comprendre, rechercher, expliquer et résoudre. Elle mobilise un comportement caractéristique de la dimension I (Investigateur) sans demander un niveau de compétence préalable. | W30: L’item relève de I2 — Analyser / raisonner : Décomposition d’un problème et mise en relation d’informations. | X30: Revue méthodologique V0.3 : surveiller compréhension du vocabulaire au pilote. | Y30: FAIBLE | Z30: FAIBLE | AA30: FAIBLE | AB30: MOYEN | AC30: MOYEN | AD30: FAIBLE | AE30: FAIBLE | AF30: FAIBLE | AG30: FAIBLE | AH30: FAIBLE | AI30: FAIBLE | AJ30: 0 | AL30: RETENU_V0.5_REECRIT_CONCRET | AN30: PIP-BANK-0.3 | AO30: PIP-BANK-0.4 | AP30: =IF(OR(C30="PILOTE",C30="ACTIF"),IF(AND(A30<>"",H30<>"",I30<>"",K30<>"",V30<>"",W30<>""),"OK","A_COMPLETER"),"OK_STRUCTURE")
A31: PIP-SIT-I-I2-007 | B31: 0.2 | C31: PILOTE | D31: 08/09/2026 | E31: 08/09/2026 | F31: SIT | G31: Situation courte avec enjeu central | H31: I | I31: I2 | J31: C | K31: Faire face à un problème où il faut raisonner étape par étape avant de trouver une explication. | L31: Cela ne m’attire pas du tout | M31: Cela m’attire peu | N31: Je suis partagé(e) / sans préférence marquée | O31: Cela m’attire | P31: Cela m’attire beaucoup | Q31: 1 | R31: 2 | S31: 3 | T31: 4 | U31: 5 | V31: La formulation cible l’intérêt pour comprendre, rechercher, expliquer et résoudre. Elle mobilise un comportement caractéristique de la dimension I (Investigateur) sans demander un niveau de compétence préalable. | W31: L’item relève de I2 — Analyser / raisonner : Décomposition d’un problème et mise en relation d’informations. | X31: Revue méthodologique V0.3 : surveiller compréhension du vocabulaire au pilote. | Y31: FAIBLE | Z31: FAIBLE | AA31: FAIBLE | AB31: MOYEN | AC31: MOYEN | AD31: FAIBLE | AE31: FAIBLE | AF31: FAIBLE | AG31: FAIBLE | AH31: FAIBLE | AI31: FAIBLE | AJ31: 0 | AL31: RETENU_V0.5_REECRIT_CONCRET | AN31: PIP-BANK-0.3 | AO31: PIP-BANK-0.4 | AP31: =IF(OR(C31="PILOTE",C31="ACTIF"),IF(AND(A31<>"",H31<>"",I31<>"",K31<>"",V31<>"",W31<>""),"OK","A_COMPLETER"),"OK_STRUCTURE")
A32: PIP-ENV-I-I2-008 | B32: 0.2 | C32: PILOTE | D32: 08/09/2026 | E32: 08/09/2026 | F32: ENV | G32: Contexte décrit par ce qu’il permet de faire | H32: I | I32: I2 | J32: C | K32: Évoluer dans un contexte où l’on doit régulièrement interpréter des informations et construire un raisonnement. | L32: Cela ne m’attire pas du tout | M32: Cela m’attire peu | N32: Je suis partagé(e) / sans préférence marquée | O32: Cela m’attire | P32: Cela m’attire beaucoup | Q32: 1 | R32: 2 | S32: 3 | T32: 4 | U32: 5 | V32: La formulation cible l’intérêt pour comprendre, rechercher, expliquer et résoudre. Elle mobilise un comportement caractéristique de la dimension I (Investigateur) sans demander un niveau de compétence préalable. | W32: L’item relève de I2 — Analyser / raisonner : Décomposition d’un problème et mise en relation d’informations. | X32: Revue méthodologique V0.3 : surveiller compréhension du vocabulaire au pilote. | Y32: FAIBLE | Z32: FAIBLE | AA32: FAIBLE | AB32: MOYEN | AC32: MOYEN | AD32: FAIBLE | AE32: FAIBLE | AF32: FAIBLE | AG32: FAIBLE | AH32: FAIBLE | AI32: FAIBLE | AJ32: 0 | AL32: RETIRE_BANQUE72_HISTORIQUE_CONSERVE | AM32: Réduction méthodologique 120→72 : doublon de facette / priorité aux activités professionnelles observables et aux items à plus faible risque. | AN32: PIP-BANK-0.3 | AO32: PIP-BANK-0.3 | AP32: =IF(OR(C32="PILOTE",C32="ACTIF"),IF(AND(A32<>"",H32<>"",I32<>"",K32<>"",V32<>"",W32<>""),"OK","A_COMPLETER"),"OK_STRUCTURE")
A33: PIP-ACT-I-I3-009 | B33: 0.2 | C33: PILOTE | D33: 08/09/2026 | E33: 08/09/2026 | F33: ACT | G33: Verbe d’action + objet/contexte | H33: I | I33: I3 | J33: C | K33: Rechercher des informations provenant de plusieurs sources pour répondre à une question. | L33: Cela ne m’attire pas du tout | M33: Cela m’attire peu | N33: Je suis partagé(e) / sans préférence marquée | O33: Cela m’attire | P33: Cela m’attire beaucoup | Q33: 1 | R33: 2 | S33: 3 | T33: 4 | U33: 5 | V33: La formulation cible l’intérêt pour comprendre, rechercher, expliquer et résoudre. Elle mobilise un comportement caractéristique de la dimension I (Investigateur) sans demander un niveau de compétence préalable. | W33: L’item relève de I3 — Rechercher / enquêter : Recherche d’informations, preuves ou explications lorsqu’une question reste ouverte. | X33: Revue méthodologique V0.3 : surveiller compréhension du vocabulaire au pilote. | Y33: FAIBLE | Z33: FAIBLE | AA33: FAIBLE | AB33: MOYEN | AC33: MOYEN | AD33: FAIBLE | AE33: FAIBLE | AF33: FAIBLE | AG33: FAIBLE | AH33: FAIBLE | AI33: FAIBLE | AJ33: 0 | AL33: RETENU_V0.5_REECRIT_CONCRET | AN33: PIP-BANK-0.3 | AO33: PIP-BANK-0.4 | AP33: =IF(OR(C33="PILOTE",C33="ACTIF"),IF(AND(A33<>"",H33<>"",I33<>"",K33<>"",V33<>"",W33<>""),"OK","A_COMPLETER"),"OK_STRUCTURE")
A34: PIP-ACT-I-I3-010 | B34: 0.2 | C34: PILOTE | D34: 08/09/2026 | E34: 08/09/2026 | F34: ACT | G34: Verbe d’action + objet/contexte | H34: I | I34: I3 | J34: C | K34: Enquêter pour vérifier ce qui est exact lorsqu’une situation reste incertaine. | L34: Cela ne m’attire pas du tout | M34: Cela m’attire peu | N34: Je suis partagé(e) / sans préférence marquée | O34: Cela m’attire | P34: Cela m’attire beaucoup | Q34: 1 | R34: 2 | S34: 3 | T34: 4 | U34: 5 | V34: La formulation cible l’intérêt pour comprendre, rechercher, expliquer et résoudre. Elle mobilise un comportement caractéristique de la dimension I (Investigateur) sans demander un niveau de compétence préalable. | W34: L’item relève de I3 — Rechercher / enquêter : Recherche d’informations, preuves ou explications lorsqu’une question reste ouverte. | X34: Revue méthodologique V0.3 : surveiller compréhension du vocabulaire au pilote. | Y34: FAIBLE | Z34: FAIBLE | AA34: FAIBLE | AB34: MOYEN | AC34: MOYEN | AD34: FAIBLE | AE34: FAIBLE | AF34: FAIBLE | AG34: FAIBLE | AH34: FAIBLE | AI34: FAIBLE | AJ34: 0 | AL34: RETENU_V0.5_REECRIT_CONCRET | AN34: PIP-BANK-0.3 | AO34: PIP-BANK-0.4 | AP34: =IF(OR(C34="PILOTE",C34="ACTIF"),IF(AND(A34<>"",H34<>"",I34<>"",K34<>"",V34<>"",W34<>""),"OK","A_COMPLETER"),"OK_STRUCTURE")
A35: PIP-SIT-I-I3-011 | B35: 0.2 | C35: PILOTE | D35: 08/09/2026 | E35: 08/09/2026 | F35: SIT | G35: Situation courte avec enjeu central | H35: I | I35: I3 | J35: C | K35: Être confronté à une question sans réponse immédiate et devoir approfondir les recherches pour la comprendre. | L35: Cela ne m’attire pas du tout | M35: Cela m’attire peu | N35: Je suis partagé(e) / sans préférence marquée | O35: Cela m’attire | P35: Cela m’attire beaucoup | Q35: 1 | R35: 2 | S35: 3 | T35: 4 | U35: 5 | V35: La formulation cible l’intérêt pour comprendre, rechercher, expliquer et résoudre. Elle mobilise un comportement caractéristique de la dimension I (Investigateur) sans demander un niveau de compétence préalable. | W35: L’item relève de I3 — Rechercher / enquêter : Recherche d’informations, preuves ou explications lorsqu’une question reste ouverte. | X35: Revue méthodologique V0.3 : surveiller compréhension du vocabulaire au pilote. | Y35: FAIBLE | Z35: FAIBLE | AA35: FAIBLE | AB35: MOYEN | AC35: MOYEN | AD35: FAIBLE | AE35: FAIBLE | AF35: FAIBLE | AG35: FAIBLE | AH35: FAIBLE | AI35: FAIBLE | AJ35: 0 | AL35: RETIRE_BANQUE72_HISTORIQUE_CONSERVE | AM35: Réduction méthodologique 120→72 : doublon de facette / priorité aux activités professionnelles observables et aux items à plus faible risque. | AN35: PIP-BANK-0.3 | AO35: PIP-BANK-0.3 | AP35: =IF(OR(C35="PILOTE",C35="ACTIF"),IF(AND(A35<>"",H35<>"",I35<>"",K35<>"",V35<>"",W35<>""),"OK","A_COMPLETER"),"OK_STRUCTURE")
A36: PIP-ENV-I-I3-012 | B36: 0.2 | C36: PILOTE | D36: 08/09/2026 | E36: 08/09/2026 | F36: ENV | G36: Contexte décrit par ce qu’il permet de faire | H36: I | I36: I3 | J36: C | K36: Travailler dans un contexte où l’on peut explorer des sujets, consulter des sources et approfondir des questions. | L36: Cela ne m’attire pas du tout | M36: Cela m’attire peu | N36: Je suis partagé(e) / sans préférence marquée | O36: Cela m’attire | P36: Cela m’attire beaucoup | Q36: 1 | R36: 2 | S36: 3 | T36: 4 | U36: 5 | V36: La formulation cible l’intérêt pour comprendre, rechercher, expliquer et résoudre. Elle mobilise un comportement caractéristique de la dimension I (Investigateur) sans demander un niveau de compétence préalable. | W36: L’item relève de I3 — Rechercher / enquêter : Recherche d’informations, preuves ou explications lorsqu’une question reste ouverte. | X36: Revue méthodologique V0.3 : surveiller compréhension du vocabulaire au pilote. | Y36: FAIBLE | Z36: FAIBLE | AA36: FAIBLE | AB36: MOYEN | AC36: MOYEN | AD36: FAIBLE | AE36: FAIBLE | AF36: FAIBLE | AG36: FAIBLE | AH36: FAIBLE | AI36: FAIBLE | AJ36: 0 | AL36: RETIRE_BANQUE72_HISTORIQUE_CONSERVE | AM36: Réduction méthodologique 120→72 : doublon de facette / priorité aux activités professionnelles observables et aux items à plus faible risque. | AN36: PIP-BANK-0.3 | AO36: PIP-BANK-0.3 | AP36: =IF(OR(C36="PILOTE",C36="ACTIF"),IF(AND(A36<>"",H36<>"",I36<>"",K36<>"",V36<>"",W36<>""),"OK","A_COMPLETER"),"OK_STRUCTURE")
A37: PIP-ACT-I-I4-013 | B37: 0.2 | C37: PILOTE | D37: 08/09/2026 | E37: 08/09/2026 | F37: ACT | G37: Verbe d’action + objet/contexte | H37: I | I37: I4 | J37: R | K37: Tester une hypothèse pour voir si elle se vérifie. | L37: Cela ne m’attire pas du tout | M37: Cela m’attire peu | N37: Je suis partagé(e) / sans préférence marquée | O37: Cela m’attire | P37: Cela m’attire beaucoup | Q37: 1 | R37: 2 | S37: 3 | T37: 4 | U37: 5 | V37: La formulation cible l’intérêt pour comprendre, rechercher, expliquer et résoudre. Elle mobilise un comportement caractéristique de la dimension I (Investigateur) sans demander un niveau de compétence préalable. | W37: L’item relève de I4 — Expérimenter / tester : Mise à l’épreuve d’hypothèses ou solutions afin d’apprendre du résultat. | X37: Revue méthodologique V0.3 : surveiller compréhension du vocabulaire au pilote. | Y37: FAIBLE | Z37: FAIBLE | AA37: FAIBLE | AB37: MOYEN | AC37: MOYEN | AD37: FAIBLE | AE37: FAIBLE | AF37: FAIBLE | AG37: FAIBLE | AH37: FAIBLE | AI37: FAIBLE | AJ37: 0 | AL37: RETENU_V0.5_REECRIT_CONCRET | AN37: PIP-BANK-0.3 | AO37: PIP-BANK-0.4 | AP37: =IF(OR(C37="PILOTE",C37="ACTIF"),IF(AND(A37<>"",H37<>"",I37<>"",K37<>"",V37<>"",W37<>""),"OK","A_COMPLETER"),"OK_STRUCTURE")
A38: PIP-ACT-I-I4-014 | B38: 0.2 | C38: PILOTE | D38: 08/09/2026 | E38: 08/09/2026 | F38: ACT | G38: Verbe d’action + objet/contexte | H38: I | I38: I4 | J38: R | K38: Comparer plusieurs essais pour comprendre ce qui produit un résultat différent. | L38: Cela ne m’attire pas du tout | M38: Cela m’attire peu | N38: Je suis partagé(e) / sans préférence marquée | O38: Cela m’attire | P38: Cela m’attire beaucoup | Q38: 1 | R38: 2 | S38: 3 | T38: 4 | U38: 5 | V38: La formulation cible l’intérêt pour comprendre, rechercher, expliquer et résoudre. Elle mobilise un comportement caractéristique de la dimension I (Investigateur) sans demander un niveau de compétence préalable. | W38: L’item relève de I4 — Expérimenter / tester : Mise à l’épreuve d’hypothèses ou solutions afin d’apprendre du résultat. | X38: Revue méthodologique V0.3 : surveiller compréhension du vocabulaire au pilote. | Y38: FAIBLE | Z38: FAIBLE | AA38: FAIBLE | AB38: MOYEN | AC38: MOYEN | AD38: FAIBLE | AE38: FAIBLE | AF38: FAIBLE | AG38: FAIBLE | AH38: FAIBLE | AI38: FAIBLE | AJ38: 0 | AL38: RETENU_V0.5_REECRIT_CONCRET | AN38: PIP-BANK-0.3 | AO38: PIP-BANK-0.4 | AP38: =IF(OR(C38="PILOTE",C38="ACTIF"),IF(AND(A38<>"",H38<>"",I38<>"",K38<>"",V38<>"",W38<>""),"OK","A_COMPLETER"),"OK_STRUCTURE")
A39: PIP-SIT-I-I4-015 | B39: 0.2 | C39: PILOTE | D39: 08/09/2026 | E39: 08/09/2026 | F39: SIT | G39: Situation courte avec enjeu central | H39: I | I39: I4 | J39: R | K39: Chercher la meilleure explication d’un phénomène en réalisant des essais ou des mesures. | L39: Cela ne m’attire pas du tout | M39: Cela m’attire peu | N39: Je suis partagé(e) / sans préférence marquée | O39: Cela m’attire | P39: Cela m’attire beaucoup | Q39: 1 | R39: 2 | S39: 3 | T39: 4 | U39: 5 | V39: La formulation cible l’intérêt pour comprendre, rechercher, expliquer et résoudre. Elle mobilise un comportement caractéristique de la dimension I (Investigateur) sans demander un niveau de compétence préalable. | W39: L’item relève de I4 — Expérimenter / tester : Mise à l’épreuve d’hypothèses ou solutions afin d’apprendre du résultat. | X39: Revue méthodologique V0.3 : surveiller compréhension du vocabulaire au pilote. | Y39: FAIBLE | Z39: FAIBLE | AA39: FAIBLE | AB39: MOYEN | AC39: MOYEN | AD39: FAIBLE | AE39: FAIBLE | AF39: FAIBLE | AG39: FAIBLE | AH39: FAIBLE | AI39: FAIBLE | AJ39: 0 | AL39: RETIRE_BANQUE72_HISTORIQUE_CONSERVE | AM39: Réduction méthodologique 120→72 : doublon de facette / priorité aux activités professionnelles observables et aux items à plus faible risque. | AN39: PIP-BANK-0.3 | AO39: PIP-BANK-0.3 | AP39: =IF(OR(C39="PILOTE",C39="ACTIF"),IF(AND(A39<>"",H39<>"",I39<>"",K39<>"",V39<>"",W39<>""),"OK","A_COMPLETER"),"OK_STRUCTURE")
A40: PIP-ENV-I-I4-016 | B40: 0.2 | C40: PILOTE | D40: 08/09/2026 | E40: 08/09/2026 | F40: ENV | G40: Contexte décrit par ce qu’il permet de faire | H40: I | I40: I4 | J40: R | K40: Évoluer dans un contexte où l’on peut expérimenter, mesurer et tirer des enseignements des résultats. | L40: Cela ne m’attire pas du tout | M40: Cela m’attire peu | N40: Je suis partagé(e) / sans préférence marquée | O40: Cela m’attire | P40: Cela m’attire beaucoup | Q40: 1 | R40: 2 | S40: 3 | T40: 4 | U40: 5 | V40: La formulation cible l’intérêt pour comprendre, rechercher, expliquer et résoudre. Elle mobilise un comportement caractéristique de la dimension I (Investigateur) sans demander un niveau de compétence préalable. | W40: L’item relève de I4 — Expérimenter / tester : Mise à l’épreuve d’hypothèses ou solutions afin d’apprendre du résultat. | X40: Revue méthodologique V0.3 : surveiller compréhension du vocabulaire au pilote. | Y40: FAIBLE | Z40: FAIBLE | AA40: FAIBLE | AB40: MOYEN | AC40: MOYEN | AD40: FAIBLE | AE40: FAIBLE | AF40: FAIBLE | AG40: FAIBLE | AH40: FAIBLE | AI40: FAIBLE | AJ40: 0 | AL40: RETIRE_BANQUE72_HISTORIQUE_CONSERVE | AM40: Réduction méthodologique 120→72 : doublon de facette / priorité aux activités professionnelles observables et aux items à plus faible risque. | AN40: PIP-BANK-0.3 | AO40: PIP-BANK-0.3 | AP40: =IF(OR(C40="PILOTE",C40="ACTIF"),IF(AND(A40<>"",H40<>"",I40<>"",K40<>"",V40<>"",W40<>""),"OK","A_COMPLETER"),"OK_STRUCTURE")
A41: PIP-ACT-I-I5-017 | B41: 0.2 | C41: PILOTE | D41: 08/09/2026 | E41: 08/09/2026 | F41: ACT | G41: Verbe d’action + objet/contexte | H41: I | I41: I5 | J41: R | K41: Chercher la cause d’un problème pour pouvoir l’expliquer. | L41: Cela ne m’attire pas du tout | M41: Cela m’attire peu | N41: Je suis partagé(e) / sans préférence marquée | O41: Cela m’attire | P41: Cela m’attire beaucoup | Q41: 1 | R41: 2 | S41: 3 | T41: 4 | U41: 5 | V41: La formulation cible l’intérêt pour comprendre, rechercher, expliquer et résoudre. Elle mobilise un comportement caractéristique de la dimension I (Investigateur) sans demander un niveau de compétence préalable. | W41: L’item relève de I5 — Résoudre / expliquer : Problèmes intellectuels dont l’enjeu est de comprendre, expliquer ou trouver une solution fondée. | X41: Revue méthodologique V0.3 : surveiller compréhension du vocabulaire au pilote. | Y41: FAIBLE | Z41: FAIBLE | AA41: FAIBLE | AB41: MOYEN | AC41: MOYEN | AD41: FAIBLE | AE41: FAIBLE | AF41: FAIBLE | AG41: FAIBLE | AH41: FAIBLE | AI41: FAIBLE | AJ41: 0 | AL41: RETENU_V0.5_REECRIT_CONCRET | AN41: PIP-BANK-0.3 | AO41: PIP-BANK-0.4 | AP41: =IF(OR(C41="PILOTE",C41="ACTIF"),IF(AND(A41<>"",H41<>"",I41<>"",K41<>"",V41<>"",W41<>""),"OK","A_COMPLETER"),"OK_STRUCTURE")
A42: PIP-ACT-I-I5-018 | B42: 0.2 | C42: PILOTE | D42: 08/09/2026 | E42: 08/09/2026 | F42: ACT | G42: Verbe d’action + objet/contexte | H42: I | I42: I5 | J42: R | K42: Résoudre un problème nouveau en construisant une solution fondée sur les informations disponibles. | L42: Cela ne m’attire pas du tout | M42: Cela m’attire peu | N42: Je suis partagé(e) / sans préférence marquée | O42: Cela m’attire | P42: Cela m’attire beaucoup | Q42: 1 | R42: 2 | S42: 3 | T42: 4 | U42: 5 | V42: La formulation cible l’intérêt pour comprendre, rechercher, expliquer et résoudre. Elle mobilise un comportement caractéristique de la dimension I (Investigateur) sans demander un niveau de compétence préalable. | W42: L’item relève de I5 — Résoudre / expliquer : Problèmes intellectuels dont l’enjeu est de comprendre, expliquer ou trouver une solution fondée. | X42: Revue méthodologique V0.3 : surveiller compréhension du vocabulaire au pilote. | Y42: FAIBLE | Z42: FAIBLE | AA42: FAIBLE | AB42: MOYEN | AC42: MOYEN | AD42: FAIBLE | AE42: FAIBLE | AF42: FAIBLE | AG42: FAIBLE | AH42: FAIBLE | AI42: FAIBLE | AJ42: 0 | AL42: RETENU_V0.5_REECRIT_CONCRET | AN42: PIP-BANK-0.3 | AO42: PIP-BANK-0.4 | AP42: =IF(OR(C42="PILOTE",C42="ACTIF"),IF(AND(A42<>"",H42<>"",I42<>"",K42<>"",V42<>"",W42<>""),"OK","A_COMPLETER"),"OK_STRUCTURE")
A43: PIP-SIT-I-I5-019 | B43: 0.2 | C43: PILOTE | D43: 08/09/2026 | E43: 08/09/2026 | F43: SIT | G43: Situation courte avec enjeu central | H43: I | I43: I5 | J43: R | K43: Prendre en charge une situation complexe dont la solution n’est pas connue à l’avance et qui demande d’abord de comprendre le problème. | L43: Cela ne m’attire pas du tout | M43: Cela m’attire peu | N43: Je suis partagé(e) / sans préférence marquée | O43: Cela m’attire | P43: Cela m’attire beaucoup | Q43: 1 | R43: 2 | S43: 3 | T43: 4 | U43: 5 | V43: La formulation cible l’intérêt pour comprendre, rechercher, expliquer et résoudre. Elle mobilise un comportement caractéristique de la dimension I (Investigateur) sans demander un niveau de compétence préalable. | W43: L’item relève de I5 — Résoudre / expliquer : Problèmes intellectuels dont l’enjeu est de comprendre, expliquer ou trouver une solution fondée. | X43: Revue méthodologique V0.3 : surveiller compréhension du vocabulaire, frontière avec R au pilote. | Y43: FAIBLE | Z43: FAIBLE | AA43: FAIBLE | AB43: MOYEN | AC43: MOYEN | AD43: FAIBLE | AE43: FAIBLE | AF43: FAIBLE | AG43: FAIBLE | AH43: FAIBLE | AI43: MOYEN | AJ43: 0 | AL43: RETIRE_BANQUE72_HISTORIQUE_CONSERVE | AM43: Réduction méthodologique 120→72 : doublon de facette / priorité aux activités professionnelles observables et aux items à plus faible risque. | AN43: PIP-BANK-0.3 | AO43: PIP-BANK-0.3 | AP43: =IF(OR(C43="PILOTE",C43="ACTIF"),IF(AND(A43<>"",H43<>"",I43<>"",K43<>"",V43<>"",W43<>""),"OK","A_COMPLETER"),"OK_STRUCTURE")
A44: PIP-ENV-I-I5-020 | B44: 0.2 | C44: PILOTE | D44: 08/09/2026 | E44: 08/09/2026 | F44: ENV | G44: Contexte décrit par ce qu’il permet de faire | H44: I | I44: I5 | J44: R | K44: Travailler dans un contexte où l’on est régulièrement amené à expliquer des phénomènes ou à résoudre des problèmes qui demandent réflexion et compréhension. | L44: Cela ne m’attire pas du tout | M44: Cela m’attire peu | N44: Je suis partagé(e) / sans préférence marquée | O44: Cela m’attire | P44: Cela m’attire beaucoup | Q44: 1 | R44: 2 | S44: 3 | T44: 4 | U44: 5 | V44: La formulation cible l’intérêt pour comprendre, rechercher, expliquer et résoudre. Elle mobilise un comportement caractéristique de la dimension I (Investigateur) sans demander un niveau de compétence préalable. | W44: L’item relève de I5 — Résoudre / expliquer : Problèmes intellectuels dont l’enjeu est de comprendre, expliquer ou trouver une solution fondée. | X44: Revue méthodologique V0.3 : surveiller compréhension du vocabulaire au pilote. | Y44: FAIBLE | Z44: FAIBLE | AA44: FAIBLE | AB44: MOYEN | AC44: MOYEN | AD44: FAIBLE | AE44: FAIBLE | AF44: FAIBLE | AG44: FAIBLE | AH44: FAIBLE | AI44: FAIBLE | AJ44: 0 | AL44: RETIRE_BANQUE72_HISTORIQUE_CONSERVE | AM44: Réduction méthodologique 120→72 : doublon de facette / priorité aux activités professionnelles observables et aux items à plus faible risque. | AN44: PIP-BANK-0.3 | AO44: PIP-BANK-0.3 | AP44: =IF(OR(C44="PILOTE",C44="ACTIF"),IF(AND(A44<>"",H44<>"",I44<>"",K44<>"",V44<>"",W44<>""),"OK","A_COMPLETER"),"OK_STRUCTURE")
A45: PIP-ACT-A-A1-001 | B45: 0.2 | C45: PILOTE | D45: 08/09/2026 | E45: 08/09/2026 | F45: ACT | G45: Verbe d’action + objet/contexte | H45: A | I45: A1 | J45: I,E | K45: Imaginer plusieurs idées nouvelles à partir d’un même sujet. | L45: Cela ne m’attire pas du tout | M45: Cela m’attire peu | N45: Je suis partagé(e) / sans préférence marquée | O45: Cela m’attire | P45: Cela m’attire beaucoup | Q45: 1 | R45: 2 | S45: 3 | T45: 4 | U45: 5 | V45: La formulation cible l’intérêt pour créer, concevoir ou exprimer avec ouverture. Elle mobilise un comportement caractéristique de la dimension A (Artistique) sans demander un niveau de compétence préalable. | W45: L’item relève de A1 — Imaginer / inventer : Génération d’idées, concepts, scénarios ou formes nouvelles. | X45: Revue méthodologique V0.3 : surveiller compréhension du vocabulaire au pilote. | Y45: FAIBLE | Z45: FAIBLE | AA45: FAIBLE | AB45: FAIBLE | AC45: MOYEN | AD45: FAIBLE | AE45: FAIBLE | AF45: FAIBLE | AG45: FAIBLE | AH45: FAIBLE | AI45: FAIBLE | AJ45: 0 | AL45: RETENU_V0.5_REECRIT_CONCRET | AN45: PIP-BANK-0.3 | AO45: PIP-BANK-0.4 | AP45: =IF(OR(C45="PILOTE",C45="ACTIF"),IF(AND(A45<>"",H45<>"",I45<>"",K45<>"",V45<>"",W45<>""),"OK","A_COMPLETER"),"OK_STRUCTURE")
A46: PIP-ACT-A-A1-002 | B46: 0.2 | C46: PILOTE | D46: 08/09/2026 | E46: 08/09/2026 | F46: ACT | G46: Verbe d’action + objet/contexte | H46: A | I46: A1 | J46: I,E | K46: Inventer une manière originale de présenter ou de réaliser quelque chose. | L46: Cela ne m’attire pas du tout | M46: Cela m’attire peu | N46: Je suis partagé(e) / sans préférence marquée | O46: Cela m’attire | P46: Cela m’attire beaucoup | Q46: 1 | R46: 2 | S46: 3 | T46: 4 | U46: 5 | V46: La formulation cible l’intérêt pour créer, concevoir ou exprimer avec ouverture. Elle mobilise un comportement caractéristique de la dimension A (Artistique) sans demander un niveau de compétence préalable. | W46: L’item relève de A1 — Imaginer / inventer : Génération d’idées, concepts, scénarios ou formes nouvelles. | X46: Revue méthodologique V0.3 : surveiller compréhension du vocabulaire au pilote. | Y46: FAIBLE | Z46: FAIBLE | AA46: FAIBLE | AB46: FAIBLE | AC46: MOYEN | AD46: FAIBLE | AE46: FAIBLE | AF46: FAIBLE | AG46: FAIBLE | AH46: FAIBLE | AI46: FAIBLE | AJ46: 0 | AL46: RETENU_V0.5_REECRIT_CONCRET | AN46: PIP-BANK-0.3 | AO46: PIP-BANK-0.4 | AP46: =IF(OR(C46="PILOTE",C46="ACTIF"),IF(AND(A46<>"",H46<>"",I46<>"",K46<>"",V46<>"",W46<>""),"OK","A_COMPLETER"),"OK_STRUCTURE")
A47: PIP-SIT-A-A1-003 | B47: 0.2 | C47: PILOTE | D47: 08/09/2026 | E47: 08/09/2026 | F47: SIT | G47: Situation courte avec enjeu central | H47: A | I47: A1 | J47: I,E | K47: Faire face à une demande pour laquelle aucune solution n’est imposée et imaginer une proposition nouvelle. | L47: Cela ne m’attire pas du tout | M47: Cela m’attire peu | N47: Je suis partagé(e) / sans préférence marquée | O47: Cela m’attire | P47: Cela m’attire beaucoup | Q47: 1 | R47: 2 | S47: 3 | T47: 4 | U47: 5 | V47: La formulation cible l’intérêt pour créer, concevoir ou exprimer avec ouverture. Elle mobilise un comportement caractéristique de la dimension A (Artistique) sans demander un niveau de compétence préalable. | W47: L’item relève de A1 — Imaginer / inventer : Génération d’idées, concepts, scénarios ou formes nouvelles. | X47: Revue méthodologique V0.3 : surveiller compréhension du vocabulaire au pilote. | Y47: FAIBLE | Z47: FAIBLE | AA47: FAIBLE | AB47: FAIBLE | AC47: MOYEN | AD47: FAIBLE | AE47: FAIBLE | AF47: FAIBLE | AG47: FAIBLE | AH47: FAIBLE | AI47: FAIBLE | AJ47: 0 | AL47: RETENU_V0.5_REECRIT_CONCRET | AN47: PIP-BANK-0.3 | AO47: PIP-BANK-0.4 | AP47: =IF(OR(C47="PILOTE",C47="ACTIF"),IF(AND(A47<>"",H47<>"",I47<>"",K47<>"",V47<>"",W47<>""),"OK","A_COMPLETER"),"OK_STRUCTURE")
A48: PIP-ENV-A-A1-004 | B48: 0.2 | C48: PILOTE | D48: 08/09/2026 | E48: 08/09/2026 | F48: ENV | G48: Contexte décrit par ce qu’il permet de faire | H48: A | I48: A1 | J48: I,E | K48: Travailler dans un contexte où l’on attend régulièrement des idées nouvelles et où plusieurs pistes sont possibles. | L48: Cela ne m’attire pas du tout | M48: Cela m’attire peu | N48: Je suis partagé(e) / sans préférence marquée | O48: Cela m’attire | P48: Cela m’attire beaucoup | Q48: 1 | R48: 2 | S48: 3 | T48: 4 | U48: 5 | V48: La formulation cible l’intérêt pour créer, concevoir ou exprimer avec ouverture. Elle mobilise un comportement caractéristique de la dimension A (Artistique) sans demander un niveau de compétence préalable. | W48: L’item relève de A1 — Imaginer / inventer : Génération d’idées, concepts, scénarios ou formes nouvelles. | X48: Revue méthodologique V0.3 : surveiller compréhension du vocabulaire au pilote. | Y48: FAIBLE | Z48: FAIBLE | AA48: FAIBLE | AB48: FAIBLE | AC48: MOYEN | AD48: FAIBLE | AE48: FAIBLE | AF48: FAIBLE | AG48: FAIBLE | AH48: FAIBLE | AI48: FAIBLE | AJ48: 0 | AL48: RETIRE_BANQUE72_HISTORIQUE_CONSERVE | AM48: Réduction méthodologique 120→72 : doublon de facette / priorité aux activités professionnelles observables et aux items à plus faible risque. | AN48: PIP-BANK-0.3 | AO48: PIP-BANK-0.3 | AP48: =IF(OR(C48="PILOTE",C48="ACTIF"),IF(AND(A48<>"",H48<>"",I48<>"",K48<>"",V48<>"",W48<>""),"OK","A_COMPLETER"),"OK_STRUCTURE")
A49: PIP-ACT-A-A2-005 | B49: 0.2 | C49: PILOTE | D49: 08/09/2026 | E49: 08/09/2026 | F49: ACT | G49: Verbe d’action + objet/contexte | H49: A | I49: A2 | J49: R | K49: Concevoir l’organisation visuelle ou la forme d’un support pour qu’il exprime une intention. | L49: Cela ne m’attire pas du tout | M49: Cela m’attire peu | N49: Je suis partagé(e) / sans préférence marquée | O49: Cela m’attire | P49: Cela m’attire beaucoup | Q49: 1 | R49: 2 | S49: 3 | T49: 4 | U49: 5 | V49: La formulation cible l’intérêt pour créer, concevoir ou exprimer avec ouverture. Elle mobilise un comportement caractéristique de la dimension A (Artistique) sans demander un niveau de compétence préalable. | W49: L’item relève de A2 — Concevoir / composer : Organisation créative d’éléments afin de produire une forme cohérente et personnelle. | X49: Revue méthodologique V0.3 : surveiller compréhension du vocabulaire, frontière avec R au pilote. | Y49: FAIBLE | Z49: FAIBLE | AA49: FAIBLE | AB49: FAIBLE | AC49: MOYEN | AD49: FAIBLE | AE49: FAIBLE | AF49: FAIBLE | AG49: FAIBLE | AH49: FAIBLE | AI49: MOYEN | AJ49: 0 | AL49: RETENU_V0.5_REECRIT_CONCRET | AN49: PIP-BANK-0.3 | AO49: PIP-BANK-0.4 | AP49: =IF(OR(C49="PILOTE",C49="ACTIF"),IF(AND(A49<>"",H49<>"",I49<>"",K49<>"",V49<>"",W49<>""),"OK","A_COMPLETER"),"OK_STRUCTURE")
A50: PIP-ACT-A-A2-006 | B50: 0.2 | C50: PILOTE | D50: 08/09/2026 | E50: 08/09/2026 | F50: ACT | G50: Verbe d’action + objet/contexte | H50: A | I50: A2 | J50: R | K50: Composer différents éléments pour créer un ensemble cohérent et personnel. | L50: Cela ne m’attire pas du tout | M50: Cela m’attire peu | N50: Je suis partagé(e) / sans préférence marquée | O50: Cela m’attire | P50: Cela m’attire beaucoup | Q50: 1 | R50: 2 | S50: 3 | T50: 4 | U50: 5 | V50: La formulation cible l’intérêt pour créer, concevoir ou exprimer avec ouverture. Elle mobilise un comportement caractéristique de la dimension A (Artistique) sans demander un niveau de compétence préalable. | W50: L’item relève de A2 — Concevoir / composer : Organisation créative d’éléments afin de produire une forme cohérente et personnelle. | X50: Revue méthodologique V0.3 : surveiller compréhension du vocabulaire au pilote. | Y50: FAIBLE | Z50: FAIBLE | AA50: FAIBLE | AB50: FAIBLE | AC50: MOYEN | AD50: FAIBLE | AE50: FAIBLE | AF50: FAIBLE | AG50: FAIBLE | AH50: FAIBLE | AI50: FAIBLE | AJ50: 0 | AL50: RETENU_V0.5_REECRIT_CONCRET | AN50: PIP-BANK-0.3 | AO50: PIP-BANK-0.4 | AP50: =IF(OR(C50="PILOTE",C50="ACTIF"),IF(AND(A50<>"",H50<>"",I50<>"",K50<>"",V50<>"",W50<>""),"OK","A_COMPLETER"),"OK_STRUCTURE")
A51: PIP-SIT-A-A2-007 | B51: 0.2 | C51: PILOTE | D51: 08/09/2026 | E51: 08/09/2026 | F51: SIT | G51: Situation courte avec enjeu central | H51: A | I51: A2 | J51: R | K51: Créer une proposition en choisissant librement la manière d’agencer plusieurs éléments. | L51: Cela ne m’attire pas du tout | M51: Cela m’attire peu | N51: Je suis partagé(e) / sans préférence marquée | O51: Cela m’attire | P51: Cela m’attire beaucoup | Q51: 1 | R51: 2 | S51: 3 | T51: 4 | U51: 5 | V51: La formulation cible l’intérêt pour créer, concevoir ou exprimer avec ouverture. Elle mobilise un comportement caractéristique de la dimension A (Artistique) sans demander un niveau de compétence préalable. | W51: L’item relève de A2 — Concevoir / composer : Organisation créative d’éléments afin de produire une forme cohérente et personnelle. | X51: Revue méthodologique V0.3 : surveiller compréhension du vocabulaire au pilote. | Y51: FAIBLE | Z51: FAIBLE | AA51: FAIBLE | AB51: FAIBLE | AC51: MOYEN | AD51: FAIBLE | AE51: FAIBLE | AF51: FAIBLE | AG51: FAIBLE | AH51: FAIBLE | AI51: FAIBLE | AJ51: 0 | AL51: RETENU_V0.5_REECRIT_CONCRET | AN51: PIP-BANK-0.3 | AO51: PIP-BANK-0.4 | AP51: =IF(OR(C51="PILOTE",C51="ACTIF"),IF(AND(A51<>"",H51<>"",I51<>"",K51<>"",V51<>"",W51<>""),"OK","A_COMPLETER"),"OK_STRUCTURE")
A52: PIP-ENV-A-A2-008 | B52: 0.2 | C52: PILOTE | D52: 08/09/2026 | E52: 08/09/2026 | F52: ENV | G52: Contexte décrit par ce qu’il permet de faire | H52: A | I52: A2 | J52: R | K52: Évoluer dans un contexte où l’on peut concevoir des formes, des contenus ou des expériences avec une réelle liberté de choix. | L52: Cela ne m’attire pas du tout | M52: Cela m’attire peu | N52: Je suis partagé(e) / sans préférence marquée | O52: Cela m’attire | P52: Cela m’attire beaucoup | Q52: 1 | R52: 2 | S52: 3 | T52: 4 | U52: 5 | V52: La formulation cible l’intérêt pour créer, concevoir ou exprimer avec ouverture. Elle mobilise un comportement caractéristique de la dimension A (Artistique) sans demander un niveau de compétence préalable. | W52: L’item relève de A2 — Concevoir / composer : Organisation créative d’éléments afin de produire une forme cohérente et personnelle. | X52: Revue méthodologique V0.3 : surveiller compréhension du vocabulaire au pilote. | Y52: FAIBLE | Z52: FAIBLE | AA52: FAIBLE | AB52: FAIBLE | AC52: MOYEN | AD52: FAIBLE | AE52: FAIBLE | AF52: FAIBLE | AG52: FAIBLE | AH52: FAIBLE | AI52: FAIBLE | AJ52: 0 | AL52: RETIRE_BANQUE72_HISTORIQUE_CONSERVE | AM52: Réduction méthodologique 120→72 : doublon de facette / priorité aux activités professionnelles observables et aux items à plus faible risque. | AN52: PIP-BANK-0.3 | AO52: PIP-BANK-0.3 | AP52: =IF(OR(C52="PILOTE",C52="ACTIF"),IF(AND(A52<>"",H52<>"",I52<>"",K52<>"",V52<>"",W52<>""),"OK","A_COMPLETER"),"OK_STRUCTURE")
A53: PIP-ACT-A-A3-009 | B53: 0.2 | C53: PILOTE | D53: 08/09/2026 | E53: 08/09/2026 | F53: ACT | G53: Verbe d’action + objet/contexte | H53: A | I53: A3 | J53: S,E | K53: Écrire un texte pour transmettre une idée, une émotion ou un point de vue. | L53: Cela ne m’attire pas du tout | M53: Cela m’attire peu | N53: Je suis partagé(e) / sans préférence marquée | O53: Cela m’attire | P53: Cela m’attire beaucoup | Q53: 1 | R53: 2 | S53: 3 | T53: 4 | U53: 5 | V53: La formulation cible l’intérêt pour créer, concevoir ou exprimer avec ouverture. Elle mobilise un comportement caractéristique de la dimension A (Artistique) sans demander un niveau de compétence préalable. | W53: L’item relève de A3 — Exprimer / raconter : Transmission d’une idée, émotion, point de vue ou histoire par une forme expressive. | X53: Revue méthodologique V0.3 : surveiller compréhension du vocabulaire au pilote. | Y53: FAIBLE | Z53: FAIBLE | AA53: FAIBLE | AB53: FAIBLE | AC53: MOYEN | AD53: FAIBLE | AE53: FAIBLE | AF53: FAIBLE | AG53: FAIBLE | AH53: FAIBLE | AI53: FAIBLE | AJ53: 0 | AL53: RETENU_V0.5_REECRIT_CONCRET | AN53: PIP-BANK-0.3 | AO53: PIP-BANK-0.4 | AP53: =IF(OR(C53="PILOTE",C53="ACTIF"),IF(AND(A53<>"",H53<>"",I53<>"",K53<>"",V53<>"",W53<>""),"OK","A_COMPLETER"),"OK_STRUCTURE")
A54: PIP-ACT-A-A3-010 | B54: 0.2 | C54: PILOTE | D54: 08/09/2026 | E54: 08/09/2026 | F54: ACT | G54: Verbe d’action + objet/contexte | H54: A | I54: A3 | J54: S,E | K54: Mettre en récit un sujet pour le rendre vivant et expressif. | L54: Cela ne m’attire pas du tout | M54: Cela m’attire peu | N54: Je suis partagé(e) / sans préférence marquée | O54: Cela m’attire | P54: Cela m’attire beaucoup | Q54: 1 | R54: 2 | S54: 3 | T54: 4 | U54: 5 | V54: La formulation cible l’intérêt pour créer, concevoir ou exprimer avec ouverture. Elle mobilise un comportement caractéristique de la dimension A (Artistique) sans demander un niveau de compétence préalable. | W54: L’item relève de A3 — Exprimer / raconter : Transmission d’une idée, émotion, point de vue ou histoire par une forme expressive. | X54: Revue méthodologique V0.3 : surveiller compréhension du vocabulaire au pilote. | Y54: FAIBLE | Z54: FAIBLE | AA54: FAIBLE | AB54: FAIBLE | AC54: MOYEN | AD54: FAIBLE | AE54: FAIBLE | AF54: FAIBLE | AG54: FAIBLE | AH54: FAIBLE | AI54: FAIBLE | AJ54: 0 | AL54: RETENU_V0.5_REECRIT_CONCRET | AN54: PIP-BANK-0.3 | AO54: PIP-BANK-0.4 | AP54: =IF(OR(C54="PILOTE",C54="ACTIF"),IF(AND(A54<>"",H54<>"",I54<>"",K54<>"",V54<>"",W54<>""),"OK","A_COMPLETER"),"OK_STRUCTURE")
A55: PIP-SIT-A-A3-011 | B55: 0.2 | C55: PILOTE | D55: 08/09/2026 | E55: 08/09/2026 | F55: SIT | G55: Situation courte avec enjeu central | H55: A | I55: A3 | J55: S,E | K55: Trouver une manière personnelle de raconter ou de représenter une histoire, une idée ou une expérience. | L55: Cela ne m’attire pas du tout | M55: Cela m’attire peu | N55: Je suis partagé(e) / sans préférence marquée | O55: Cela m’attire | P55: Cela m’attire beaucoup | Q55: 1 | R55: 2 | S55: 3 | T55: 4 | U55: 5 | V55: La formulation cible l’intérêt pour créer, concevoir ou exprimer avec ouverture. Elle mobilise un comportement caractéristique de la dimension A (Artistique) sans demander un niveau de compétence préalable. | W55: L’item relève de A3 — Exprimer / raconter : Transmission d’une idée, émotion, point de vue ou histoire par une forme expressive. | X55: Revue méthodologique V0.3 : surveiller compréhension du vocabulaire au pilote. | Y55: FAIBLE | Z55: FAIBLE | AA55: FAIBLE | AB55: FAIBLE | AC55: MOYEN | AD55: FAIBLE | AE55: FAIBLE | AF55: FAIBLE | AG55: FAIBLE | AH55: FAIBLE | AI55: FAIBLE | AJ55: 0 | AL55: RETIRE_BANQUE72_HISTORIQUE_CONSERVE | AM55: Réduction méthodologique 120→72 : doublon de facette / priorité aux activités professionnelles observables et aux items à plus faible risque. | AN55: PIP-BANK-0.3 | AO55: PIP-BANK-0.3 | AP55: =IF(OR(C55="PILOTE",C55="ACTIF"),IF(AND(A55<>"",H55<>"",I55<>"",K55<>"",V55<>"",W55<>""),"OK","A_COMPLETER"),"OK_STRUCTURE")
A56: PIP-ENV-A-A3-012 | B56: 0.2 | C56: PILOTE | D56: 08/09/2026 | E56: 08/09/2026 | F56: ENV | G56: Contexte décrit par ce qu’il permet de faire | H56: A | I56: A3 | J56: S,E | K56: Travailler dans un contexte où l’expression par les mots, les images, le son ou la mise en scène occupe une place importante. | L56: Cela ne m’attire pas du tout | M56: Cela m’attire peu | N56: Je suis partagé(e) / sans préférence marquée | O56: Cela m’attire | P56: Cela m’attire beaucoup | Q56: 1 | R56: 2 | S56: 3 | T56: 4 | U56: 5 | V56: La formulation cible l’intérêt pour créer, concevoir ou exprimer avec ouverture. Elle mobilise un comportement caractéristique de la dimension A (Artistique) sans demander un niveau de compétence préalable. | W56: L’item relève de A3 — Exprimer / raconter : Transmission d’une idée, émotion, point de vue ou histoire par une forme expressive. | X56: Revue méthodologique V0.3 : surveiller compréhension du vocabulaire au pilote. | Y56: FAIBLE | Z56: FAIBLE | AA56: FAIBLE | AB56: FAIBLE | AC56: MOYEN | AD56: FAIBLE | AE56: FAIBLE | AF56: FAIBLE | AG56: FAIBLE | AH56: FAIBLE | AI56: FAIBLE | AJ56: 0 | AL56: RETIRE_BANQUE72_HISTORIQUE_CONSERVE | AM56: Réduction méthodologique 120→72 : doublon de facette / priorité aux activités professionnelles observables et aux items à plus faible risque. | AN56: PIP-BANK-0.3 | AO56: PIP-BANK-0.3 | AP56: =IF(OR(C56="PILOTE",C56="ACTIF"),IF(AND(A56<>"",H56<>"",I56<>"",K56<>"",V56<>"",W56<>""),"OK","A_COMPLETER"),"OK_STRUCTURE")
A57: PIP-ACT-A-A4-013 | B57: 0.2 | C57: PILOTE | D57: 08/09/2026 | E57: 08/09/2026 | F57: ACT | G57: Verbe d’action + objet/contexte | H57: A | I57: A4 | J57: R | K57: Créer une composition visuelle en jouant sur les formes, les images ou les couleurs. | L57: Cela ne m’attire pas du tout | M57: Cela m’attire peu | N57: Je suis partagé(e) / sans préférence marquée | O57: Cela m’attire | P57: Cela m’attire beaucoup | Q57: 1 | R57: 2 | S57: 3 | T57: 4 | U57: 5 | V57: La formulation cible l’intérêt pour créer, concevoir ou exprimer avec ouverture. Elle mobilise un comportement caractéristique de la dimension A (Artistique) sans demander un niveau de compétence préalable. | W57: L’item relève de A4 — Créer visuellement / sensoriellement : Création mobilisant formes, images, sons, mouvements, matières, espaces ou expériences sensibles. | X57: Revue méthodologique V0.3 : surveiller compréhension du vocabulaire au pilote. | Y57: FAIBLE | Z57: FAIBLE | AA57: FAIBLE | AB57: FAIBLE | AC57: MOYEN | AD57: FAIBLE | AE57: FAIBLE | AF57: FAIBLE | AG57: FAIBLE | AH57: FAIBLE | AI57: FAIBLE | AJ57: 0 | AL57: RETENU_V0.5_REECRIT_CONCRET | AN57: PIP-BANK-0.3 | AO57: PIP-BANK-0.4 | AP57: =IF(OR(C57="PILOTE",C57="ACTIF"),IF(AND(A57<>"",H57<>"",I57<>"",K57<>"",V57<>"",W57<>""),"OK","A_COMPLETER"),"OK_STRUCTURE")
A58: PIP-ACT-A-A4-014 | B58: 0.2 | C58: PILOTE | D58: 08/09/2026 | E58: 08/09/2026 | F58: ACT | G58: Verbe d’action + objet/contexte | H58: A | I58: A4 | J58: R | K58: Imaginer une ambiance à partir de sons, d’images, de matières ou d’un espace. | L58: Cela ne m’attire pas du tout | M58: Cela m’attire peu | N58: Je suis partagé(e) / sans préférence marquée | O58: Cela m’attire | P58: Cela m’attire beaucoup | Q58: 1 | R58: 2 | S58: 3 | T58: 4 | U58: 5 | V58: La formulation cible l’intérêt pour créer, concevoir ou exprimer avec ouverture. Elle mobilise un comportement caractéristique de la dimension A (Artistique) sans demander un niveau de compétence préalable. | W58: L’item relève de A4 — Créer visuellement / sensoriellement : Création mobilisant formes, images, sons, mouvements, matières, espaces ou expériences sensibles. | X58: Revue méthodologique V0.3 : surveiller compréhension du vocabulaire au pilote. | Y58: FAIBLE | Z58: FAIBLE | AA58: FAIBLE | AB58: FAIBLE | AC58: MOYEN | AD58: FAIBLE | AE58: FAIBLE | AF58: FAIBLE | AG58: FAIBLE | AH58: FAIBLE | AI58: FAIBLE | AJ58: 0 | AL58: RETENU_V0.5_REECRIT_CONCRET | AN58: PIP-BANK-0.3 | AO58: PIP-BANK-0.4 | AP58: =IF(OR(C58="PILOTE",C58="ACTIF"),IF(AND(A58<>"",H58<>"",I58<>"",K58<>"",V58<>"",W58<>""),"OK","A_COMPLETER"),"OK_STRUCTURE")
A59: PIP-SIT-A-A4-015 | B59: 0.2 | C59: PILOTE | D59: 08/09/2026 | E59: 08/09/2026 | F59: SIT | G59: Situation courte avec enjeu central | H59: A | I59: A4 | J59: R | K59: Concevoir une expérience où l’effet visuel, sonore ou sensoriel compte autant que la fonction. | L59: Cela ne m’attire pas du tout | M59: Cela m’attire peu | N59: Je suis partagé(e) / sans préférence marquée | O59: Cela m’attire | P59: Cela m’attire beaucoup | Q59: 1 | R59: 2 | S59: 3 | T59: 4 | U59: 5 | V59: La formulation cible l’intérêt pour créer, concevoir ou exprimer avec ouverture. Elle mobilise un comportement caractéristique de la dimension A (Artistique) sans demander un niveau de compétence préalable. | W59: L’item relève de A4 — Créer visuellement / sensoriellement : Création mobilisant formes, images, sons, mouvements, matières, espaces ou expériences sensibles. | X59: Revue méthodologique V0.3 : surveiller compréhension du vocabulaire au pilote. | Y59: FAIBLE | Z59: FAIBLE | AA59: FAIBLE | AB59: FAIBLE | AC59: MOYEN | AD59: FAIBLE | AE59: FAIBLE | AF59: FAIBLE | AG59: FAIBLE | AH59: FAIBLE | AI59: FAIBLE | AJ59: 0 | AL59: RETIRE_BANQUE72_HISTORIQUE_CONSERVE | AM59: Réduction méthodologique 120→72 : doublon de facette / priorité aux activités professionnelles observables et aux items à plus faible risque. | AN59: PIP-BANK-0.3 | AO59: PIP-BANK-0.3 | AP59: =IF(OR(C59="PILOTE",C59="ACTIF"),IF(AND(A59<>"",H59<>"",I59<>"",K59<>"",V59<>"",W59<>""),"OK","A_COMPLETER"),"OK_STRUCTURE")
A60: PIP-ENV-A-A4-016 | B60: 0.2 | C60: PILOTE | D60: 08/09/2026 | E60: 08/09/2026 | F60: ENV | G60: Contexte décrit par ce qu’il permet de faire | H60: A | I60: A4 | J60: R | K60: Évoluer dans un contexte où l’on crée régulièrement des contenus, des espaces ou des objets destinés à produire une impression visuelle ou sensorielle. | L60: Cela ne m’attire pas du tout | M60: Cela m’attire peu | N60: Je suis partagé(e) / sans préférence marquée | O60: Cela m’attire | P60: Cela m’attire beaucoup | Q60: 1 | R60: 2 | S60: 3 | T60: 4 | U60: 5 | V60: La formulation cible l’intérêt pour créer, concevoir ou exprimer avec ouverture. Elle mobilise un comportement caractéristique de la dimension A (Artistique) sans demander un niveau de compétence préalable. | W60: L’item relève de A4 — Créer visuellement / sensoriellement : Création mobilisant formes, images, sons, mouvements, matières, espaces ou expériences sensibles. | X60: Revue méthodologique V0.3 : surveiller compréhension du vocabulaire au pilote. | Y60: FAIBLE | Z60: FAIBLE | AA60: FAIBLE | AB60: FAIBLE | AC60: MOYEN | AD60: FAIBLE | AE60: FAIBLE | AF60: FAIBLE | AG60: FAIBLE | AH60: FAIBLE | AI60: FAIBLE | AJ60: 0 | AL60: RETIRE_BANQUE72_HISTORIQUE_CONSERVE | AM60: Réduction méthodologique 120→72 : doublon de facette / priorité aux activités professionnelles observables et aux items à plus faible risque. | AN60: PIP-BANK-0.3 | AO60: PIP-BANK-0.3 | AP60: =IF(OR(C60="PILOTE",C60="ACTIF"),IF(AND(A60<>"",H60<>"",I60<>"",K60<>"",V60<>"",W60<>""),"OK","A_COMPLETER"),"OK_STRUCTURE")
A61: PIP-ACT-A-A5-017 | B61: 0.2 | C61: PILOTE | D61: 08/09/2026 | E61: 08/09/2026 | F61: ACT | G61: Verbe d’action + objet/contexte | H61: A | I61: A5 | J61: I,E | K61: Explorer plusieurs pistes créatives avant de choisir celle qui convient le mieux. | L61: Cela ne m’attire pas du tout | M61: Cela m’attire peu | N61: Je suis partagé(e) / sans préférence marquée | O61: Cela m’attire | P61: Cela m’attire beaucoup | Q61: 1 | R61: 2 | S61: 3 | T61: 4 | U61: 5 | V61: La formulation cible l’intérêt pour créer, concevoir ou exprimer avec ouverture. Elle mobilise un comportement caractéristique de la dimension A (Artistique) sans demander un niveau de compétence préalable. | W61: L’item relève de A5 — Explorer des solutions ouvertes : Tâches créatives où plusieurs réponses sont possibles et l’originalité a une place réelle. | X61: Revue méthodologique V0.3 : surveiller compréhension du vocabulaire au pilote. | Y61: FAIBLE | Z61: FAIBLE | AA61: FAIBLE | AB61: FAIBLE | AC61: MOYEN | AD61: FAIBLE | AE61: FAIBLE | AF61: FAIBLE | AG61: FAIBLE | AH61: FAIBLE | AI61: FAIBLE | AJ61: 0 | AL61: RETENU_V0.5_REECRIT_CONCRET | AN61: PIP-BANK-0.3 | AO61: PIP-BANK-0.4 | AP61: =IF(OR(C61="PILOTE",C61="ACTIF"),IF(AND(A61<>"",H61<>"",I61<>"",K61<>"",V61<>"",W61<>""),"OK","A_COMPLETER"),"OK_STRUCTURE")
A62: PIP-ACT-A-A5-018 | B62: 0.2 | C62: PILOTE | D62: 08/09/2026 | E62: 08/09/2026 | F62: ACT | G62: Verbe d’action + objet/contexte | H62: A | I62: A5 | J62: I,E | K62: Réinventer une manière habituelle de faire pour proposer une approche originale. | L62: Cela ne m’attire pas du tout | M62: Cela m’attire peu | N62: Je suis partagé(e) / sans préférence marquée | O62: Cela m’attire | P62: Cela m’attire beaucoup | Q62: 1 | R62: 2 | S62: 3 | T62: 4 | U62: 5 | V62: La formulation cible l’intérêt pour créer, concevoir ou exprimer avec ouverture. Elle mobilise un comportement caractéristique de la dimension A (Artistique) sans demander un niveau de compétence préalable. | W62: L’item relève de A5 — Explorer des solutions ouvertes : Tâches créatives où plusieurs réponses sont possibles et l’originalité a une place réelle. | X62: Revue méthodologique V0.3 : surveiller compréhension du vocabulaire au pilote. | Y62: FAIBLE | Z62: FAIBLE | AA62: FAIBLE | AB62: FAIBLE | AC62: MOYEN | AD62: FAIBLE | AE62: FAIBLE | AF62: FAIBLE | AG62: FAIBLE | AH62: FAIBLE | AI62: FAIBLE | AJ62: 0 | AL62: RETENU_V0.5_REECRIT_CONCRET | AN62: PIP-BANK-0.3 | AO62: PIP-BANK-0.4 | AP62: =IF(OR(C62="PILOTE",C62="ACTIF"),IF(AND(A62<>"",H62<>"",I62<>"",K62<>"",V62<>"",W62<>""),"OK","A_COMPLETER"),"OK_STRUCTURE")
A63: PIP-SIT-A-A5-019 | B63: 0.2 | C63: PILOTE | D63: 08/09/2026 | E63: 08/09/2026 | F63: SIT | G63: Situation courte avec enjeu central | H63: A | I63: A5 | J63: I,E | K63: Travailler sur un problème pour lequel plusieurs réponses différentes peuvent être pertinentes. | L63: Cela ne m’attire pas du tout | M63: Cela m’attire peu | N63: Je suis partagé(e) / sans préférence marquée | O63: Cela m’attire | P63: Cela m’attire beaucoup | Q63: 1 | R63: 2 | S63: 3 | T63: 4 | U63: 5 | V63: La formulation cible l’intérêt pour créer, concevoir ou exprimer avec ouverture. Elle mobilise un comportement caractéristique de la dimension A (Artistique) sans demander un niveau de compétence préalable. | W63: L’item relève de A5 — Explorer des solutions ouvertes : Tâches créatives où plusieurs réponses sont possibles et l’originalité a une place réelle. | X63: Revue méthodologique V0.3 : surveiller compréhension du vocabulaire, frontière avec I au pilote. | Y63: FAIBLE | Z63: FAIBLE | AA63: FAIBLE | AB63: FAIBLE | AC63: MOYEN | AD63: FAIBLE | AE63: FAIBLE | AF63: FAIBLE | AG63: FAIBLE | AH63: FAIBLE | AI63: MOYEN | AJ63: 0 | AL63: RETIRE_BANQUE72_HISTORIQUE_CONSERVE | AM63: Réduction méthodologique 120→72 : doublon de facette / priorité aux activités professionnelles observables et aux items à plus faible risque. | AN63: PIP-BANK-0.3 | AO63: PIP-BANK-0.3 | AP63: =IF(OR(C63="PILOTE",C63="ACTIF"),IF(AND(A63<>"",H63<>"",I63<>"",K63<>"",V63<>"",W63<>""),"OK","A_COMPLETER"),"OK_STRUCTURE")
A64: PIP-ENV-A-A5-020 | B64: 0.2 | C64: PILOTE | D64: 08/09/2026 | E64: 08/09/2026 | F64: ENV | G64: Contexte décrit par ce qu’il permet de faire | H64: A | I64: A5 | J64: I,E | K64: Évoluer dans un contexte où les consignes laissent une place importante à l’interprétation personnelle et à l’expérimentation créative. | L64: Cela ne m’attire pas du tout | M64: Cela m’attire peu | N64: Je suis partagé(e) / sans préférence marquée | O64: Cela m’attire | P64: Cela m’attire beaucoup | Q64: 1 | R64: 2 | S64: 3 | T64: 4 | U64: 5 | V64: La formulation cible l’intérêt pour créer, concevoir ou exprimer avec ouverture. Elle mobilise un comportement caractéristique de la dimension A (Artistique) sans demander un niveau de compétence préalable. | W64: L’item relève de A5 — Explorer des solutions ouvertes : Tâches créatives où plusieurs réponses sont possibles et l’originalité a une place réelle. | X64: Revue méthodologique V0.3 : surveiller compréhension du vocabulaire au pilote. | Y64: FAIBLE | Z64: FAIBLE | AA64: FAIBLE | AB64: FAIBLE | AC64: MOYEN | AD64: FAIBLE | AE64: FAIBLE | AF64: FAIBLE | AG64: FAIBLE | AH64: FAIBLE | AI64: FAIBLE | AJ64: 0 | AL64: RETIRE_BANQUE72_HISTORIQUE_CONSERVE | AM64: Réduction méthodologique 120→72 : doublon de facette / priorité aux activités professionnelles observables et aux items à plus faible risque. | AN64: PIP-BANK-0.3 | AO64: PIP-BANK-0.3 | AP64: =IF(OR(C64="PILOTE",C64="ACTIF"),IF(AND(A64<>"",H64<>"",I64<>"",K64<>"",V64<>"",W64<>""),"OK","A_COMPLETER"),"OK_STRUCTURE")
A65: PIP-ACT-S-S1-001 | B65: 0.2 | C65: PILOTE | D65: 08/09/2026 | E65: 08/09/2026 | F65: ACT | G65: Verbe d’action + objet/contexte | H65: S | I65: S1 | J65: I | K65: Expliquer un sujet à une personne pour l’aider à le comprendre. | L65: Cela ne m’attire pas du tout | M65: Cela m’attire peu | N65: Je suis partagé(e) / sans préférence marquée | O65: Cela m’attire | P65: Cela m’attire beaucoup | Q65: 1 | R65: 2 | S65: 3 | T65: 4 | U65: 5 | V65: La formulation cible l’intérêt pour aider, développer, soutenir ou servir autrui. Elle mobilise un comportement caractéristique de la dimension S (Social) sans demander un niveau de compétence préalable. | W65: L’item relève de S1 — Enseigner / transmettre : Faire apprendre, expliquer et développer des connaissances ou savoir-faire chez autrui. | X65: Revue méthodologique V0.3 : surveiller désirabilité sociale, stéréotypes de genre historiques liés au soin/service au pilote. | Y65: MOYEN | Z65: FAIBLE | AA65: FAIBLE | AB65: FAIBLE | AC65: FAIBLE | AD65: FAIBLE | AE65: FAIBLE | AF65: FAIBLE | AG65: FAIBLE | AH65: MOYEN | AI65: FAIBLE | AJ65: 0 | AL65: RETENU_V0.5_REECRIT_CONCRET | AN65: PIP-BANK-0.3 | AO65: PIP-BANK-0.4 | AP65: =IF(OR(C65="PILOTE",C65="ACTIF"),IF(AND(A65<>"",H65<>"",I65<>"",K65<>"",V65<>"",W65<>""),"OK","A_COMPLETER"),"OK_STRUCTURE")
A66: PIP-ACT-S-S1-002 | B66: 0.2 | C66: PILOTE | D66: 08/09/2026 | E66: 08/09/2026 | F66: ACT | G66: Verbe d’action + objet/contexte | H66: S | I66: S1 | J66: I | K66: Montrer à quelqu’un comment réaliser une tâche afin qu’il puisse ensuite la faire seul. | L66: Cela ne m’attire pas du tout | M66: Cela m’attire peu | N66: Je suis partagé(e) / sans préférence marquée | O66: Cela m’attire | P66: Cela m’attire beaucoup | Q66: 1 | R66: 2 | S66: 3 | T66: 4 | U66: 5 | V66: La formulation cible l’intérêt pour aider, développer, soutenir ou servir autrui. Elle mobilise un comportement caractéristique de la dimension S (Social) sans demander un niveau de compétence préalable. | W66: L’item relève de S1 — Enseigner / transmettre : Faire apprendre, expliquer et développer des connaissances ou savoir-faire chez autrui. | X66: Revue méthodologique V0.3 : surveiller désirabilité sociale, stéréotypes de genre historiques liés au soin/service au pilote. | Y66: MOYEN | Z66: FAIBLE | AA66: FAIBLE | AB66: FAIBLE | AC66: FAIBLE | AD66: FAIBLE | AE66: FAIBLE | AF66: FAIBLE | AG66: FAIBLE | AH66: MOYEN | AI66: FAIBLE | AJ66: 0 | AL66: RETENU_V0.5_REECRIT_CONCRET | AN66: PIP-BANK-0.3 | AO66: PIP-BANK-0.4 | AP66: =IF(OR(C66="PILOTE",C66="ACTIF"),IF(AND(A66<>"",H66<>"",I66<>"",K66<>"",V66<>"",W66<>""),"OK","A_COMPLETER"),"OK_STRUCTURE")
A67: PIP-SIT-S-S1-003 | B67: 0.2 | C67: PILOTE | D67: 08/09/2026 | E67: 08/09/2026 | F67: SIT | G67: Situation courte avec enjeu central | H67: S | I67: S1 | J67: I | K67: Adapter sa manière d’expliquer lorsqu’une personne ne comprend pas du premier coup. | L67: Cela ne m’attire pas du tout | M67: Cela m’attire peu | N67: Je suis partagé(e) / sans préférence marquée | O67: Cela m’attire | P67: Cela m’attire beaucoup | Q67: 1 | R67: 2 | S67: 3 | T67: 4 | U67: 5 | V67: La formulation cible l’intérêt pour aider, développer, soutenir ou servir autrui. Elle mobilise un comportement caractéristique de la dimension S (Social) sans demander un niveau de compétence préalable. | W67: L’item relève de S1 — Enseigner / transmettre : Faire apprendre, expliquer et développer des connaissances ou savoir-faire chez autrui. | X67: Revue méthodologique V0.3 : surveiller désirabilité sociale, stéréotypes de genre historiques liés au soin/service au pilote. | Y67: MOYEN | Z67: FAIBLE | AA67: FAIBLE | AB67: FAIBLE | AC67: FAIBLE | AD67: FAIBLE | AE67: FAIBLE | AF67: FAIBLE | AG67: FAIBLE | AH67: MOYEN | AI67: FAIBLE | AJ67: 0 | AL67: RETENU_V0.5_REECRIT_CONCRET | AN67: PIP-BANK-0.3 | AO67: PIP-BANK-0.4 | AP67: =IF(OR(C67="PILOTE",C67="ACTIF"),IF(AND(A67<>"",H67<>"",I67<>"",K67<>"",V67<>"",W67<>""),"OK","A_COMPLETER"),"OK_STRUCTURE")
A68: PIP-ENV-S-S1-004 | B68: 0.2 | C68: PILOTE | D68: 08/09/2026 | E68: 08/09/2026 | F68: ENV | G68: Contexte décrit par ce qu’il permet de faire | H68: S | I68: S1 | J68: I | K68: Travailler dans un contexte où l’on aide régulièrement d’autres personnes à apprendre ou à progresser. | L68: Cela ne m’attire pas du tout | M68: Cela m’attire peu | N68: Je suis partagé(e) / sans préférence marquée | O68: Cela m’attire | P68: Cela m’attire beaucoup | Q68: 1 | R68: 2 | S68: 3 | T68: 4 | U68: 5 | V68: La formulation cible l’intérêt pour aider, développer, soutenir ou servir autrui. Elle mobilise un comportement caractéristique de la dimension S (Social) sans demander un niveau de compétence préalable. | W68: L’item relève de S1 — Enseigner / transmettre : Faire apprendre, expliquer et développer des connaissances ou savoir-faire chez autrui. | X68: Revue méthodologique V0.3 : surveiller désirabilité sociale, stéréotypes de genre historiques liés au soin/service au pilote. | Y68: MOYEN | Z68: FAIBLE | AA68: FAIBLE | AB68: FAIBLE | AC68: FAIBLE | AD68: FAIBLE | AE68: FAIBLE | AF68: FAIBLE | AG68: FAIBLE | AH68: MOYEN | AI68: FAIBLE | AJ68: 0 | AL68: RETIRE_BANQUE72_HISTORIQUE_CONSERVE | AM68: Réduction méthodologique 120→72 : doublon de facette / priorité aux activités professionnelles observables et aux items à plus faible risque. | AN68: PIP-BANK-0.3 | AO68: PIP-BANK-0.3 | AP68: =IF(OR(C68="PILOTE",C68="ACTIF"),IF(AND(A68<>"",H68<>"",I68<>"",K68<>"",V68<>"",W68<>""),"OK","A_COMPLETER"),"OK_STRUCTURE")
A69: PIP-ACT-S-S2-005 | B69: 0.2 | C69: PILOTE | D69: 08/09/2026 | E69: 08/09/2026 | F69: ACT | G69: Verbe d’action + objet/contexte | H69: S | I69: S2 | J69: E | K69: Accompagner une personne dans la réalisation d’un objectif qui compte pour elle. | L69: Cela ne m’attire pas du tout | M69: Cela m’attire peu | N69: Je suis partagé(e) / sans préférence marquée | O69: Cela m’attire | P69: Cela m’attire beaucoup | Q69: 1 | R69: 2 | S69: 3 | T69: 4 | U69: 5 | V69: La formulation cible l’intérêt pour aider, développer, soutenir ou servir autrui. Elle mobilise un comportement caractéristique de la dimension S (Social) sans demander un niveau de compétence préalable. | W69: L’item relève de S2 — Aider / soutenir / accompagner : Soutenir une personne face à une difficulté, un changement ou un objectif. | X69: Revue méthodologique V0.3 : surveiller désirabilité sociale, stéréotypes de genre historiques liés au soin/service au pilote. | Y69: MOYEN | Z69: FAIBLE | AA69: FAIBLE | AB69: FAIBLE | AC69: FAIBLE | AD69: FAIBLE | AE69: FAIBLE | AF69: FAIBLE | AG69: FAIBLE | AH69: MOYEN | AI69: FAIBLE | AJ69: 0 | AL69: RETENU_V0.5_REECRIT_CONCRET | AN69: PIP-BANK-0.3 | AO69: PIP-BANK-0.4 | AP69: =IF(OR(C69="PILOTE",C69="ACTIF"),IF(AND(A69<>"",H69<>"",I69<>"",K69<>"",V69<>"",W69<>""),"OK","A_COMPLETER"),"OK_STRUCTURE")
A70: PIP-ACT-S-S2-006 | B70: 0.2 | C70: PILOTE | D70: 08/09/2026 | E70: 08/09/2026 | F70: ACT | G70: Verbe d’action + objet/contexte | H70: S | I70: S2 | J70: E | K70: Soutenir quelqu’un qui rencontre une difficulté dans son parcours. | L70: Cela ne m’attire pas du tout | M70: Cela m’attire peu | N70: Je suis partagé(e) / sans préférence marquée | O70: Cela m’attire | P70: Cela m’attire beaucoup | Q70: 1 | R70: 2 | S70: 3 | T70: 4 | U70: 5 | V70: La formulation cible l’intérêt pour aider, développer, soutenir ou servir autrui. Elle mobilise un comportement caractéristique de la dimension S (Social) sans demander un niveau de compétence préalable. | W70: L’item relève de S2 — Aider / soutenir / accompagner : Soutenir une personne face à une difficulté, un changement ou un objectif. | X70: Revue méthodologique V0.3 : surveiller désirabilité sociale, stéréotypes de genre historiques liés au soin/service au pilote. | Y70: MOYEN | Z70: FAIBLE | AA70: FAIBLE | AB70: FAIBLE | AC70: FAIBLE | AD70: FAIBLE | AE70: FAIBLE | AF70: FAIBLE | AG70: FAIBLE | AH70: MOYEN | AI70: FAIBLE | AJ70: 0 | AL70: RETENU_V0.5_REECRIT_CONCRET | AN70: PIP-BANK-0.3 | AO70: PIP-BANK-0.4 | AP70: =IF(OR(C70="PILOTE",C70="ACTIF"),IF(AND(A70<>"",H70<>"",I70<>"",K70<>"",V70<>"",W70<>""),"OK","A_COMPLETER"),"OK_STRUCTURE")
A71: PIP-SIT-S-S2-007 | B71: 0.2 | C71: PILOTE | D71: 08/09/2026 | E71: 08/09/2026 | F71: SIT | G71: Situation courte avec enjeu central | H71: S | I71: S2 | J71: E | K71: Être aux côtés d’une personne pendant une période de changement et l’aider à avancer. | L71: Cela ne m’attire pas du tout | M71: Cela m’attire peu | N71: Je suis partagé(e) / sans préférence marquée | O71: Cela m’attire | P71: Cela m’attire beaucoup | Q71: 1 | R71: 2 | S71: 3 | T71: 4 | U71: 5 | V71: La formulation cible l’intérêt pour aider, développer, soutenir ou servir autrui. Elle mobilise un comportement caractéristique de la dimension S (Social) sans demander un niveau de compétence préalable. | W71: L’item relève de S2 — Aider / soutenir / accompagner : Soutenir une personne face à une difficulté, un changement ou un objectif. | X71: Revue méthodologique V0.3 : surveiller désirabilité sociale, stéréotypes de genre historiques liés au soin/service au pilote. | Y71: MOYEN | Z71: FAIBLE | AA71: FAIBLE | AB71: FAIBLE | AC71: FAIBLE | AD71: FAIBLE | AE71: FAIBLE | AF71: FAIBLE | AG71: FAIBLE | AH71: MOYEN | AI71: FAIBLE | AJ71: 0 | AL71: RETENU_V0.5_REECRIT_CONCRET | AN71: PIP-BANK-0.3 | AO71: PIP-BANK-0.4 | AP71: =IF(OR(C71="PILOTE",C71="ACTIF"),IF(AND(A71<>"",H71<>"",I71<>"",K71<>"",V71<>"",W71<>""),"OK","A_COMPLETER"),"OK_STRUCTURE")
A72: PIP-ENV-S-S2-008 | B72: 0.2 | C72: PILOTE | D72: 08/09/2026 | E72: 08/09/2026 | F72: ENV | G72: Contexte décrit par ce qu’il permet de faire | H72: S | I72: S2 | J72: E | K72: Évoluer dans un contexte où une part importante du travail consiste à soutenir directement des personnes dans leur progression. | L72: Cela ne m’attire pas du tout | M72: Cela m’attire peu | N72: Je suis partagé(e) / sans préférence marquée | O72: Cela m’attire | P72: Cela m’attire beaucoup | Q72: 1 | R72: 2 | S72: 3 | T72: 4 | U72: 5 | V72: La formulation cible l’intérêt pour aider, développer, soutenir ou servir autrui. Elle mobilise un comportement caractéristique de la dimension S (Social) sans demander un niveau de compétence préalable. | W72: L’item relève de S2 — Aider / soutenir / accompagner : Soutenir une personne face à une difficulté, un changement ou un objectif. | X72: Revue méthodologique V0.3 : surveiller désirabilité sociale, stéréotypes de genre historiques liés au soin/service au pilote. | Y72: MOYEN | Z72: FAIBLE | AA72: FAIBLE | AB72: FAIBLE | AC72: FAIBLE | AD72: FAIBLE | AE72: FAIBLE | AF72: FAIBLE | AG72: FAIBLE | AH72: MOYEN | AI72: FAIBLE | AJ72: 0 | AL72: RETIRE_BANQUE72_HISTORIQUE_CONSERVE | AM72: Réduction méthodologique 120→72 : doublon de facette / priorité aux activités professionnelles observables et aux items à plus faible risque. | AN72: PIP-BANK-0.3 | AO72: PIP-BANK-0.3 | AP72: =IF(OR(C72="PILOTE",C72="ACTIF"),IF(AND(A72<>"",H72<>"",I72<>"",K72<>"",V72<>"",W72<>""),"OK","A_COMPLETER"),"OK_STRUCTURE")
A73: PIP-ACT-S-S3-009 | B73: 0.2 | C73: PILOTE | D73: 08/09/2026 | E73: 08/09/2026 | F73: ACT | G73: Verbe d’action + objet/contexte | H73: S | I73: S3 | J73: E,I | K73: Écouter la situation d’une personne puis l’aider à identifier les options qui s’offrent à elle. | L73: Cela ne m’attire pas du tout | M73: Cela m’attire peu | N73: Je suis partagé(e) / sans préférence marquée | O73: Cela m’attire | P73: Cela m’attire beaucoup | Q73: 1 | R73: 2 | S73: 3 | T73: 4 | U73: 5 | V73: La formulation cible l’intérêt pour aider, développer, soutenir ou servir autrui. Elle mobilise un comportement caractéristique de la dimension S (Social) sans demander un niveau de compétence préalable. | W73: L’item relève de S3 — Conseiller / guider / orienter : Aider une personne à comprendre ses options ou avancer dans une décision. | X73: Revue méthodologique V0.3 : surveiller désirabilité sociale, frontière avec I, stéréotypes de genre historiques liés au soin/service au pilote. | Y73: MOYEN | Z73: FAIBLE | AA73: FAIBLE | AB73: FAIBLE | AC73: FAIBLE | AD73: FAIBLE | AE73: FAIBLE | AF73: FAIBLE | AG73: FAIBLE | AH73: MOYEN | AI73: MOYEN | AJ73: 0 | AL73: RETENU_V0.5_REECRIT_CONCRET | AN73: PIP-BANK-0.3 | AO73: PIP-BANK-0.4 | AP73: =IF(OR(C73="PILOTE",C73="ACTIF"),IF(AND(A73<>"",H73<>"",I73<>"",K73<>"",V73<>"",W73<>""),"OK","A_COMPLETER"),"OK_STRUCTURE")
A74: PIP-ACT-S-S3-010 | B74: 0.2 | C74: PILOTE | D74: 08/09/2026 | E74: 08/09/2026 | F74: ACT | G74: Verbe d’action + objet/contexte | H74: S | I74: S3 | J74: E,I | K74: Donner des informations utiles pour aider quelqu’un à faire un choix. | L74: Cela ne m’attire pas du tout | M74: Cela m’attire peu | N74: Je suis partagé(e) / sans préférence marquée | O74: Cela m’attire | P74: Cela m’attire beaucoup | Q74: 1 | R74: 2 | S74: 3 | T74: 4 | U74: 5 | V74: La formulation cible l’intérêt pour aider, développer, soutenir ou servir autrui. Elle mobilise un comportement caractéristique de la dimension S (Social) sans demander un niveau de compétence préalable. | W74: L’item relève de S3 — Conseiller / guider / orienter : Aider une personne à comprendre ses options ou avancer dans une décision. | X74: Revue méthodologique V0.3 : surveiller désirabilité sociale, stéréotypes de genre historiques liés au soin/service au pilote. | Y74: MOYEN | Z74: FAIBLE | AA74: FAIBLE | AB74: FAIBLE | AC74: FAIBLE | AD74: FAIBLE | AE74: FAIBLE | AF74: FAIBLE | AG74: FAIBLE | AH74: MOYEN | AI74: FAIBLE | AJ74: 0 | AL74: RETENU_V0.5_REECRIT_CONCRET | AN74: PIP-BANK-0.3 | AO74: PIP-BANK-0.4 | AP74: =IF(OR(C74="PILOTE",C74="ACTIF"),IF(AND(A74<>"",H74<>"",I74<>"",K74<>"",V74<>"",W74<>""),"OK","A_COMPLETER"),"OK_STRUCTURE")
A75: PIP-SIT-S-S3-011 | B75: 0.2 | C75: PILOTE | D75: 08/09/2026 | E75: 08/09/2026 | F75: SIT | G75: Situation courte avec enjeu central | H75: S | I75: S3 | J75: E,I | K75: Aider une personne indécise à clarifier ce qui lui conviendrait le mieux sans décider à sa place. | L75: Cela ne m’attire pas du tout | M75: Cela m’attire peu | N75: Je suis partagé(e) / sans préférence marquée | O75: Cela m’attire | P75: Cela m’attire beaucoup | Q75: 1 | R75: 2 | S75: 3 | T75: 4 | U75: 5 | V75: La formulation cible l’intérêt pour aider, développer, soutenir ou servir autrui. Elle mobilise un comportement caractéristique de la dimension S (Social) sans demander un niveau de compétence préalable. | W75: L’item relève de S3 — Conseiller / guider / orienter : Aider une personne à comprendre ses options ou avancer dans une décision. | X75: Revue méthodologique V0.3 : surveiller désirabilité sociale, frontière avec E, stéréotypes de genre historiques liés au soin/service au pilote. | Y75: MOYEN | Z75: FAIBLE | AA75: FAIBLE | AB75: FAIBLE | AC75: FAIBLE | AD75: FAIBLE | AE75: FAIBLE | AF75: FAIBLE | AG75: FAIBLE | AH75: MOYEN | AI75: MOYEN | AJ75: 0 | AL75: RETIRE_BANQUE72_HISTORIQUE_CONSERVE | AM75: Réduction méthodologique 120→72 : doublon de facette / priorité aux activités professionnelles observables et aux items à plus faible risque. | AN75: PIP-BANK-0.3 | AO75: PIP-BANK-0.3 | AP75: =IF(OR(C75="PILOTE",C75="ACTIF"),IF(AND(A75<>"",H75<>"",I75<>"",K75<>"",V75<>"",W75<>""),"OK","A_COMPLETER"),"OK_STRUCTURE")
A76: PIP-ENV-S-S3-012 | B76: 0.2 | C76: PILOTE | D76: 08/09/2026 | E76: 08/09/2026 | F76: ENV | G76: Contexte décrit par ce qu’il permet de faire | H76: S | I76: S3 | J76: E,I | K76: Travailler dans un contexte où l’on conseille et oriente régulièrement des personnes en fonction de leur situation. | L76: Cela ne m’attire pas du tout | M76: Cela m’attire peu | N76: Je suis partagé(e) / sans préférence marquée | O76: Cela m’attire | P76: Cela m’attire beaucoup | Q76: 1 | R76: 2 | S76: 3 | T76: 4 | U76: 5 | V76: La formulation cible l’intérêt pour aider, développer, soutenir ou servir autrui. Elle mobilise un comportement caractéristique de la dimension S (Social) sans demander un niveau de compétence préalable. | W76: L’item relève de S3 — Conseiller / guider / orienter : Aider une personne à comprendre ses options ou avancer dans une décision. | X76: Revue méthodologique V0.3 : surveiller désirabilité sociale, stéréotypes de genre historiques liés au soin/service au pilote. | Y76: MOYEN | Z76: FAIBLE | AA76: FAIBLE | AB76: FAIBLE | AC76: FAIBLE | AD76: FAIBLE | AE76: FAIBLE | AF76: FAIBLE | AG76: FAIBLE | AH76: MOYEN | AI76: FAIBLE | AJ76: 0 | AL76: RETIRE_BANQUE72_HISTORIQUE_CONSERVE | AM76: Réduction méthodologique 120→72 : doublon de facette / priorité aux activités professionnelles observables et aux items à plus faible risque. | AN76: PIP-BANK-0.3 | AO76: PIP-BANK-0.3 | AP76: =IF(OR(C76="PILOTE",C76="ACTIF"),IF(AND(A76<>"",H76<>"",I76<>"",K76<>"",V76<>"",W76<>""),"OK","A_COMPLETER"),"OK_STRUCTURE")
A77: PIP-ACT-S-S4-013 | B77: 0.2 | C77: PILOTE | D77: 08/09/2026 | E77: 08/09/2026 | F77: ACT | G77: Verbe d’action + objet/contexte | H77: S | I77: S4 | J77: R,I | K77: Prendre soin d’une personne qui a besoin d’aide pour préserver ou retrouver son bien-être. | L77: Cela ne m’attire pas du tout | M77: Cela m’attire peu | N77: Je suis partagé(e) / sans préférence marquée | O77: Cela m’attire | P77: Cela m’attire beaucoup | Q77: 1 | R77: 2 | S77: 3 | T77: 4 | U77: 5 | V77: La formulation cible l’intérêt pour aider, développer, soutenir ou servir autrui. Elle mobilise un comportement caractéristique de la dimension S (Social) sans demander un niveau de compétence préalable. | W77: L’item relève de S4 — Soigner / prendre soin : Contribuer directement à la santé, au bien-être, à la sécurité ou au rétablissement d’une personne. | X77: Revue méthodologique V0.3 : surveiller projection en cas de limitation physique ou sensorielle, désirabilité sociale, stéréotypes de genre historiques liés au soin/service au pilote. | Y77: MOYEN | Z77: FAIBLE | AA77: FAIBLE | AB77: FAIBLE | AC77: FAIBLE | AD77: MOYEN | AE77: FAIBLE | AF77: FAIBLE | AG77: FAIBLE | AH77: MOYEN | AI77: FAIBLE | AJ77: 0 | AL77: RETENU_V0.5_REECRIT_CONCRET | AN77: PIP-BANK-0.3 | AO77: PIP-BANK-0.4 | AP77: =IF(OR(C77="PILOTE",C77="ACTIF"),IF(AND(A77<>"",H77<>"",I77<>"",K77<>"",V77<>"",W77<>""),"OK","A_COMPLETER"),"OK_STRUCTURE")
A78: PIP-ACT-S-S4-014 | B78: 0.2 | C78: PILOTE | D78: 08/09/2026 | E78: 08/09/2026 | F78: ACT | G78: Verbe d’action + objet/contexte | H78: S | I78: S4 | J78: R,I | K78: Réaliser des gestes d’assistance destinés à protéger la santé ou la sécurité d’une personne. | L78: Cela ne m’attire pas du tout | M78: Cela m’attire peu | N78: Je suis partagé(e) / sans préférence marquée | O78: Cela m’attire | P78: Cela m’attire beaucoup | Q78: 1 | R78: 2 | S78: 3 | T78: 4 | U78: 5 | V78: La formulation cible l’intérêt pour aider, développer, soutenir ou servir autrui. Elle mobilise un comportement caractéristique de la dimension S (Social) sans demander un niveau de compétence préalable. | W78: L’item relève de S4 — Soigner / prendre soin : Contribuer directement à la santé, au bien-être, à la sécurité ou au rétablissement d’une personne. | X78: Revue méthodologique V0.3 : surveiller projection en cas de limitation physique ou sensorielle, familiarité avec le contexte professionnel, désirabilité sociale, stéréotypes de genre historiques liés au soin/service au pilote. | Y78: MOYEN | Z78: FAIBLE | AA78: FAIBLE | AB78: FAIBLE | AC78: FAIBLE | AD78: MOYEN | AE78: FAIBLE | AF78: FAIBLE | AG78: MOYEN | AH78: MOYEN | AI78: FAIBLE | AJ78: 0 | AL78: RETENU_V0.5_REECRIT_CONCRET | AN78: PIP-BANK-0.3 | AO78: PIP-BANK-0.4 | AP78: =IF(OR(C78="PILOTE",C78="ACTIF"),IF(AND(A78<>"",H78<>"",I78<>"",K78<>"",V78<>"",W78<>""),"OK","A_COMPLETER"),"OK_STRUCTURE")
A79: PIP-SIT-S-S4-015 | B79: 0.2 | C79: PILOTE | D79: 08/09/2026 | E79: 08/09/2026 | F79: SIT | G79: Situation courte avec enjeu central | H79: S | I79: S4 | J79: R,I | K79: Intervenir auprès d’une personne fragilisée afin de l’aider à retrouver davantage d’autonomie. | L79: Cela ne m’attire pas du tout | M79: Cela m’attire peu | N79: Je suis partagé(e) / sans préférence marquée | O79: Cela m’attire | P79: Cela m’attire beaucoup | Q79: 1 | R79: 2 | S79: 3 | T79: 4 | U79: 5 | V79: La formulation cible l’intérêt pour aider, développer, soutenir ou servir autrui. Elle mobilise un comportement caractéristique de la dimension S (Social) sans demander un niveau de compétence préalable. | W79: L’item relève de S4 — Soigner / prendre soin : Contribuer directement à la santé, au bien-être, à la sécurité ou au rétablissement d’une personne. | X79: Revue méthodologique V0.3 : surveiller projection en cas de limitation physique ou sensorielle, désirabilité sociale, stéréotypes de genre historiques liés au soin/service au pilote. | Y79: MOYEN | Z79: FAIBLE | AA79: FAIBLE | AB79: FAIBLE | AC79: FAIBLE | AD79: MOYEN | AE79: FAIBLE | AF79: FAIBLE | AG79: FAIBLE | AH79: MOYEN | AI79: FAIBLE | AJ79: 0 | AL79: RETIRE_BANQUE72_HISTORIQUE_CONSERVE | AM79: Réduction méthodologique 120→72 : doublon de facette / priorité aux activités professionnelles observables et aux items à plus faible risque. | AN79: PIP-BANK-0.3 | AO79: PIP-BANK-0.3 | AP79: =IF(OR(C79="PILOTE",C79="ACTIF"),IF(AND(A79<>"",H79<>"",I79<>"",K79<>"",V79<>"",W79<>""),"OK","A_COMPLETER"),"OK_STRUCTURE")
A80: PIP-ENV-S-S4-016 | B80: 0.2 | C80: PILOTE | D80: 08/09/2026 | E80: 08/09/2026 | F80: ENV | G80: Contexte décrit par ce qu’il permet de faire | H80: S | I80: S4 | J80: R,I | K80: Évoluer dans un contexte où l’on contribue directement à la santé, au bien-être ou à la sécurité des personnes. | L80: Cela ne m’attire pas du tout | M80: Cela m’attire peu | N80: Je suis partagé(e) / sans préférence marquée | O80: Cela m’attire | P80: Cela m’attire beaucoup | Q80: 1 | R80: 2 | S80: 3 | T80: 4 | U80: 5 | V80: La formulation cible l’intérêt pour aider, développer, soutenir ou servir autrui. Elle mobilise un comportement caractéristique de la dimension S (Social) sans demander un niveau de compétence préalable. | W80: L’item relève de S4 — Soigner / prendre soin : Contribuer directement à la santé, au bien-être, à la sécurité ou au rétablissement d’une personne. | X80: Revue méthodologique V0.3 : surveiller projection en cas de limitation physique ou sensorielle, familiarité avec le contexte professionnel, désirabilité sociale, stéréotypes de genre historiques liés au soin/service au pilote. | Y80: MOYEN | Z80: FAIBLE | AA80: FAIBLE | AB80: FAIBLE | AC80: FAIBLE | AD80: MOYEN | AE80: FAIBLE | AF80: FAIBLE | AG80: MOYEN | AH80: MOYEN | AI80: FAIBLE | AJ80: 0 | AL80: RETIRE_BANQUE72_HISTORIQUE_CONSERVE | AM80: Réduction méthodologique 120→72 : doublon de facette / priorité aux activités professionnelles observables et aux items à plus faible risque. | AN80: PIP-BANK-0.3 | AO80: PIP-BANK-0.3 | AP80: =IF(OR(C80="PILOTE",C80="ACTIF"),IF(AND(A80<>"",H80<>"",I80<>"",K80<>"",V80<>"",W80<>""),"OK","A_COMPLETER"),"OK_STRUCTURE")
A81: PIP-ACT-S-S5-017 | B81: 0.2 | C81: PILOTE | D81: 08/09/2026 | E81: 08/09/2026 | F81: ACT | G81: Verbe d’action + objet/contexte | H81: S | I81: S5 | J81: E,C | K81: Accueillir une personne et l’aider à obtenir le service dont elle a besoin. | L81: Cela ne m’attire pas du tout | M81: Cela m’attire peu | N81: Je suis partagé(e) / sans préférence marquée | O81: Cela m’attire | P81: Cela m’attire beaucoup | Q81: 1 | R81: 2 | S81: 3 | T81: 4 | U81: 5 | V81: La formulation cible l’intérêt pour aider, développer, soutenir ou servir autrui. Elle mobilise un comportement caractéristique de la dimension S (Social) sans demander un niveau de compétence préalable. | W81: L’item relève de S5 — Servir / assister directement : Rendre un service concret ou personnalisé répondant à un besoin d’autrui. | X81: Revue méthodologique V0.3 : surveiller désirabilité sociale, stéréotypes de genre historiques liés au soin/service au pilote. | Y81: MOYEN | Z81: FAIBLE | AA81: FAIBLE | AB81: FAIBLE | AC81: FAIBLE | AD81: FAIBLE | AE81: FAIBLE | AF81: FAIBLE | AG81: FAIBLE | AH81: MOYEN | AI81: FAIBLE | AJ81: 0 | AL81: RETENU_V0.5_REECRIT_CONCRET | AN81: PIP-BANK-0.3 | AO81: PIP-BANK-0.4 | AP81: =IF(OR(C81="PILOTE",C81="ACTIF"),IF(AND(A81<>"",H81<>"",I81<>"",K81<>"",V81<>"",W81<>""),"OK","A_COMPLETER"),"OK_STRUCTURE")
A82: PIP-ACT-S-S5-018 | B82: 0.2 | C82: PILOTE | D82: 08/09/2026 | E82: 08/09/2026 | F82: ACT | G82: Verbe d’action + objet/contexte | H82: S | I82: S5 | J82: E,C | K82: Répondre concrètement à une demande afin de faciliter la démarche d’une personne. | L82: Cela ne m’attire pas du tout | M82: Cela m’attire peu | N82: Je suis partagé(e) / sans préférence marquée | O82: Cela m’attire | P82: Cela m’attire beaucoup | Q82: 1 | R82: 2 | S82: 3 | T82: 4 | U82: 5 | V82: La formulation cible l’intérêt pour aider, développer, soutenir ou servir autrui. Elle mobilise un comportement caractéristique de la dimension S (Social) sans demander un niveau de compétence préalable. | W82: L’item relève de S5 — Servir / assister directement : Rendre un service concret ou personnalisé répondant à un besoin d’autrui. | X82: Revue méthodologique V0.3 : surveiller désirabilité sociale, stéréotypes de genre historiques liés au soin/service au pilote. | Y82: MOYEN | Z82: FAIBLE | AA82: FAIBLE | AB82: FAIBLE | AC82: FAIBLE | AD82: FAIBLE | AE82: FAIBLE | AF82: FAIBLE | AG82: FAIBLE | AH82: MOYEN | AI82: FAIBLE | AJ82: 0 | AL82: RETENU_V0.5_REECRIT_CONCRET | AN82: PIP-BANK-0.3 | AO82: PIP-BANK-0.4 | AP82: =IF(OR(C82="PILOTE",C82="ACTIF"),IF(AND(A82<>"",H82<>"",I82<>"",K82<>"",V82<>"",W82<>""),"OK","A_COMPLETER"),"OK_STRUCTURE")
A83: PIP-SIT-S-S5-019 | B83: 0.2 | C83: PILOTE | D83: 08/09/2026 | E83: 08/09/2026 | F83: SIT | G83: Situation courte avec enjeu central | H83: S | I83: S5 | J83: E,C | K83: Aider un usager ou un client qui ne sait pas comment accomplir une démarche. | L83: Cela ne m’attire pas du tout | M83: Cela m’attire peu | N83: Je suis partagé(e) / sans préférence marquée | O83: Cela m’attire | P83: Cela m’attire beaucoup | Q83: 1 | R83: 2 | S83: 3 | T83: 4 | U83: 5 | V83: La formulation cible l’intérêt pour aider, développer, soutenir ou servir autrui. Elle mobilise un comportement caractéristique de la dimension S (Social) sans demander un niveau de compétence préalable. | W83: L’item relève de S5 — Servir / assister directement : Rendre un service concret ou personnalisé répondant à un besoin d’autrui. | X83: Revue méthodologique V0.3 : surveiller familiarité avec le contexte professionnel, désirabilité sociale, stéréotypes de genre historiques liés au soin/service au pilote. | Y83: MOYEN | Z83: FAIBLE | AA83: FAIBLE | AB83: FAIBLE | AC83: FAIBLE | AD83: FAIBLE | AE83: FAIBLE | AF83: FAIBLE | AG83: MOYEN | AH83: MOYEN | AI83: FAIBLE | AJ83: 0 | AL83: RETIRE_BANQUE72_HISTORIQUE_CONSERVE | AM83: Réduction méthodologique 120→72 : doublon de facette / priorité aux activités professionnelles observables et aux items à plus faible risque. | AN83: PIP-BANK-0.3 | AO83: PIP-BANK-0.3 | AP83: =IF(OR(C83="PILOTE",C83="ACTIF"),IF(AND(A83<>"",H83<>"",I83<>"",K83<>"",V83<>"",W83<>""),"OK","A_COMPLETER"),"OK_STRUCTURE")
A84: PIP-ENV-S-S5-020 | B84: 0.2 | C84: PILOTE | D84: 08/09/2026 | E84: 08/09/2026 | F84: ENV | G84: Contexte décrit par ce qu’il permet de faire | H84: S | I84: S5 | J84: E,C | K84: Travailler dans un contexte où l’on rend directement des services utiles à des personnes aux besoins variés. | L84: Cela ne m’attire pas du tout | M84: Cela m’attire peu | N84: Je suis partagé(e) / sans préférence marquée | O84: Cela m’attire | P84: Cela m’attire beaucoup | Q84: 1 | R84: 2 | S84: 3 | T84: 4 | U84: 5 | V84: La formulation cible l’intérêt pour aider, développer, soutenir ou servir autrui. Elle mobilise un comportement caractéristique de la dimension S (Social) sans demander un niveau de compétence préalable. | W84: L’item relève de S5 — Servir / assister directement : Rendre un service concret ou personnalisé répondant à un besoin d’autrui. | X84: Revue méthodologique V0.3 : surveiller désirabilité sociale, stéréotypes de genre historiques liés au soin/service au pilote. | Y84: MOYEN | Z84: FAIBLE | AA84: FAIBLE | AB84: FAIBLE | AC84: FAIBLE | AD84: FAIBLE | AE84: FAIBLE | AF84: FAIBLE | AG84: FAIBLE | AH84: MOYEN | AI84: FAIBLE | AJ84: 0 | AL84: RETIRE_BANQUE72_HISTORIQUE_CONSERVE | AM84: Réduction méthodologique 120→72 : doublon de facette / priorité aux activités professionnelles observables et aux items à plus faible risque. | AN84: PIP-BANK-0.3 | AO84: PIP-BANK-0.3 | AP84: =IF(OR(C84="PILOTE",C84="ACTIF"),IF(AND(A84<>"",H84<>"",I84<>"",K84<>"",V84<>"",W84<>""),"OK","A_COMPLETER"),"OK_STRUCTURE")
A85: PIP-ACT-E-E1-001 | B85: 0.2 | C85: PILOTE | D85: 08/09/2026 | E85: 08/09/2026 | F85: ACT | G85: Verbe d’action + objet/contexte | H85: E | I85: E1 | J85: A | K85: Lancer un nouveau projet à partir d’une idée ou d’une opportunité. | L85: Cela ne m’attire pas du tout | M85: Cela m’attire peu | N85: Je suis partagé(e) / sans préférence marquée | O85: Cela m’attire | P85: Cela m’attire beaucoup | Q85: 1 | R85: 2 | S85: 3 | T85: 4 | U85: 5 | V85: La formulation cible l’intérêt pour initier, influencer, décider et faire avancer. Elle mobilise un comportement caractéristique de la dimension E (Entreprenant) sans demander un niveau de compétence préalable. | W85: L’item relève de E1 — Initier / entreprendre / développer : Lancer, faire croître ou transformer une activité, un projet ou une opportunité. | X85: Revue méthodologique V0.3 : surveiller compréhension du vocabulaire, désirabilité sociale, effet de prestige/statut au pilote. | Y85: FAIBLE | Z85: FAIBLE | AA85: FAIBLE | AB85: FAIBLE | AC85: MOYEN | AD85: FAIBLE | AE85: FAIBLE | AF85: MOYEN | AG85: FAIBLE | AH85: MOYEN | AI85: FAIBLE | AJ85: 0 | AL85: RETENU_V0.5_REECRIT_CONCRET | AN85: PIP-BANK-0.3 | AO85: PIP-BANK-0.4 | AP85: =IF(OR(C85="PILOTE",C85="ACTIF"),IF(AND(A85<>"",H85<>"",I85<>"",K85<>"",V85<>"",W85<>""),"OK","A_COMPLETER"),"OK_STRUCTURE")
A86: PIP-ACT-E-E1-002 | B86: 0.2 | C86: PILOTE | D86: 08/09/2026 | E86: 08/09/2026 | F86: ACT | G86: Verbe d’action + objet/contexte | H86: E | I86: E1 | J86: A | K86: Faire progresser un projet en identifiant de nouvelles possibilités de développement. | L86: Cela ne m’attire pas du tout | M86: Cela m’attire peu | N86: Je suis partagé(e) / sans préférence marquée | O86: Cela m’attire | P86: Cela m’attire beaucoup | Q86: 1 | R86: 2 | S86: 3 | T86: 4 | U86: 5 | V86: La formulation cible l’intérêt pour initier, influencer, décider et faire avancer. Elle mobilise un comportement caractéristique de la dimension E (Entreprenant) sans demander un niveau de compétence préalable. | W86: L’item relève de E1 — Initier / entreprendre / développer : Lancer, faire croître ou transformer une activité, un projet ou une opportunité. | X86: Revue méthodologique V0.3 : surveiller compréhension du vocabulaire, désirabilité sociale, effet de prestige/statut au pilote. | Y86: FAIBLE | Z86: FAIBLE | AA86: FAIBLE | AB86: FAIBLE | AC86: MOYEN | AD86: FAIBLE | AE86: FAIBLE | AF86: MOYEN | AG86: FAIBLE | AH86: MOYEN | AI86: FAIBLE | AJ86: 0 | AL86: RETENU_V0.5_REECRIT_CONCRET | AN86: PIP-BANK-0.3 | AO86: PIP-BANK-0.4 | AP86: =IF(OR(C86="PILOTE",C86="ACTIF"),IF(AND(A86<>"",H86<>"",I86<>"",K86<>"",V86<>"",W86<>""),"OK","A_COMPLETER"),"OK_STRUCTURE")
A87: PIP-SIT-E-E1-003 | B87: 0.2 | C87: PILOTE | D87: 08/09/2026 | E87: 08/09/2026 | F87: SIT | G87: Situation courte avec enjeu central | H87: E | I87: E1 | J87: A | K87: Voir une opportunité et prendre l’initiative de la transformer en projet concret. | L87: Cela ne m’attire pas du tout | M87: Cela m’attire peu | N87: Je suis partagé(e) / sans préférence marquée | O87: Cela m’attire | P87: Cela m’attire beaucoup | Q87: 1 | R87: 2 | S87: 3 | T87: 4 | U87: 5 | V87: La formulation cible l’intérêt pour initier, influencer, décider et faire avancer. Elle mobilise un comportement caractéristique de la dimension E (Entreprenant) sans demander un niveau de compétence préalable. | W87: L’item relève de E1 — Initier / entreprendre / développer : Lancer, faire croître ou transformer une activité, un projet ou une opportunité. | X87: Revue méthodologique V0.3 : surveiller compréhension du vocabulaire, désirabilité sociale, effet de prestige/statut au pilote. | Y87: FAIBLE | Z87: FAIBLE | AA87: FAIBLE | AB87: FAIBLE | AC87: MOYEN | AD87: FAIBLE | AE87: FAIBLE | AF87: MOYEN | AG87: FAIBLE | AH87: MOYEN | AI87: FAIBLE | AJ87: 0 | AL87: RETENU_V0.5_REECRIT_CONCRET | AN87: PIP-BANK-0.3 | AO87: PIP-BANK-0.4 | AP87: =IF(OR(C87="PILOTE",C87="ACTIF"),IF(AND(A87<>"",H87<>"",I87<>"",K87<>"",V87<>"",W87<>""),"OK","A_COMPLETER"),"OK_STRUCTURE")
